Workbook
Name SegmentaçãodeDados_Origem: #N/A
Name SegmentaçãodeDados_País_de_Destino: #N/A

Sheet Comece Aqui
A2: • | B2: Nesse arquivo você encontra 30 exercícios baseados em situações do dia a dia de trabalho e em questões de processos seletivos. Esses exercícios abragem os seguintes módulos do Excel Impressionador:
B4: Conceitos Introdutórios
B5: Atalhos
B6: Formatação
B7: Funções Básicas
B8: Classificar e Filtrar
B9: Ferramentas de Dados
B10: Funções Mercado de Trabalho.
A12: • | B12: Sugiro fortemente que assista todas as aulas dos módulos acima antes de responder as questões a seguir.
A14: • | B14: Você deve responder as questões nas planilhas azuis utilizando as demais planilhas como base de dados. Utilize quaisquer ferramentas aprendidas nos módulos citados anteriormente para responder as questões.
B15: Algumas perguntas podem ser respondidas de mais de uma forma, utilizando fórmulas e ferramentas diferentes do Excel. Sempre que se deparar com uma questão como essa, sugiro que responda a mesma questão de todas as formas que conseguir. Pode parecer estranho responder a mesma questão 2 ou 3 vezes, mas vai ser uma excelente prática para você resolver um problema ou desafio no Excel de diversas maneiras possíveis.
A18: • | B18: Preste atenção nos enunciados. Entendender as questões já faz parte do exercício, da mesma forma que entender as questões em um processo seletivo e as demandas do seu chefe é uma forma de avaliar seu trabalho e conhecimento de Excel.
A20: • | B20: O objetivo desses exercícios é apenas desenvolver seu conhecimento e prática com as ferramentas e fórmulas do Excel aprendidas até agora. Você não receberá uma nota (como se fosse uma prova de colégio) e tampouco o certificado do curso depende dessas questões.
A23: • | B23: Após responder todas as questões, assista as demais aulas desse módulo para acompanhar a correção de cada pergunta.

Sheet Base de Dados
A1: Descrição | B1: Código | C1: Origem | D1: Região | E1: Chave do Produto | F1: Data de Validade | G1: Urgência de Envio de Produtos | H1: Ano | I1: Mês | J1: Custo de Produção | K1: País de Destino | N1: {=_xlfn.UNIQUE(B:B)} -> Código | O1: Repetições | R1: Validação de Dados | U1: Validação de dados
A2: Pacofapipe | B2: H574P162 | C2: ES | D2: =VLOOKUP(Tabela1[[#This Row],[Origem]], 'Perguntas 1 a 24'!$J$28:$K$34, 2, 0) -> Sudeste | E2: =Tabela1[[#This Row],[Descrição]]&"-"&Tabela1[[#This Row],[Código]]&"/"&Tabela1[[#This Row],[Origem]] -> Pacofapipe-H574P162/ES | F2: 45425 | G2: {=_xlfn.IFS(AND(Tabela1[[#This Row],[Data de Validade]]<= DATE(2025, 12, 31), Tabela1[[#This Row],[Custo de Produção]]>50000), "Urgente e Caro", AND(Tabela1[[#This Row],[Data de Validade]]<= DATE(2025, 12, 31), Tabela1[[#This Row],[Custo de Produção]]<= 50000), "Urgente", AND(F2>= DATE(2026,1,1), F2<= DATE(2028, 12, 31), J2>50000), "Pendente e Caro", AND(F2>= DATE(2026,1,1), F2<= DATE(2028, 12, 31), J2<=50000), "Pendente", F2>= DATE(2029,1,1), "Não prioeitário")} -> Urgente e Caro | H2: =YEAR(Tabela1[[#This Row],[Data de Validade]]) -> 2024 | I2: =MONTH(Tabela1[[#This Row],[Data de Validade]]) -> 5 | J2: 111076 | K2: Holanda | N2: H574P162 | O2: =COUNTIFS(B:B,N2) -> 1 | R2: País | S2: Holanda | U2: Somatório | V2: Média | W2: Contagem | X2: Máximo | Y2: Mínimo
A3: Nolifepa | B3: H735H276 | C3: SP | D3: =VLOOKUP(Tabela1[[#This Row],[Origem]], 'Perguntas 1 a 24'!$J$28:$K$34, 2, 0) -> Sudeste | E3: =Tabela1[[#This Row],[Descrição]]&"-"&Tabela1[[#This Row],[Código]]&"/"&Tabela1[[#This Row],[Origem]] -> Nolifepa-H735H276/SP | F3: 45425 | G3: {=_xlfn.IFS(AND(Tabela1[[#This Row],[Data de Validade]]<= DATE(2025, 12, 31), Tabela1[[#This Row],[Custo de Produção]]>50000), "Urgente e Caro", AND(Tabela1[[#This Row],[Data de Validade]]<= DATE(2025, 12, 31), Tabela1[[#This Row],[Custo de Produção]]<= 50000), "Urgente", AND(F3>= DATE(2026,1,1), F3<= DATE(2028, 12, 31), J3>50000), "Pendente e Caro", AND(F3>= DATE(2026,1,1), F3<= DATE(2028, 12, 31), J3<=50000), "Pendente", F3>= DATE(2029,1,1), "Não prioeitário")} -> Urgente e Caro | H3: =YEAR(Tabela1[[#This Row],[Data de Validade]]) -> 2024 | I3: =MONTH(Tabela1[[#This Row],[Data de Validade]]) -> 5 | J3: 107568 | K3: Holanda | N3: H735H276 | O3: =COUNTIFS(B:B,N3) -> 1 | R3: Ano | S3: 2028 | U3: =SUMIFS(J:J, K:K, S2, H:H, S3) -> 9841767 | V3: =AVERAGEIFS(J:J, K:K, S2) -> 69997.152 | W3: =COUNTIFS(K:K, S2) -> 958 | X3: =_xlfn.MAXIFS(J:J, K:K, S2) -> 119595 | Y3: =_xlfn.MINIFS(J:J, K:K, S2) -> 20081
A4: Rapopa | B4: H538H378 | C4: MG | D4: =VLOOKUP(Tabela1[[#This Row],[Origem]], 'Perguntas 1 a 24'!$J$28:$K$34, 2, 0) -> Sudeste | E4: =Tabela1[[#This Row],[Descrição]]&"-"&Tabela1[[#This Row],[Código]]&"/"&Tabela1[[#This Row],[Origem]] -> Rapopa-H538H378/MG | F4: 45425 | G4: {=_xlfn.IFS(AND(Tabela1[[#This Row],[Data de Validade]]<= DATE(2025, 12, 31), Tabela1[[#This Row],[Custo de Produção]]>50000), "Urgente e Caro", AND(Tabela1[[#This Row],[Data de Validade]]<= DATE(2025, 12, 31), Tabela1[[#This Row],[Custo de Produção]]<= 50000), "Urgente", AND(F4>= DATE(2026,1,1), F4<= DATE(2028, 12, 31), J4>50000), "Pendente e Caro", AND(F4>= DATE(2026,1,1), F4<= DATE(2028, 12, 31), J4<=50000), "Pendente", F4>= DATE(2029,1,1), "Não prioeitário")} -> Urgente e Caro | H4: =YEAR(Tabela1[[#This Row],[Data de Validade]]) -> 2024 | I4: =MONTH(Tabela1[[#This Row],[Data de Validade]]) -> 5 | J4: 86399 | K4: Austrália | N4: H538H378 | O4: =COUNTIFS(B:B,N4) -> 1 | R4: Custo de Produção | S4: =SUMIFS(J:J,K:K,S2, H:H, S3) -> 9841767
A5: Godopadu | B5: P116P159 | C5: SP | D5: =VLOOKUP(Tabela1[[#This Row],[Origem]], 'Perguntas 1 a 24'!$J$28:$K$34, 2, 0) -> Sudeste | E5: =Tabela1[[#This Row],[Descrição]]&"-"&Tabela1[[#This Row],[Código]]&"/"&Tabela1[[#This Row],[Origem]] -> Godopadu-P116P159/SP | F5: 45425 | G5: {=_xlfn.IFS(AND(Tabela1[[#This Row],[Data de Validade]]<= DATE(2025, 12, 31), Tabela1[[#This Row],[Custo de Produção]]>50000), "Urgente e Caro", AND(Tabela1[[#This Row],[Data de Validade]]<= DATE(2025, 12, 31), Tabela1[[#This Row],[Custo de Produção]]<= 50000), "Urgente", AND(F5>= DATE(2026,1,1), F5<= DATE(2028, 12, 31), J5>50000), "Pendente e Caro", AND(F5>= DATE(2026,1,1), F5<= DATE(2028, 12, 31), J5<=50000), "Pendente", F5>= DATE(2029,1,1), "Não prioeitário")} -> Urgente e Caro | H5: =YEAR(Tabela1[[#This Row],[Data de Validade]]) -> 2024 | I5: =MONTH(Tabela1[[#This Row],[Data de Validade]]) -> 5 | J5: 80288 | K5: Panamá | N5: P116P159 | O5: =COUNTIFS(B:B,N5) -> 1 | R5: Análise dos dados - Geral
A6: Raliru | B6: H515P175 | C6: ES | D6: =VLOOKUP(Tabela1[[#This Row],[Origem]], 'Perguntas 1 a 24'!$J$28:$K$34, 2, 0) -> Sudeste | E6: =Tabela1[[#This Row],[Descrição]]&"-"&Tabela1[[#This Row],[Código]]&"/"&Tabela1[[#This Row],[Origem]] -> Raliru-H515P175/ES | F6: 45425 | G6: {=_xlfn.IFS(AND(Tabela1[[#This Row],[Data de Validade]]<= DATE(2025, 12, 31), Tabela1[[#This Row],[Custo de Produção]]>50000), "Urgente e Caro", AND(Tabela1[[#This Row],[Data de Validade]]<= DATE(2025, 12, 31), Tabela1[[#This Row],[Custo de Produção]]<= 50000), "Urgente", AND(F6>= DATE(2026,1,1), F6<= DATE(2028, 12, 31), J6>50000), "Pendente e Caro", AND(F6>= DATE(2026,1,1), F6<= DATE(2028, 12, 31), J6<=50000), "Pendente", F6>= DATE(2029,1,1), "Não prioeitário")} -> Urgente e Caro | H6: =YEAR(Tabela1[[#This Row],[Data de Validade]]) -> 2024 | I6: =MONTH(Tabela1[[#This Row],[Data de Validade]]) -> 5 | J6: 80281 | K6: Panamá | N6: H515P175 | O6: =COUNTIFS(B:B,N6) -> 1 | R6: Somatório do Custo | S6: Média de Custo | T6: Contagem de Transações | U6: Valor Máximo de Custo | V6: Valor Mínimo de Custo
A7: Ratena | B7: H917H959 | C7: SP | D7: =VLOOKUP(Tabela1[[#This Row],[Origem]], 'Perguntas 1 a 24'!$J$28:$K$34, 2, 0) -> Sudeste | E7: =Tabela1[[#This Row],[Descrição]]&"-"&Tabela1[[#This Row],[Código]]&"/"&Tabela1[[#This Row],[Origem]] -> Ratena-H917H959/SP | F7: 45425 | G7: {=_xlfn.IFS(AND(Tabela1[[#This Row],[Data de Validade]]<= DATE(2025, 12, 31), Tabela1[[#This Row],[Custo de Produção]]>50000), "Urgente e Caro", AND(Tabela1[[#This Row],[Data de Validade]]<= DATE(2025, 12, 31), Tabela1[[#This Row],[Custo de Produção]]<= 50000), "Urgente", AND(F7>= DATE(2026,1,1), F7<= DATE(2028, 12, 31), J7>50000), "Pendente e Caro", AND(F7>= DATE(2026,1,1), F7<= DATE(2028, 12, 31), J7<=50000), "Pendente", F7>= DATE(2029,1,1), "Não prioeitário")} -> Urgente e Caro | H7: =YEAR(Tabela1[[#This Row],[Data de Validade]]) -> 2024 | I7: =MONTH(Tabela1[[#This Row],[Data de Validade]]) -> 5 | J7: 75598 | K7: Panamá | N7: H917H959 | O7: =COUNTIFS(B:B,N7) -> 1 | R7: =SUM(J:J) -> 272140218 | S7: =AVERAGE(J:J) -> 70594.09 | T7: =COUNT(J:J) -> 3855 | U7: =MAX(Tabela1[Custo de Produção]) -> 119945 | V7: =MIN(Tabela1[Custo de Produção]) -> 20044
A8: Roduma | B8: P363P987 | C8: GO | D8: =VLOOKUP(Tabela1[[#This Row],[Origem]], 'Perguntas 1 a 24'!$J$28:$K$34, 2, 0) -> Centro-Oeste | E8: =Tabela1[[#This Row],[Descrição]]&"-"&Tabela1[[#This Row],[Código]]&"/"&Tabela1[[#This Row],[Origem]] -> Roduma-P363P987/GO | F8: 45425 | G8: {=_xlfn.IFS(AND(Tabela1[[#This Row],[Data de Validade]]<= DATE(2025, 12, 31), Tabela1[[#This Row],[Custo de Produção]]>50000), "Urgente e Caro", AND(Tabela1[[#This Row],[Data de Validade]]<= DATE(2025, 12, 31), Tabela1[[#This Row],[Custo de Produção]]<= 50000), "Urgente", AND(F8>= DATE(2026,1,1), F8<= DATE(2028, 12, 31), J8>50000), "Pendente e Caro", AND(F8>= DATE(2026,1,1), F8<= DATE(2028, 12, 31), J8<=50000), "Pendente", F8>= DATE(2029,1,1), "Não prioeitário")} -> Urgente e Caro | H8: =YEAR(Tabela1[[#This Row],[Data de Validade]]) -> 2024 | I8: =MONTH(Tabela1[[#This Row],[Data de Validade]]) -> 5 | J8: 65781 | K8: Austrália | N8: P363P987 | O8: =COUNTIFS(B:B,N8) -> 1 | Y8: Contagem
A9: Firamu | B9: P589P568 | C9: ES | D9: =VLOOKUP(Tabela1[[#This Row],[Origem]], 'Perguntas 1 a 24'!$J$28:$K$34, 2, 0) -> Sudeste | E9: =Tabela1[[#This Row],[Descrição]]&"-"&Tabela1[[#This Row],[Código]]&"/"&Tabela1[[#This Row],[Origem]] -> Firamu-P589P568/ES | F9: 45425 | G9: {=_xlfn.IFS(AND(Tabela1[[#This Row],[Data de Validade]]<= DATE(2025, 12, 31), Tabela1[[#This Row],[Custo de Produção]]>50000), "Urgente e Caro", AND(Tabela1[[#This Row],[Data de Validade]]<= DATE(2025, 12, 31), Tabela1[[#This Row],[Custo de Produção]]<= 50000), "Urgente", AND(F9>= DATE(2026,1,1), F9<= DATE(2028, 12, 31), J9>50000), "Pendente e Caro", AND(F9>= DATE(2026,1,1), F9<= DATE(2028, 12, 31), J9<=50000), "Pendente", F9>= DATE(2029,1,1), "Não prioeitário")} -> Urgente e Caro | H9: =YEAR(Tabela1[[#This Row],[Data de Validade]]) -> 2024 | I9: =MONTH(Tabela1[[#This Row],[Data de Validade]]) -> 5 | J9: 57874 | K9: Espanha | N9: P589P568 | O9: =COUNTIFS(B:B,N9) -> 1 | S9: Resumo Custo de Produção por Região | Y9: Austrália | Z9: Espanha | AA9: Holanda | AB9: Panamá
A10: Namirolacu | B10: P445P823 | C10: ES | D10: =VLOOKUP(Tabela1[[#This Row],[Origem]], 'Perguntas 1 a 24'!$J$28:$K$34, 2, 0) -> Sudeste | E10: =Tabela1[[#This Row],[Descrição]]&"-"&Tabela1[[#This Row],[Código]]&"/"&Tabela1[[#This Row],[Origem]] -> Namirolacu-P445P823/ES | F10: 45425 | G10: {=_xlfn.IFS(AND(Tabela1[[#This Row],[Data de Validade]]<= DATE(2025, 12, 31), Tabela1[[#This Row],[Custo de Produção]]>50000), "Urgente e Caro", AND(Tabela1[[#This Row],[Data de Validade]]<= DATE(2025, 12, 31), Tabela1[[#This Row],[Custo de Produção]]<= 50000), "Urgente", AND(F10>= DATE(2026,1,1), F10<= DATE(2028, 12, 31), J10>50000), "Pendente e Caro", AND(F10>= DATE(2026,1,1), F10<= DATE(2028, 12, 31), J10<=50000), "Pendente", F10>= DATE(2029,1,1), "Não prioeitário")} -> Urgente e Caro | H10: =YEAR(Tabela1[[#This Row],[Data de Validade]]) -> 2024 | I10: =MONTH(Tabela1[[#This Row],[Data de Validade]]) -> 5 | J10: 56196 | K10: Austrália | N10: P445P823 | O10: =COUNTIFS(B:B,N10) -> 1 | S10: Austrália | T10: Espanha | U10: Holanda | V10: Panamá | X10: Nordeste | Y10: =COUNTIFS($K:$K, Y$9, $D:$D, $X10) -> 307 | Z10: =COUNTIFS($K:$K, Z$9, $D:$D, $X10) -> 257 | AA10: =COUNTIFS($K:$K, AA$9, $D:$D, $X10) -> 290 | AB10: =COUNTIFS($K:$K, AB$9, $D:$D, $X10) -> 274
A11: Turucego | B11: H647P923 | C11: GO | D11: =VLOOKUP(Tabela1[[#This Row],[Origem]], 'Perguntas 1 a 24'!$J$28:$K$34, 2, 0) -> Centro-Oeste | E11: =Tabela1[[#This Row],[Descrição]]&"-"&Tabela1[[#This Row],[Código]]&"/"&Tabela1[[#This Row],[Origem]] -> Turucego-H647P923/GO | F11: 45426 | G11: {=_xlfn.IFS(AND(Tabela1[[#This Row],[Data de Validade]]<= DATE(2025, 12, 31), Tabela1[[#This Row],[Custo de Produção]]>50000), "Urgente e Caro", AND(Tabela1[[#This Row],[Data de Validade]]<= DATE(2025, 12, 31), Tabela1[[#This Row],[Custo de Produção]]<= 50000), "Urgente", AND(F11>= DATE(2026,1,1), F11<= DATE(2028, 12, 31), J11>50000), "Pendente e Caro", AND(F11>= DATE(2026,1,1), F11<= DATE(2028, 12, 31), J11<=50000), "Pendente", F11>= DATE(2029,1,1), "Não prioeitário")} -> Urgente e Caro | H11: =YEAR(Tabela1[[#This Row],[Data de Validade]]) -> 2024 | I11: =MONTH(Tabela1[[#This Row],[Data de Validade]]) -> 5 | J11: 56196 | K11: Panamá | N11: H647P923 | O11: =COUNTIFS(B:B,N11) -> 1 | R11: Nordeste | S11: =SUMIFS($J:$J,$K:$K, S$10, $D:$D, $R11) -> 21582443 | T11: =SUMIFS($J:$J,$K:$K, T$10, $D:$D, $R11) -> 18432363 | U11: =SUMIFS($J:$J,$K:$K, U$10, $D:$D, $R11) -> 19384102 | V11: =SUMIFS($J:$J,$K:$K, V$10, $D:$D, $R11) -> 19329788 | X11: Sudeste | Y11: =COUNTIFS($K:$K, Y$9, $D:$D, $X11) -> 528 | Z11: =COUNTIFS($K:$K, Z$9, $D:$D, $X11) -> 540 | AA11: =COUNTIFS($K:$K, AA$9, $D:$D, $X11) -> 532 | AB11: =COUNTIFS($K:$K, AB$9, $D:$D, $X11) -> 545
A12: Tugafacumi | B12: P915P867 | C12: RJ | D12: =VLOOKUP(Tabela1[[#This Row],[Origem]], 'Perguntas 1 a 24'!$J$28:$K$34, 2, 0) -> Sudeste | E12: =Tabela1[[#This Row],[Descrição]]&"-"&Tabela1[[#This Row],[Código]]&"/"&Tabela1[[#This Row],[Origem]] -> Tugafacumi-P915P867/RJ | F12: 45426 | G12: {=_xlfn.IFS(AND(Tabela1[[#This Row],[Data de Validade]]<= DATE(2025, 12, 31), Tabela1[[#This Row],[Custo de Produção]]>50000), "Urgente e Caro", AND(Tabela1[[#This Row],[Data de Validade]]<= DATE(2025, 12, 31), Tabela1[[#This Row],[Custo de Produção]]<= 50000), "Urgente", AND(F12>= DATE(2026,1,1), F12<= DATE(2028, 12, 31), J12>50000), "Pendente e Caro", AND(F12>= DATE(2026,1,1), F12<= DATE(2028, 12, 31), J12<=50000), "Pendente", F12>= DATE(2029,1,1), "Não prioeitário")} -> Urgente e Caro | H12: =YEAR(Tabela1[[#This Row],[Data de Validade]]) -> 2024 | I12: =MONTH(Tabela1[[#This Row],[Data de Validade]]) -> 5 | J12: 88834 | K12: Panamá | N12: P915P867 | O12: =COUNTIFS(B:B,N12) -> 1 | R12: Sudeste | S12: =SUMIFS($J:$J,$K:$K, S$10, $D:$D, $R12) -> 37494439 | T12: =SUMIFS($J:$J,$K:$K, T$10, $D:$D, $R12) -> 38989407 | U12: =SUMIFS($J:$J,$K:$K, U$10, $D:$D, $R12) -> 38539749 | V12: =SUMIFS($J:$J,$K:$K, V$10, $D:$D, $R12) -> 37891952 | X12: Centro-Oeste | Y12: =COUNTIFS($K:$K, Y$9, $D:$D, $X12) -> 172 | Z12: =COUNTIFS($K:$K, Z$9, $D:$D, $X12) -> 133 | AA12: =COUNTIFS($K:$K, AA$9, $D:$D, $X12) -> 136 | AB12: =COUNTIFS($K:$K, AB$9, $D:$D, $X12) -> 141
A13: Motufidatu | B13: P318P546 | C13: MA | D13: =VLOOKUP(Tabela1[[#This Row],[Origem]], 'Perguntas 1 a 24'!$J$28:$K$34, 2, 0) -> Nordeste | E13: =Tabela1[[#This Row],[Descrição]]&"-"&Tabela1[[#This Row],[Código]]&"/"&Tabela1[[#This Row],[Origem]] -> Motufidatu-P318P546/MA | F13: 45427 | G13: {=_xlfn.IFS(AND(Tabela1[[#This Row],[Data de Validade]]<= DATE(2025, 12, 31), Tabela1[[#This Row],[Custo de Produção]]>50000), "Urgente e Caro", AND(Tabela1[[#This Row],[Data de Validade]]<= DATE(2025, 12, 31), Tabela1[[#This Row],[Custo de Produção]]<= 50000), "Urgente", AND(F13>= DATE(2026,1,1), F13<= DATE(2028, 12, 31), J13>50000), "Pendente e Caro", AND(F13>= DATE(2026,1,1), F13<= DATE(2028, 12, 31), J13<=50000), "Pendente", F13>= DATE(2029,1,1), "Não prioeitário")} -> Urgente e Caro | H13: =YEAR(Tabela1[[#This Row],[Data de Validade]]) -> 2024 | I13: =MONTH(Tabela1[[#This Row],[Data de Validade]]) -> 5 | J13: 87366 | K13: Espanha | N13: P318P546 | O13: =COUNTIFS(B:B,N13) -> 1 | R13: Centro-Oeste | S13: =SUMIFS($J:$J,$K:$K, S$10, $D:$D, $R13) -> 12025755 | T13: =SUMIFS($J:$J,$K:$K, T$10, $D:$D, $R13) -> 9401319 | U13: =SUMIFS($J:$J,$K:$K, U$10, $D:$D, $R13) -> 9133421 | V13: =SUMIFS($J:$J,$K:$K, V$10, $D:$D, $R13) -> 9935480 | X13: Norte | Y13: =COUNTIFS($K:$K, Y$9, $D:$D, $X13) -> 0 | Z13: =COUNTIFS($K:$K, Z$9, $D:$D, $X13) -> 0 | AA13: =COUNTIFS($K:$K, AA$9, $D:$D, $X13) -> 0 | AB13: =COUNTIFS($K:$K, AB$9, $D:$D, $X13) -> 0
A14: Cepeti | B14: P937P636 | C14: GO | D14: =VLOOKUP(Tabela1[[#This Row],[Origem]], 'Perguntas 1 a 24'!$J$28:$K$34, 2, 0) -> Centro-Oeste | E14: =Tabela1[[#This Row],[Descrição]]&"-"&Tabela1[[#This Row],[Código]]&"/"&Tabela1[[#This Row],[Origem]] -> Cepeti-P937P636/GO | F14: 45427 | G14: {=_xlfn.IFS(AND(Tabela1[[#This Row],[Data de Validade]]<= DATE(2025, 12, 31), Tabela1[[#This Row],[Custo de Produção]]>50000), "Urgente e Caro", AND(Tabela1[[#This Row],[Data de Validade]]<= DATE(2025, 12, 31), Tabela1[[#This Row],[Custo de Produção]]<= 50000), "Urgente", AND(F14>= DATE(2026,1,1), F14<= DATE(2028, 12, 31), J14>50000), "Pendente e Caro", AND(F14>= DATE(2026,1,1), F14<= DATE(2028, 12, 31), J14<=50000), "Pendente", F14>= DATE(2029,1,1), "Não prioeitário")} -> Urgente e Caro | H14: =YEAR(Tabela1[[#This Row],[Data de Validade]]) -> 2024 | I14: =MONTH(Tabela1[[#This Row],[Data de Validade]]) -> 5 | J14: 60456 | K14: Panamá | N14: P937P636 | O14: =COUNTIFS(B:B,N14) -> 1 | R14: Total | S14: =SUM(S11:S13) -> 71102637 | T14: =SUM(T11:T13) -> 66823089 | U14: =SUM(U11:U13) -> 67057272 | V14: =SUM(V11:V13) -> 67157220 | X14: Total | Y14: =SUM(Y10:Y13) -> 1007 | Z14: =SUM(Z10:Z13) -> 930 | AA14: =SUM(AA10:AA13) -> 958 | AB14: =SUM(AB10:AB13) -> 960
A15: Pudepa | B15: H586H551 | C15: AL | D15: =VLOOKUP(Tabela1[[#This Row],[Origem]], 'Perguntas 1 a 24'!$J$28:$K$34, 2, 0) -> Nordeste | E15: =Tabela1[[#This Row],[Descrição]]&"-"&Tabela1[[#This Row],[Código]]&"/"&Tabela1[[#This Row],[Origem]] -> Pudepa-H586H551/AL | F15: 45427 | G15: {=_xlfn.IFS(AND(Tabela1[[#This Row],[Data de Validade]]<= DATE(2025, 12, 31), Tabela1[[#This Row],[Custo de Produção]]>50000), "Urgente e Caro", AND(Tabela1[[#This Row],[Data de Validade]]<= DATE(2025, 12, 31), Tabela1[[#This Row],[Custo de Produção]]<= 50000), "Urgente", AND(F15>= DATE(2026,1,1), F15<= DATE(2028, 12, 31), J15>50000), "Pendente e Caro", AND(F15>= DATE(2026,1,1), F15<= DATE(2028, 12, 31), J15<=50000), "Pendente", F15>= DATE(2029,1,1), "Não prioeitário")} -> Urgente e Caro | H15: =YEAR(Tabela1[[#This Row],[Data de Validade]]) -> 2024 | I15: =MONTH(Tabela1[[#This Row],[Data de Validade]]) -> 5 | J15: 56807 | K15: Austrália | N15: H586H551 | O15: =COUNTIFS(B:B,N15) -> 1
A16: Cirefapu | B16: H824P368 | C16: SP | D16: =VLOOKUP(Tabela1[[#This Row],[Origem]], 'Perguntas 1 a 24'!$J$28:$K$34, 2, 0) -> Sudeste | E16: =Tabela1[[#This Row],[Descrição]]&"-"&Tabela1[[#This Row],[Código]]&"/"&Tabela1[[#This Row],[Origem]] -> Cirefapu-H824P368/SP | F16: 45428 | G16: {=_xlfn.IFS(AND(Tabela1[[#This Row],[Data de Validade]]<= DATE(2025, 12, 31), Tabela1[[#This Row],[Custo de Produção]]>50000), "Urgente e Caro", AND(Tabela1[[#This Row],[Data de Validade]]<= DATE(2025, 12, 31), Tabela1[[#This Row],[Custo de Produção]]<= 50000), "Urgente", AND(F16>= DATE(2026,1,1), F16<= DATE(2028, 12, 31), J16>50000), "Pendente e Caro", AND(F16>= DATE(2026,1,1), F16<= DATE(2028, 12, 31), J16<=50000), "Pendente", F16>= DATE(2029,1,1), "Não prioeitário")} -> Urgente e Caro | H16: =YEAR(Tabela1[[#This Row],[Data de Validade]]) -> 2024 | I16: =MONTH(Tabela1[[#This Row],[Data de Validade]]) -> 5 | J16: 65721 | K16: Panamá | N16: H824P368 | O16: =COUNTIFS(B:B,N16) -> 1 | R16: Qual o País que é maior em Qtd? E também em Valor de Custo?
A17: Netugo | B17: H149P458 | C17: ES | D17: =VLOOKUP(Tabela1[[#This Row],[Origem]], 'Perguntas 1 a 24'!$J$28:$K$34, 2, 0) -> Sudeste | E17: =Tabela1[[#This Row],[Descrição]]&"-"&Tabela1[[#This Row],[Código]]&"/"&Tabela1[[#This Row],[Origem]] -> Netugo-H149P458/ES | F17: 45429 | G17: {=_xlfn.IFS(AND(Tabela1[[#This Row],[Data de Validade]]<= DATE(2025, 12, 31), Tabela1[[#This Row],[Custo de Produção]]>50000), "Urgente e Caro", AND(Tabela1[[#This Row],[Data de Validade]]<= DATE(2025, 12, 31), Tabela1[[#This Row],[Custo de Produção]]<= 50000), "Urgente", AND(F17>= DATE(2026,1,1), F17<= DATE(2028, 12, 31), J17>50000), "Pendente e Caro", AND(F17>= DATE(2026,1,1), F17<= DATE(2028, 12, 31), J17<=50000), "Pendente", F17>= DATE(2029,1,1), "Não prioeitário")} -> Urgente e Caro | H17: =YEAR(Tabela1[[#This Row],[Data de Validade]]) -> 2024 | I17: =MONTH(Tabela1[[#This Row],[Data de Validade]]) -> 5 | J17: 53918 | K17: Holanda | N17: H149P458 | O17: =COUNTIFS(B:B,N17) -> 1 | R17: Quantidade | S17: {=INDEX(Y9:AB9, 0, MATCH(LARGE(Y14:AB14, 1), Y14:AB14, 0))} -> Austrália
A18: Pofodoge | B18: H985H461 | C18: RJ | D18: =VLOOKUP(Tabela1[[#This Row],[Origem]], 'Perguntas 1 a 24'!$J$28:$K$34, 2, 0) -> Sudeste | E18: =Tabela1[[#This Row],[Descrição]]&"-"&Tabela1[[#This Row],[Código]]&"/"&Tabela1[[#This Row],[Origem]] -> Pofodoge-H985H461/RJ | F18: 45429 | G18: {=_xlfn.IFS(AND(Tabela1[[#This Row],[Data de Validade]]<= DATE(2025, 12, 31), Tabela1[[#This Row],[Custo de Produção]]>50000), "Urgente e Caro", AND(Tabela1[[#This Row],[Data de Validade]]<= DATE(2025, 12, 31), Tabela1[[#This Row],[Custo de Produção]]<= 50000), "Urgente", AND(F18>= DATE(2026,1,1), F18<= DATE(2028, 12, 31), J18>50000), "Pendente e Caro", AND(F18>= DATE(2026,1,1), F18<= DATE(2028, 12, 31), J18<=50000), "Pendente", F18>= DATE(2029,1,1), "Não prioeitário")} -> Urgente | H18: =YEAR(Tabela1[[#This Row],[Data de Validade]]) -> 2024 | I18: =MONTH(Tabela1[[#This Row],[Data de Validade]]) -> 5 | J18: 27565 | K18: Panamá | N18: H985H461 | O18: =COUNTIFS(B:B,N18) -> 1 | R18: Valor | S18: {=INDEX(S10:V10, 0, MATCH(LARGE(S14:V14, 1), S14:V14, 0))} -> Austrália
B19: P561H622 | C19: ES | D19: =VLOOKUP(Tabela1[[#This Row],[Origem]], 'Perguntas 1 a 24'!$J$28:$K$34, 2, 0) -> Sudeste | E19: =Tabela1[[#This Row],[Descrição]]&"-"&Tabela1[[#This Row],[Código]]&"/"&Tabela1[[#This Row],[Origem]] -> -P561H622/ES | F19: 45430 | G19: {=_xlfn.IFS(AND(Tabela1[[#This Row],[Data de Validade]]<= DATE(2025, 12, 31), Tabela1[[#This Row],[Custo de Produção]]>50000), "Urgente e Caro", AND(Tabela1[[#This Row],[Data de Validade]]<= DATE(2025, 12, 31), Tabela1[[#This Row],[Custo de Produção]]<= 50000), "Urgente", AND(F19>= DATE(2026,1,1), F19<= DATE(2028, 12, 31), J19>50000), "Pendente e Caro", AND(F19>= DATE(2026,1,1), F19<= DATE(2028, 12, 31), J19<=50000), "Pendente", F19>= DATE(2029,1,1), "Não prioeitário")} -> Urgente e Caro | H19: =YEAR(Tabela1[[#This Row],[Data de Validade]]) -> 2024 | I19: =MONTH(Tabela1[[#This Row],[Data de Validade]]) -> 5 | J19: 51114 | K19: Panamá | N19: P561H622 | O19: =COUNTIFS(B:B,N19) -> 1
A20: Limalegado | B20: H635H414 | C20: AL | D20: =VLOOKUP(Tabela1[[#This Row],[Origem]], 'Perguntas 1 a 24'!$J$28:$K$34, 2, 0) -> Nordeste | E20: =Tabela1[[#This Row],[Descrição]]&"-"&Tabela1[[#This Row],[Código]]&"/"&Tabela1[[#This Row],[Origem]] -> Limalegado-H635H414/AL | F20: 45431 | G20: {=_xlfn.IFS(AND(Tabela1[[#This Row],[Data de Validade]]<= DATE(2025, 12, 31), Tabela1[[#This Row],[Custo de Produção]]>50000), "Urgente e Caro", AND(Tabela1[[#This Row],[Data de Validade]]<= DATE(2025, 12, 31), Tabela1[[#This Row],[Custo de Produção]]<= 50000), "Urgente", AND(F20>= DATE(2026,1,1), F20<= DATE(2028, 12, 31), J20>50000), "Pendente e Caro", AND(F20>= DATE(2026,1,1), F20<= DATE(2028, 12, 31), J20<=50000), "Pendente", F20>= DATE(2029,1,1), "Não prioeitário")} -> Urgente | H20: =YEAR(Tabela1[[#This Row],[Data de Validade]]) -> 2024 | I20: =MONTH(Tabela1[[#This Row],[Data de Validade]]) -> 5 | J20: 41665 | K20: Austrália | N20: H635H414 | O20: =COUNTIFS(B:B,N20) -> 1
A21: Tepogigiro | B21: H877P957 | C21: MG | D21: =VLOOKUP(Tabela1[[#This Row],[Origem]], 'Perguntas 1 a 24'!$J$28:$K$34, 2, 0) -> Sudeste | E21: =Tabela1[[#This Row],[Descrição]]&"-"&Tabela1[[#This Row],[Código]]&"/"&Tabela1[[#This Row],[Origem]] -> Tepogigiro-H877P957/MG | F21: 45433 | G21: {=_xlfn.IFS(AND(Tabela1[[#This Row],[Data de Validade]]<= DATE(2025, 12, 31), Tabela1[[#This Row],[Custo de Produção]]>50000), "Urgente e Caro", AND(Tabela1[[#This Row],[Data de Validade]]<= DATE(2025, 12, 31), Tabela1[[#This Row],[Custo de Produção]]<= 50000), "Urgente", AND(F21>= DATE(2026,1,1), F21<= DATE(2028, 12, 31), J21>50000), "Pendente e Caro", AND(F21>= DATE(2026,1,1), F21<= DATE(2028, 12, 31), J21<=50000), "Pendente", F21>= DATE(2029,1,1), "Não prioeitário")} -> Urgente e Caro | H21: =YEAR(Tabela1[[#This Row],[Data de Validade]]) -> 2024 | I21: =MONTH(Tabela1[[#This Row],[Data de Validade]]) -> 5 | J21: 87845 | K21: Austrália | N21: H877P957 | O21: =COUNTIFS(B:B,N21) -> 1
A22: Natavi | B22: P767H833 | C22: SP | D22: =VLOOKUP(Tabela1[[#This Row],[Origem]], 'Perguntas 1 a 24'!$J$28:$K$34, 2, 0) -> Sudeste | E22: =Tabela1[[#This Row],[Descrição]]&"-"&Tabela1[[#This Row],[Código]]&"/"&Tabela1[[#This Row],[Origem]] -> Natavi-P767H833/SP | F22: 45433 | G22: {=_xlfn.IFS(AND(Tabela1[[#This Row],[Data de Validade]]<= DATE(2025, 12, 31), Tabela1[[#This Row],[Custo de Produção]]>50000), "Urgente e Caro", AND(Tabela1[[#This Row],[Data de Validade]]<= DATE(2025, 12, 31), Tabela1[[#This Row],[Custo de Produção]]<= 50000), "Urgente", AND(F22>= DATE(2026,1,1), F22<= DATE(2028, 12, 31), J22>50000), "Pendente e Caro", AND(F22>= DATE(2026,1,1), F22<= DATE(2028, 12, 31), J22<=50000), "Pendente", F22>= DATE(2029,1,1), "Não prioeitário")} -> Urgente e Caro | H22: =YEAR(Tabela1[[#This Row],[Data de Validade]]) -> 2024 | I22: =MONTH(Tabela1[[#This Row],[Data de Validade]]) -> 5 | J22: 50593 | K22: Holanda | N22: P767H833 | O22: =COUNTIFS(B:B,N22) -> 1 | S22: Análise dos Top 5 que tiveram maiores Custos de Produção
A23: Mafune | B23: P472P981 | C23: GO | D23: =VLOOKUP(Tabela1[[#This Row],[Origem]], 'Perguntas 1 a 24'!$J$28:$K$34, 2, 0) -> Centro-Oeste | E23: =Tabela1[[#This Row],[Descrição]]&"-"&Tabela1[[#This Row],[Código]]&"/"&Tabela1[[#This Row],[Origem]] -> Mafune-P472P981/GO | F23: 45434 | G23: {=_xlfn.IFS(AND(Tabela1[[#This Row],[Data de Validade]]<= DATE(2025, 12, 31), Tabela1[[#This Row],[Custo de Produção]]>50000), "Urgente e Caro", AND(Tabela1[[#This Row],[Data de Validade]]<= DATE(2025, 12, 31), Tabela1[[#This Row],[Custo de Produção]]<= 50000), "Urgente", AND(F23>= DATE(2026,1,1), F23<= DATE(2028, 12, 31), J23>50000), "Pendente e Caro", AND(F23>= DATE(2026,1,1), F23<= DATE(2028, 12, 31), J23<=50000), "Pendente", F23>= DATE(2029,1,1), "Não prioeitário")} -> Urgente e Caro | H23: =YEAR(Tabela1[[#This Row],[Data de Validade]]) -> 2024 | I23: =MONTH(Tabela1[[#This Row],[Data de Validade]]) -> 5 | J23: 78874 | K23: Espanha | N23: P472P981 | O23: =COUNTIFS(B:B,N23) -> 1 | R23: TOP 5 | S23: Descrição | T23: Código | U23: Custo de Produção | V23: País de Destino
A24: Pevupetiti | B24: H124P283 | C24: MA | D24: =VLOOKUP(Tabela1[[#This Row],[Origem]], 'Perguntas 1 a 24'!$J$28:$K$34, 2, 0) -> Nordeste | E24: =Tabela1[[#This Row],[Descrição]]&"-"&Tabela1[[#This Row],[Código]]&"/"&Tabela1[[#This Row],[Origem]] -> Pevupetiti-H124P283/MA | F24: 45434 | G24: {=_xlfn.IFS(AND(Tabela1[[#This Row],[Data de Validade]]<= DATE(2025, 12, 31), Tabela1[[#This Row],[Custo de Produção]]>50000), "Urgente e Caro", AND(Tabela1[[#This Row],[Data de Validade]]<= DATE(2025, 12, 31), Tabela1[[#This Row],[Custo de Produção]]<= 50000), "Urgente", AND(F24>= DATE(2026,1,1), F24<= DATE(2028, 12, 31), J24>50000), "Pendente e Caro", AND(F24>= DATE(2026,1,1), F24<= DATE(2028, 12, 31), J24<=50000), "Pendente", F24>= DATE(2029,1,1), "Não prioeitário")} -> Urgente | H24: =YEAR(Tabela1[[#This Row],[Data de Validade]]) -> 2024 | I24: =MONTH(Tabela1[[#This Row],[Data de Validade]]) -> 5 | J24: 41981 | K24: Panamá | N24: H124P283 | O24: =COUNTIFS(B:B,N24) -> 1 | R24: 1 | S24: =INDEX(A:A, MATCH(LARGE(J:J, R24),J:J, 0)) -> Vutufe | T24: =INDEX(B:B, MATCH(LARGE(J:J,R24),J:J, 0)) -> P873H963 | U24: {=INDEX(J:J, MATCH(LARGE(J:J, R24), J:J,0), 0)} -> 119945 | V24: {=INDEX(K:K, MATCH(LARGE(J:J, R24),J:J, 0), 0)} -> Panamá
A25: Vapotudi | B25: P716H775 | C25: AL | D25: =VLOOKUP(Tabela1[[#This Row],[Origem]], 'Perguntas 1 a 24'!$J$28:$K$34, 2, 0) -> Nordeste | E25: =Tabela1[[#This Row],[Descrição]]&"-"&Tabela1[[#This Row],[Código]]&"/"&Tabela1[[#This Row],[Origem]] -> Vapotudi-P716H775/AL | F25: 45434 | G25: {=_xlfn.IFS(AND(Tabela1[[#This Row],[Data de Validade]]<= DATE(2025, 12, 31), Tabela1[[#This Row],[Custo de Produção]]>50000), "Urgente e Caro", AND(Tabela1[[#This Row],[Data de Validade]]<= DATE(2025, 12, 31), Tabela1[[#This Row],[Custo de Produção]]<= 50000), "Urgente", AND(F25>= DATE(2026,1,1), F25<= DATE(2028, 12, 31), J25>50000), "Pendente e Caro", AND(F25>= DATE(2026,1,1), F25<= DATE(2028, 12, 31), J25<=50000), "Pendente", F25>= DATE(2029,1,1), "Não prioeitário")} -> Urgente | H25: =YEAR(Tabela1[[#This Row],[Data de Validade]]) -> 2024 | I25: =MONTH(Tabela1[[#This Row],[Data de Validade]]) -> 5 | J25: 24458 | K25: Austrália | N25: P716H775 | O25: =COUNTIFS(B:B,N25) -> 1 | R25: 2 | S25: =INDEX(A:A, MATCH(LARGE(J:J, R25),J:J, 0)) -> Licapiro | T25: =INDEX(B:B, MATCH(LARGE(J:J,R25),J:J, 0)) -> H948H323 | U25: {=INDEX(J:J, MATCH(LARGE(J:J, R25), J:J,0), 0)} -> 119933 | V25: {=INDEX(K:K, MATCH(LARGE(J:J, R25),J:J, 0), 0)} -> Austrália
A26: Pavaputi | B26: P441H685 | C26: MA | D26: =VLOOKUP(Tabela1[[#This Row],[Origem]], 'Perguntas 1 a 24'!$J$28:$K$34, 2, 0) -> Nordeste | E26: =Tabela1[[#This Row],[Descrição]]&"-"&Tabela1[[#This Row],[Código]]&"/"&Tabela1[[#This Row],[Origem]] -> Pavaputi-P441H685/MA | F26: 45435 | G26: {=_xlfn.IFS(AND(Tabela1[[#This Row],[Data de Validade]]<= DATE(2025, 12, 31), Tabela1[[#This Row],[Custo de Produção]]>50000), "Urgente e Caro", AND(Tabela1[[#This Row],[Data de Validade]]<= DATE(2025, 12, 31), Tabela1[[#This Row],[Custo de Produção]]<= 50000), "Urgente", AND(F26>= DATE(2026,1,1), F26<= DATE(2028, 12, 31), J26>50000), "Pendente e Caro", AND(F26>= DATE(2026,1,1), F26<= DATE(2028, 12, 31), J26<=50000), "Pendente", F26>= DATE(2029,1,1), "Não prioeitário")} -> Urgente e Caro | H26: =YEAR(Tabela1[[#This Row],[Data de Validade]]) -> 2024 | I26: =MONTH(Tabela1[[#This Row],[Data de Validade]]) -> 5 | J26: 114895 | K26: Panamá | N26: P441H685 | O26: =COUNTIFS(B:B,N26) -> 1 | R26: 3 | S26: =INDEX(A:A, MATCH(LARGE(J:J, R26),J:J, 0)) -> Gopenemo | T26: =INDEX(B:B, MATCH(LARGE(J:J,R26),J:J, 0)) -> H155P441 | U26: {=INDEX(J:J, MATCH(LARGE(J:J, R26), J:J,0), 0)} -> 119903 | V26: {=INDEX(K:K, MATCH(LARGE(J:J, R26),J:J, 0), 0)} -> Austrália
A27: Varive | B27: H867P288 | C27: AL | D27: =VLOOKUP(Tabela1[[#This Row],[Origem]], 'Perguntas 1 a 24'!$J$28:$K$34, 2, 0) -> Nordeste | E27: =Tabela1[[#This Row],[Descrição]]&"-"&Tabela1[[#This Row],[Código]]&"/"&Tabela1[[#This Row],[Origem]] -> Varive-H867P288/AL | F27: 45435 | G27: {=_xlfn.IFS(AND(Tabela1[[#This Row],[Data de Validade]]<= DATE(2025, 12, 31), Tabela1[[#This Row],[Custo de Produção]]>50000), "Urgente e Caro", AND(Tabela1[[#This Row],[Data de Validade]]<= DATE(2025, 12, 31), Tabela1[[#This Row],[Custo de Produção]]<= 50000), "Urgente", AND(F27>= DATE(2026,1,1), F27<= DATE(2028, 12, 31), J27>50000), "Pendente e Caro", AND(F27>= DATE(2026,1,1), F27<= DATE(2028, 12, 31), J27<=50000), "Pendente", F27>= DATE(2029,1,1), "Não prioeitário")} -> Urgente e Caro | H27: =YEAR(Tabela1[[#This Row],[Data de Validade]]) -> 2024 | I27: =MONTH(Tabela1[[#This Row],[Data de Validade]]) -> 5 | J27: 62600 | K27: Panamá | N27: H867P288 | O27: =COUNTIFS(B:B,N27) -> 1 | R27: 4 | S27: =INDEX(A:A, MATCH(LARGE(J:J, R27),J:J, 0)) -> Petitode | T27: =INDEX(B:B, MATCH(LARGE(J:J,R27),J:J, 0)) -> H119P473 | U27: {=INDEX(J:J, MATCH(LARGE(J:J, R27), J:J,0), 0)} -> 119901 | V27: {=INDEX(K:K, MATCH(LARGE(J:J, R27),J:J, 0), 0)} -> Austrália
A28: Momupa | B28: P892H748 | C28: ES | D28: =VLOOKUP(Tabela1[[#This Row],[Origem]], 'Perguntas 1 a 24'!$J$28:$K$34, 2, 0) -> Sudeste | E28: =Tabela1[[#This Row],[Descrição]]&"-"&Tabela1[[#This Row],[Código]]&"/"&Tabela1[[#This Row],[Origem]] -> Momupa-P892H748/ES | F28: 45436 | G28: {=_xlfn.IFS(AND(Tabela1[[#This Row],[Data de Validade]]<= DATE(2025, 12, 31), Tabela1[[#This Row],[Custo de Produção]]>50000), "Urgente e Caro", AND(Tabela1[[#This Row],[Data de Validade]]<= DATE(2025, 12, 31), Tabela1[[#This Row],[Custo de Produção]]<= 50000), "Urgente", AND(F28>= DATE(2026,1,1), F28<= DATE(2028, 12, 31), J28>50000), "Pendente e Caro", AND(F28>= DATE(2026,1,1), F28<= DATE(2028, 12, 31), J28<=50000), "Pendente", F28>= DATE(2029,1,1), "Não prioeitário")} -> Urgente e Caro | H28: =YEAR(Tabela1[[#This Row],[Data de Validade]]) -> 2024 | I28: =MONTH(Tabela1[[#This Row],[Data de Validade]]) -> 5 | J28: 75024 | K28: Espanha | N28: P892H748 | O28: =COUNTIFS(B:B,N28) -> 1 | R28: 5 | S28: =INDEX(A:A, MATCH(LARGE(J:J, R28),J:J, 0)) -> Vigopurutu | T28: =INDEX(B:B, MATCH(LARGE(J:J,R28),J:J, 0)) -> H776P365 | U28: {=INDEX(J:J, MATCH(LARGE(J:J, R28), J:J,0), 0)} -> 119889 | V28: {=INDEX(K:K, MATCH(LARGE(J:J, R28),J:J, 0), 0)} -> Panamá
A29: Retorago | B29: H872P394 | C29: GO | D29: =VLOOKUP(Tabela1[[#This Row],[Origem]], 'Perguntas 1 a 24'!$J$28:$K$34, 2, 0) -> Centro-Oeste | E29: =Tabela1[[#This Row],[Descrição]]&"-"&Tabela1[[#This Row],[Código]]&"/"&Tabela1[[#This Row],[Origem]] -> Retorago-H872P394/GO | F29: 45437 | G29: {=_xlfn.IFS(AND(Tabela1[[#This Row],[Data de Validade]]<= DATE(2025, 12, 31), Tabela1[[#This Row],[Custo de Produção]]>50000), "Urgente e Caro", AND(Tabela1[[#This Row],[Data de Validade]]<= DATE(2025, 12, 31), Tabela1[[#This Row],[Custo de Produção]]<= 50000), "Urgente", AND(F29>= DATE(2026,1,1), F29<= DATE(2028, 12, 31), J29>50000), "Pendente e Caro", AND(F29>= DATE(2026,1,1), F29<= DATE(2028, 12, 31), J29<=50000), "Pendente", F29>= DATE(2029,1,1), "Não prioeitário")} -> Urgente e Caro | H29: =YEAR(Tabela1[[#This Row],[Data de Validade]]) -> 2024 | I29: =MONTH(Tabela1[[#This Row],[Data de Validade]]) -> 5 | J29: 86978 | K29: Espanha | N29: H872P394 | O29: =COUNTIFS(B:B,N29) -> 1
A30: Vicofegu | B30: H186H326 | C30: GO | D30: =VLOOKUP(Tabela1[[#This Row],[Origem]], 'Perguntas 1 a 24'!$J$28:$K$34, 2, 0) -> Centro-Oeste | E30: =Tabela1[[#This Row],[Descrição]]&"-"&Tabela1[[#This Row],[Código]]&"/"&Tabela1[[#This Row],[Origem]] -> Vicofegu-H186H326/GO | F30: 45437 | G30: {=_xlfn.IFS(AND(Tabela1[[#This Row],[Data de Validade]]<= DATE(2025, 12, 31), Tabela1[[#This Row],[Custo de Produção]]>50000), "Urgente e Caro", AND(Tabela1[[#This Row],[Data de Validade]]<= DATE(2025, 12, 31), Tabela1[[#This Row],[Custo de Produção]]<= 50000), "Urgente", AND(F30>= DATE(2026,1,1), F30<= DATE(2028, 12, 31), J30>50000), "Pendente e Caro", AND(F30>= DATE(2026,1,1), F30<= DATE(2028, 12, 31), J30<=50000), "Pendente", F30>= DATE(2029,1,1), "Não prioeitário")} -> Urgente | H30: =YEAR(Tabela1[[#This Row],[Data de Validade]]) -> 2024 | I30: =MONTH(Tabela1[[#This Row],[Data de Validade]]) -> 5 | J30: 36787 | K30: Holanda | N30: H186H326 | O30: =COUNTIFS(B:B,N30) -> 1
A31: Paleropu | B31: H611P813 | C31: GO | D31: =VLOOKUP(Tabela1[[#This Row],[Origem]], 'Perguntas 1 a 24'!$J$28:$K$34, 2, 0) -> Centro-Oeste | E31: =Tabela1[[#This Row],[Descrição]]&"-"&Tabela1[[#This Row],[Código]]&"/"&Tabela1[[#This Row],[Origem]] -> Paleropu-H611P813/GO | F31: 45438 | G31: {=_xlfn.IFS(AND(Tabela1[[#This Row],[Data de Validade]]<= DATE(2025, 12, 31), Tabela1[[#This Row],[Custo de Produção]]>50000), "Urgente e Caro", AND(Tabela1[[#This Row],[Data de Validade]]<= DATE(2025, 12, 31), Tabela1[[#This Row],[Custo de Produção]]<= 50000), "Urgente", AND(F31>= DATE(2026,1,1), F31<= DATE(2028, 12, 31), J31>50000), "Pendente e Caro", AND(F31>= DATE(2026,1,1), F31<= DATE(2028, 12, 31), J31<=50000), "Pendente", F31>= DATE(2029,1,1), "Não prioeitário")} -> Urgente e Caro | H31: =YEAR(Tabela1[[#This Row],[Data de Validade]]) -> 2024 | I31: =MONTH(Tabela1[[#This Row],[Data de Validade]]) -> 5 | J31: 114045 | K31: Espanha | N31: H611P813 | O31: =COUNTIFS(B:B,N31) -> 1
A32: Teterifipa | B32: P876H266 | C32: SP | D32: =VLOOKUP(Tabela1[[#This Row],[Origem]], 'Perguntas 1 a 24'!$J$28:$K$34, 2, 0) -> Sudeste | E32: =Tabela1[[#This Row],[Descrição]]&"-"&Tabela1[[#This Row],[Código]]&"/"&Tabela1[[#This Row],[Origem]] -> Teterifipa-P876H266/SP | F32: 45438 | G32: {=_xlfn.IFS(AND(Tabela1[[#This Row],[Data de Validade]]<= DATE(2025, 12, 31), Tabela1[[#This Row],[Custo de Produção]]>50000), "Urgente e Caro", AND(Tabela1[[#This Row],[Data de Validade]]<= DATE(2025, 12, 31), Tabela1[[#This Row],[Custo de Produção]]<= 50000), "Urgente", AND(F32>= DATE(2026,1,1), F32<= DATE(2028, 12, 31), J32>50000), "Pendente e Caro", AND(F32>= DATE(2026,1,1), F32<= DATE(2028, 12, 31), J32<=50000), "Pendente", F32>= DATE(2029,1,1), "Não prioeitário")} -> Urgente e Caro | H32: =YEAR(Tabela1[[#This Row],[Data de Validade]]) -> 2024 | I32: =MONTH(Tabela1[[#This Row],[Data de Validade]]) -> 5 | J32: 90122 | K32: Espanha | N32: P876H266 | O32: =COUNTIFS(B:B,N32) -> 1
A33: Tupagada | B33: P422H219 | C33: SP | D33: =VLOOKUP(Tabela1[[#This Row],[Origem]], 'Perguntas 1 a 24'!$J$28:$K$34, 2, 0) -> Sudeste | E33: =Tabela1[[#This Row],[Descrição]]&"-"&Tabela1[[#This Row],[Código]]&"/"&Tabela1[[#This Row],[Origem]] -> Tupagada-P422H219/SP | F33: 45438 | G33: {=_xlfn.IFS(AND(Tabela1[[#This Row],[Data de Validade]]<= DATE(2025, 12, 31), Tabela1[[#This Row],[Custo de Produção]]>50000), "Urgente e Caro", AND(Tabela1[[#This Row],[Data de Validade]]<= DATE(2025, 12, 31), Tabela1[[#This Row],[Custo de Produção]]<= 50000), "Urgente", AND(F33>= DATE(2026,1,1), F33<= DATE(2028, 12, 31), J33>50000), "Pendente e Caro", AND(F33>= DATE(2026,1,1), F33<= DATE(2028, 12, 31), J33<=50000), "Pendente", F33>= DATE(2029,1,1), "Não prioeitário")} -> Urgente | H33: =YEAR(Tabela1[[#This Row],[Data de Validade]]) -> 2024 | I33: =MONTH(Tabela1[[#This Row],[Data de Validade]]) -> 5 | J33: 35450 | K33: Panamá | N33: P422H219 | O33: =COUNTIFS(B:B,N33) -> 1
A34: Porepore | B34: P873P382 | C34: SP | D34: =VLOOKUP(Tabela1[[#This Row],[Origem]], 'Perguntas 1 a 24'!$J$28:$K$34, 2, 0) -> Sudeste | E34: =Tabela1[[#This Row],[Descrição]]&"-"&Tabela1[[#This Row],[Código]]&"/"&Tabela1[[#This Row],[Origem]] -> Porepore-P873P382/SP | F34: 45441 | G34: {=_xlfn.IFS(AND(Tabela1[[#This Row],[Data de Validade]]<= DATE(2025, 12, 31), Tabela1[[#This Row],[Custo de Produção]]>50000), "Urgente e Caro", AND(Tabela1[[#This Row],[Data de Validade]]<= DATE(2025, 12, 31), Tabela1[[#This Row],[Custo de Produção]]<= 50000), "Urgente", AND(F34>= DATE(2026,1,1), F34<= DATE(2028, 12, 31), J34>50000), "Pendente e Caro", AND(F34>= DATE(2026,1,1), F34<= DATE(2028, 12, 31), J34<=50000), "Pendente", F34>= DATE(2029,1,1), "Não prioeitário")} -> Urgente e Caro | H34: =YEAR(Tabela1[[#This Row],[Data de Validade]]) -> 2024 | I34: =MONTH(Tabela1[[#This Row],[Data de Validade]]) -> 5 | J34: 103488 | K34: Austrália | N34: P873P382 | O34: =COUNTIFS(B:B,N34) -> 1
A35: Tacicopo | B35: P561P729 | C35: SP | D35: =VLOOKUP(Tabela1[[#This Row],[Origem]], 'Perguntas 1 a 24'!$J$28:$K$34, 2, 0) -> Sudeste | E35: =Tabela1[[#This Row],[Descrição]]&"-"&Tabela1[[#This Row],[Código]]&"/"&Tabela1[[#This Row],[Origem]] -> Tacicopo-P561P729/SP | F35: 45442 | G35: {=_xlfn.IFS(AND(Tabela1[[#This Row],[Data de Validade]]<= DATE(2025, 12, 31), Tabela1[[#This Row],[Custo de Produção]]>50000), "Urgente e Caro", AND(Tabela1[[#This Row],[Data de Validade]]<= DATE(2025, 12, 31), Tabela1[[#This Row],[Custo de Produção]]<= 50000), "Urgente", AND(F35>= DATE(2026,1,1), F35<= DATE(2028, 12, 31), J35>50000), "Pendente e Caro", AND(F35>= DATE(2026,1,1), F35<= DATE(2028, 12, 31), J35<=50000), "Pendente", F35>= DATE(2029,1,1), "Não prioeitário")} -> Urgente e Caro | H35: =YEAR(Tabela1[[#This Row],[Data de Validade]]) -> 2024 | I35: =MONTH(Tabela1[[#This Row],[Data de Validade]]) -> 5 | J35: 68472 | K35: Espanha | N35: P561P729 | O35: =COUNTIFS(B:B,N35) -> 1
A36: Macirori | B36: H925H857 | C36: RJ | D36: =VLOOKUP(Tabela1[[#This Row],[Origem]], 'Perguntas 1 a 24'!$J$28:$K$34, 2, 0) -> Sudeste | E36: =Tabela1[[#This Row],[Descrição]]&"-"&Tabela1[[#This Row],[Código]]&"/"&Tabela1[[#This Row],[Origem]] -> Macirori-H925H857/RJ | F36: 45442 | G36: {=_xlfn.IFS(AND(Tabela1[[#This Row],[Data de Validade]]<= DATE(2025, 12, 31), Tabela1[[#This Row],[Custo de Produção]]>50000), "Urgente e Caro", AND(Tabela1[[#This Row],[Data de Validade]]<= DATE(2025, 12, 31), Tabela1[[#This Row],[Custo de Produção]]<= 50000), "Urgente", AND(F36>= DATE(2026,1,1), F36<= DATE(2028, 12, 31), J36>50000), "Pendente e Caro", AND(F36>= DATE(2026,1,1), F36<= DATE(2028, 12, 31), J36<=50000), "Pendente", F36>= DATE(2029,1,1), "Não prioeitário")} -> Urgente | H36: =YEAR(Tabela1[[#This Row],[Data de Validade]]) -> 2024 | I36: =MONTH(Tabela1[[#This Row],[Data de Validade]]) -> 5 | J36: 22772 | K36: Panamá | N36: H925H857 | O36: =COUNTIFS(B:B,N36) -> 1
A37: Pavifepo | B37: H499P514 | C37: MA | D37: =VLOOKUP(Tabela1[[#This Row],[Origem]], 'Perguntas 1 a 24'!$J$28:$K$34, 2, 0) -> Nordeste | E37: =Tabela1[[#This Row],[Descrição]]&"-"&Tabela1[[#This Row],[Código]]&"/"&Tabela1[[#This Row],[Origem]] -> Pavifepo-H499P514/MA | F37: 45443 | G37: {=_xlfn.IFS(AND(Tabela1[[#This Row],[Data de Validade]]<= DATE(2025, 12, 31), Tabela1[[#This Row],[Custo de Produção]]>50000), "Urgente e Caro", AND(Tabela1[[#This Row],[Data de Validade]]<= DATE(2025, 12, 31), Tabela1[[#This Row],[Custo de Produção]]<= 50000), "Urgente", AND(F37>= DATE(2026,1,1), F37<= DATE(2028, 12, 31), J37>50000), "Pendente e Caro", AND(F37>= DATE(2026,1,1), F37<= DATE(2028, 12, 31), J37<=50000), "Pendente", F37>= DATE(2029,1,1), "Não prioeitário")} -> Urgente | H37: =YEAR(Tabela1[[#This Row],[Data de Validade]]) -> 2024 | I37: =MONTH(Tabela1[[#This Row],[Data de Validade]]) -> 5 | J37: 43230 | K37: Holanda | N37: H499P514 | O37: =COUNTIFS(B:B,N37) -> 1
A38: Feleforu | B38: H749P458 | C38: GO | D38: =VLOOKUP(Tabela1[[#This Row],[Origem]], 'Perguntas 1 a 24'!$J$28:$K$34, 2, 0) -> Centro-Oeste | E38: =Tabela1[[#This Row],[Descrição]]&"-"&Tabela1[[#This Row],[Código]]&"/"&Tabela1[[#This Row],[Origem]] -> Feleforu-H749P458/GO | F38: 45444 | G38: {=_xlfn.IFS(AND(Tabela1[[#This Row],[Data de Validade]]<= DATE(2025, 12, 31), Tabela1[[#This Row],[Custo de Produção]]>50000), "Urgente e Caro", AND(Tabela1[[#This Row],[Data de Validade]]<= DATE(2025, 12, 31), Tabela1[[#This Row],[Custo de Produção]]<= 50000), "Urgente", AND(F38>= DATE(2026,1,1), F38<= DATE(2028, 12, 31), J38>50000), "Pendente e Caro", AND(F38>= DATE(2026,1,1), F38<= DATE(2028, 12, 31), J38<=50000), "Pendente", F38>= DATE(2029,1,1), "Não prioeitário")} -> Urgente | H38: =YEAR(Tabela1[[#This Row],[Data de Validade]]) -> 2024 | I38: =MONTH(Tabela1[[#This Row],[Data de Validade]]) -> 6 | J38: 44180 | K38: Panamá | N38: H749P458 | O38: =COUNTIFS(B:B,N38) -> 1
A39: Puvoca | B39: P379H325 | C39: GO | D39: =VLOOKUP(Tabela1[[#This Row],[Origem]], 'Perguntas 1 a 24'!$J$28:$K$34, 2, 0) -> Centro-Oeste | E39: =Tabela1[[#This Row],[Descrição]]&"-"&Tabela1[[#This Row],[Código]]&"/"&Tabela1[[#This Row],[Origem]] -> Puvoca-P379H325/GO | F39: 45445 | G39: {=_xlfn.IFS(AND(Tabela1[[#This Row],[Data de Validade]]<= DATE(2025, 12, 31), Tabela1[[#This Row],[Custo de Produção]]>50000), "Urgente e Caro", AND(Tabela1[[#This Row],[Data de Validade]]<= DATE(2025, 12, 31), Tabela1[[#This Row],[Custo de Produção]]<= 50000), "Urgente", AND(F39>= DATE(2026,1,1), F39<= DATE(2028, 12, 31), J39>50000), "Pendente e Caro", AND(F39>= DATE(2026,1,1), F39<= DATE(2028, 12, 31), J39<=50000), "Pendente", F39>= DATE(2029,1,1), "Não prioeitário")} -> Urgente e Caro | H39: =YEAR(Tabela1[[#This Row],[Data de Validade]]) -> 2024 | I39: =MONTH(Tabela1[[#This Row],[Data de Validade]]) -> 6 | J39: 112672 | K39: Holanda | N39: P379H325 | O39: =COUNTIFS(B:B,N39) -> 1
A40: Gurolicale | B40: H985H459 | C40: MG | D40: =VLOOKUP(Tabela1[[#This Row],[Origem]], 'Perguntas 1 a 24'!$J$28:$K$34, 2, 0) -> Sudeste | E40: =Tabela1[[#This Row],[Descrição]]&"-"&Tabela1[[#This Row],[Código]]&"/"&Tabela1[[#This Row],[Origem]] -> Gurolicale-H985H459/MG | F40: 45445 | G40: {=_xlfn.IFS(AND(Tabela1[[#This Row],[Data de Validade]]<= DATE(2025, 12, 31), Tabela1[[#This Row],[Custo de Produção]]>50000), "Urgente e Caro", AND(Tabela1[[#This Row],[Data de Validade]]<= DATE(2025, 12, 31), Tabela1[[#This Row],[Custo de Produção]]<= 50000), "Urgente", AND(F40>= DATE(2026,1,1), F40<= DATE(2028, 12, 31), J40>50000), "Pendente e Caro", AND(F40>= DATE(2026,1,1), F40<= DATE(2028, 12, 31), J40<=50000), "Pendente", F40>= DATE(2029,1,1), "Não prioeitário")} -> Urgente e Caro | H40: =YEAR(Tabela1[[#This Row],[Data de Validade]]) -> 2024 | I40: =MONTH(Tabela1[[#This Row],[Data de Validade]]) -> 6 | J40: 105592 | K40: Espanha | N40: H985H459 | O40: =COUNTIFS(B:B,N40) -> 1
... A1583: Deforidula | B1583: P264H647 | C1583: RJ | D1583: =VLOOKUP(Tabela1[[#This Row],[Origem]], 'Perguntas 1 a 24'!$J$28:$K$34, 2, 0) -> Sudeste | E1583: =Tabela1[[#This Row],[Descrição]]&"-"&Tabela1[[#This Row],[Código]]&"/"&Tabela1[[#This Row],[Origem]] -> Deforidula-P264H647/RJ | F1583: 46391 | G1583: {=_xlfn.IFS(AND(Tabela1[[#This Row],[Data de Validade]]<= DATE(2025, 12, 31), Tabela1[[#This Row],[Custo de Produção]]>50000), "Urgente e Caro", AND(Tabela1[[#This Row],[Data de Validade]]<= DATE(2025, 12, 31), Tabela1[[#This Row],[Custo de Produção]]<= 50000), "Urgente", AND(F1583>= DATE(2026,1,1), F1583<= DATE(2028, 12, 31), J1583>50000), "Pendente e Caro", AND(F1583>= DATE(2026,1,1), F1583<= DATE(2028, 12, 31), J1583<=50000), "Pendente", F1583>= DATE(2029,1,1), "Não prioeitário")} -> Pendente | H1583: =YEAR(Tabela1[[#This Row],[Data de Validade]]) -> 2027 | I1583: =MONTH(Tabela1[[#This Row],[Data de Validade]]) -> 1 | J1583: 20952 | K1583: Panamá | N1583: P264H647 | O1583: =COUNTIFS(B:B,N1583) -> 1
A1584: Rumipitero | B1584: H288P128 | C1584: MG | D1584: =VLOOKUP(Tabela1[[#This Row],[Origem]], 'Perguntas 1 a 24'!$J$28:$K$34, 2, 0) -> Sudeste | E1584: =Tabela1[[#This Row],[Descrição]]&"-"&Tabela1[[#This Row],[Código]]&"/"&Tabela1[[#This Row],[Origem]] -> Rumipitero-H288P128/MG | F1584: 46391 | G1584: {=_xlfn.IFS(AND(Tabela1[[#This Row],[Data de Validade]]<= DATE(2025, 12, 31), Tabela1[[#This Row],[Custo de Produção]]>50000), "Urgente e Caro", AND(Tabela1[[#This Row],[Data de Validade]]<= DATE(2025, 12, 31), Tabela1[[#This Row],[Custo de Produção]]<= 50000), "Urgente", AND(F1584>= DATE(2026,1,1), F1584<= DATE(2028, 12, 31), J1584>50000), "Pendente e Caro", AND(F1584>= DATE(2026,1,1), F1584<= DATE(2028, 12, 31), J1584<=50000), "Pendente", F1584>= DATE(2029,1,1), "Não prioeitário")} -> Pendente | H1584: =YEAR(Tabela1[[#This Row],[Data de Validade]]) -> 2027 | I1584: =MONTH(Tabela1[[#This Row],[Data de Validade]]) -> 1 | J1584: 20286 | K1584: Panamá | N1584: H288P128 | O1584: =COUNTIFS(B:B,N1584) -> 1 | R1584: =71534.94+70654.45 -> 142189.39
A1585: Dapeli | B1585: P197H653 | C1585: MA | D1585: =VLOOKUP(Tabela1[[#This Row],[Origem]], 'Perguntas 1 a 24'!$J$28:$K$34, 2, 0) -> Nordeste | E1585: =Tabela1[[#This Row],[Descrição]]&"-"&Tabela1[[#This Row],[Código]]&"/"&Tabela1[[#This Row],[Origem]] -> Dapeli-P197H653/MA | F1585: 46392 | G1585: {=_xlfn.IFS(AND(Tabela1[[#This Row],[Data de Validade]]<= DATE(2025, 12, 31), Tabela1[[#This Row],[Custo de Produção]]>50000), "Urgente e Caro", AND(Tabela1[[#This Row],[Data de Validade]]<= DATE(2025, 12, 31), Tabela1[[#This Row],[Custo de Produção]]<= 50000), "Urgente", AND(F1585>= DATE(2026,1,1), F1585<= DATE(2028, 12, 31), J1585>50000), "Pendente e Caro", AND(F1585>= DATE(2026,1,1), F1585<= DATE(2028, 12, 31), J1585<=50000), "Pendente", F1585>= DATE(2029,1,1), "Não prioeitário")} -> Pendente e Caro | H1585: =YEAR(Tabela1[[#This Row],[Data de Validade]]) -> 2027 | I1585: =MONTH(Tabela1[[#This Row],[Data de Validade]]) -> 1 | J1585: 113530 | K1585: Espanha | N1585: P197H653 | O1585: =COUNTIFS(B:B,N1585) -> 1 | R1585: =R1584/2 -> 71094.695
A1586: Fenocete | B1586: H696H439 | C1586: GO | D1586: =VLOOKUP(Tabela1[[#This Row],[Origem]], 'Perguntas 1 a 24'!$J$28:$K$34, 2, 0) -> Centro-Oeste | E1586: =Tabela1[[#This Row],[Descrição]]&"-"&Tabela1[[#This Row],[Código]]&"/"&Tabela1[[#This Row],[Origem]] -> Fenocete-H696H439/GO | F1586: 46393 | G1586: {=_xlfn.IFS(AND(Tabela1[[#This Row],[Data de Validade]]<= DATE(2025, 12, 31), Tabela1[[#This Row],[Custo de Produção]]>50000), "Urgente e Caro", AND(Tabela1[[#This Row],[Data de Validade]]<= DATE(2025, 12, 31), Tabela1[[#This Row],[Custo de Produção]]<= 50000), "Urgente", AND(F1586>= DATE(2026,1,1), F1586<= DATE(2028, 12, 31), J1586>50000), "Pendente e Caro", AND(F1586>= DATE(2026,1,1), F1586<= DATE(2028, 12, 31), J1586<=50000), "Pendente", F1586>= DATE(2029,1,1), "Não prioeitário")} -> Pendente e Caro | H1586: =YEAR(Tabela1[[#This Row],[Data de Validade]]) -> 2027 | I1586: =MONTH(Tabela1[[#This Row],[Data de Validade]]) -> 1 | J1586: 63906 | K1586: Espanha | N1586: H696H439 | O1586: =COUNTIFS(B:B,N1586) -> 1
A1587: Cefolado | B1587: P996P358 | C1587: ES | D1587: =VLOOKUP(Tabela1[[#This Row],[Origem]], 'Perguntas 1 a 24'!$J$28:$K$34, 2, 0) -> Sudeste | E1587: =Tabela1[[#This Row],[Descrição]]&"-"&Tabela1[[#This Row],[Código]]&"/"&Tabela1[[#This Row],[Origem]] -> Cefolado-P996P358/ES | F1587: 46393 | G1587: {=_xlfn.IFS(AND(Tabela1[[#This Row],[Data de Validade]]<= DATE(2025, 12, 31), Tabela1[[#This Row],[Custo de Produção]]>50000), "Urgente e Caro", AND(Tabela1[[#This Row],[Data de Validade]]<= DATE(2025, 12, 31), Tabela1[[#This Row],[Custo de Produção]]<= 50000), "Urgente", AND(F1587>= DATE(2026,1,1), F1587<= DATE(2028, 12, 31), J1587>50000), "Pendente e Caro", AND(F1587>= DATE(2026,1,1), F1587<= DATE(2028, 12, 31), J1587<=50000), "Pendente", F1587>= DATE(2029,1,1), "Não prioeitário")} -> Pendente | H1587: =YEAR(Tabela1[[#This Row],[Data de Validade]]) -> 2027 | I1587: =MONTH(Tabela1[[#This Row],[Data de Validade]]) -> 1 | J1587: 20139 | K1587: Holanda | N1587: P996P358 | O1587: =COUNTIFS(B:B,N1587) -> 1
A1588: Pefunotifa | B1588: H863P859 | C1588: GO | D1588: =VLOOKUP(Tabela1[[#This Row],[Origem]], 'Perguntas 1 a 24'!$J$28:$K$34, 2, 0) -> Centro-Oeste | E1588: =Tabela1[[#This Row],[Descrição]]&"-"&Tabela1[[#This Row],[Código]]&"/"&Tabela1[[#This Row],[Origem]] -> Pefunotifa-H863P859/GO | F1588: 46395 | G1588: {=_xlfn.IFS(AND(Tabela1[[#This Row],[Data de Validade]]<= DATE(2025, 12, 31), Tabela1[[#This Row],[Custo de Produção]]>50000), "Urgente e Caro", AND(Tabela1[[#This Row],[Data de Validade]]<= DATE(2025, 12, 31), Tabela1[[#This Row],[Custo de Produção]]<= 50000), "Urgente", AND(F1588>= DATE(2026,1,1), F1588<= DATE(2028, 12, 31), J1588>50000), "Pendente e Caro", AND(F1588>= DATE(2026,1,1), F1588<= DATE(2028, 12, 31), J1588<=50000), "Pendente", F1588>= DATE(2029,1,1), "Não prioeitário")} -> Pendente | H1588: =YEAR(Tabela1[[#This Row],[Data de Validade]]) -> 2027 | I1588: =MONTH(Tabela1[[#This Row],[Data de Validade]]) -> 1 | J1588: 29827 | K1588: Austrália | N1588: H863P859 | O1588: =COUNTIFS(B:B,N1588) -> 1
A1589: Cetame | B1589: P187H652 | C1589: GO | D1589: =VLOOKUP(Tabela1[[#This Row],[Origem]], 'Perguntas 1 a 24'!$J$28:$K$34, 2, 0) -> Centro-Oeste | E1589: =Tabela1[[#This Row],[Descrição]]&"-"&Tabela1[[#This Row],[Código]]&"/"&Tabela1[[#This Row],[Origem]] -> Cetame-P187H652/GO | F1589: 46397 | G1589: {=_xlfn.IFS(AND(Tabela1[[#This Row],[Data de Validade]]<= DATE(2025, 12, 31), Tabela1[[#This Row],[Custo de Produção]]>50000), "Urgente e Caro", AND(Tabela1[[#This Row],[Data de Validade]]<= DATE(2025, 12, 31), Tabela1[[#This Row],[Custo de Produção]]<= 50000), "Urgente", AND(F1589>= DATE(2026,1,1), F1589<= DATE(2028, 12, 31), J1589>50000), "Pendente e Caro", AND(F1589>= DATE(2026,1,1), F1589<= DATE(2028, 12, 31), J1589<=50000), "Pendente", F1589>= DATE(2029,1,1), "Não prioeitário")} -> Pendente | H1589: =YEAR(Tabela1[[#This Row],[Data de Validade]]) -> 2027 | I1589: =MONTH(Tabela1[[#This Row],[Data de Validade]]) -> 1 | J1589: 34826 | K1589: Holanda | N1589: P187H652 | O1589: =COUNTIFS(B:B,N1589) -> 1
A1590: Vitagu | B1590: H635P832 | C1590: GO | D1590: =VLOOKUP(Tabela1[[#This Row],[Origem]], 'Perguntas 1 a 24'!$J$28:$K$34, 2, 0) -> Centro-Oeste | E1590: =Tabela1[[#This Row],[Descrição]]&"-"&Tabela1[[#This Row],[Código]]&"/"&Tabela1[[#This Row],[Origem]] -> Vitagu-H635P832/GO | F1590: 46398 | G1590: {=_xlfn.IFS(AND(Tabela1[[#This Row],[Data de Validade]]<= DATE(2025, 12, 31), Tabela1[[#This Row],[Custo de Produção]]>50000), "Urgente e Caro", AND(Tabela1[[#This Row],[Data de Validade]]<= DATE(2025, 12, 31), Tabela1[[#This Row],[Custo de Produção]]<= 50000), "Urgente", AND(F1590>= DATE(2026,1,1), F1590<= DATE(2028, 12, 31), J1590>50000), "Pendente e Caro", AND(F1590>= DATE(2026,1,1), F1590<= DATE(2028, 12, 31), J1590<=50000), "Pendente", F1590>= DATE(2029,1,1), "Não prioeitário")} -> Pendente e Caro | H1590: =YEAR(Tabela1[[#This Row],[Data de Validade]]) -> 2027 | I1590: =MONTH(Tabela1[[#This Row],[Data de Validade]]) -> 1 | J1590: 68744 | K1590: Espanha | N1590: H635P832 | O1590: =COUNTIFS(B:B,N1590) -> 1
A1591: Ruruperave | B1591: H159H591 | C1591: MA | D1591: =VLOOKUP(Tabela1[[#This Row],[Origem]], 'Perguntas 1 a 24'!$J$28:$K$34, 2, 0) -> Nordeste | E1591: =Tabela1[[#This Row],[Descrição]]&"-"&Tabela1[[#This Row],[Código]]&"/"&Tabela1[[#This Row],[Origem]] -> Ruruperave-H159H591/MA | F1591: 46399 | G1591: {=_xlfn.IFS(AND(Tabela1[[#This Row],[Data de Validade]]<= DATE(2025, 12, 31), Tabela1[[#This Row],[Custo de Produção]]>50000), "Urgente e Caro", AND(Tabela1[[#This Row],[Data de Validade]]<= DATE(2025, 12, 31), Tabela1[[#This Row],[Custo de Produção]]<= 50000), "Urgente", AND(F1591>= DATE(2026,1,1), F1591<= DATE(2028, 12, 31), J1591>50000), "Pendente e Caro", AND(F1591>= DATE(2026,1,1), F1591<= DATE(2028, 12, 31), J1591<=50000), "Pendente", F1591>= DATE(2029,1,1), "Não prioeitário")} -> Pendente e Caro | H1591: =YEAR(Tabela1[[#This Row],[Data de Validade]]) -> 2027 | I1591: =MONTH(Tabela1[[#This Row],[Data de Validade]]) -> 1 | J1591: 76130 | K1591: Espanha | N1591: H159H591 | O1591: =COUNTIFS(B:B,N1591) -> 1
A1592: Pavopavu | B1592: P374H788 | C1592: MG | D1592: =VLOOKUP(Tabela1[[#This Row],[Origem]], 'Perguntas 1 a 24'!$J$28:$K$34, 2, 0) -> Sudeste | E1592: =Tabela1[[#This Row],[Descrição]]&"-"&Tabela1[[#This Row],[Código]]&"/"&Tabela1[[#This Row],[Origem]] -> Pavopavu-P374H788/MG | F1592: 46401 | G1592: {=_xlfn.IFS(AND(Tabela1[[#This Row],[Data de Validade]]<= DATE(2025, 12, 31), Tabela1[[#This Row],[Custo de Produção]]>50000), "Urgente e Caro", AND(Tabela1[[#This Row],[Data de Validade]]<= DATE(2025, 12, 31), Tabela1[[#This Row],[Custo de Produção]]<= 50000), "Urgente", AND(F1592>= DATE(2026,1,1), F1592<= DATE(2028, 12, 31), J1592>50000), "Pendente e Caro", AND(F1592>= DATE(2026,1,1), F1592<= DATE(2028, 12, 31), J1592<=50000), "Pendente", F1592>= DATE(2029,1,1), "Não prioeitário")} -> Pendente e Caro | H1592: =YEAR(Tabela1[[#This Row],[Data de Validade]]) -> 2027 | I1592: =MONTH(Tabela1[[#This Row],[Data de Validade]]) -> 1 | J1592: 93675 | K1592: Espanha | N1592: P374H788 | O1592: =COUNTIFS(B:B,N1592) -> 1
A1593: Purupetilu | B1593: H678P823 | C1593: ES | D1593: =VLOOKUP(Tabela1[[#This Row],[Origem]], 'Perguntas 1 a 24'!$J$28:$K$34, 2, 0) -> Sudeste | E1593: =Tabela1[[#This Row],[Descrição]]&"-"&Tabela1[[#This Row],[Código]]&"/"&Tabela1[[#This Row],[Origem]] -> Purupetilu-H678P823/ES | F1593: 46402 | G1593: {=_xlfn.IFS(AND(Tabela1[[#This Row],[Data de Validade]]<= DATE(2025, 12, 31), Tabela1[[#This Row],[Custo de Produção]]>50000), "Urgente e Caro", AND(Tabela1[[#This Row],[Data de Validade]]<= DATE(2025, 12, 31), Tabela1[[#This Row],[Custo de Produção]]<= 50000), "Urgente", AND(F1593>= DATE(2026,1,1), F1593<= DATE(2028, 12, 31), J1593>50000), "Pendente e Caro", AND(F1593>= DATE(2026,1,1), F1593<= DATE(2028, 12, 31), J1593<=50000), "Pendente", F1593>= DATE(2029,1,1), "Não prioeitário")} -> Pendente e Caro | H1593: =YEAR(Tabela1[[#This Row],[Data de Validade]]) -> 2027 | I1593: =MONTH(Tabela1[[#This Row],[Data de Validade]]) -> 1 | J1593: 61661 | K1593: Espanha | N1593: H678P823 | O1593: =COUNTIFS(B:B,N1593) -> 1
A1594: Repugo | B1594: H412P682 | C1594: MA | D1594: =VLOOKUP(Tabela1[[#This Row],[Origem]], 'Perguntas 1 a 24'!$J$28:$K$34, 2, 0) -> Nordeste | E1594: =Tabela1[[#This Row],[Descrição]]&"-"&Tabela1[[#This Row],[Código]]&"/"&Tabela1[[#This Row],[Origem]] -> Repugo-H412P682/MA | F1594: 46403 | G1594: {=_xlfn.IFS(AND(Tabela1[[#This Row],[Data de Validade]]<= DATE(2025, 12, 31), Tabela1[[#This Row],[Custo de Produção]]>50000), "Urgente e Caro", AND(Tabela1[[#This Row],[Data de Validade]]<= DATE(2025, 12, 31), Tabela1[[#This Row],[Custo de Produção]]<= 50000), "Urgente", AND(F1594>= DATE(2026,1,1), F1594<= DATE(2028, 12, 31), J1594>50000), "Pendente e Caro", AND(F1594>= DATE(2026,1,1), F1594<= DATE(2028, 12, 31), J1594<=50000), "Pendente", F1594>= DATE(2029,1,1), "Não prioeitário")} -> Pendente e Caro | H1594: =YEAR(Tabela1[[#This Row],[Data de Validade]]) -> 2027 | I1594: =MONTH(Tabela1[[#This Row],[Data de Validade]]) -> 1 | J1594: 107539 | K1594: Espanha | N1594: H412P682 | O1594: =COUNTIFS(B:B,N1594) -> 1
A1595: Litavolu | B1595: H873P158 | C1595: SP | D1595: =VLOOKUP(Tabela1[[#This Row],[Origem]], 'Perguntas 1 a 24'!$J$28:$K$34, 2, 0) -> Sudeste | E1595: =Tabela1[[#This Row],[Descrição]]&"-"&Tabela1[[#This Row],[Código]]&"/"&Tabela1[[#This Row],[Origem]] -> Litavolu-H873P158/SP | F1595: 46403 | G1595: {=_xlfn.IFS(AND(Tabela1[[#This Row],[Data de Validade]]<= DATE(2025, 12, 31), Tabela1[[#This Row],[Custo de Produção]]>50000), "Urgente e Caro", AND(Tabela1[[#This Row],[Data de Validade]]<= DATE(2025, 12, 31), Tabela1[[#This Row],[Custo de Produção]]<= 50000), "Urgente", AND(F1595>= DATE(2026,1,1), F1595<= DATE(2028, 12, 31), J1595>50000), "Pendente e Caro", AND(F1595>= DATE(2026,1,1), F1595<= DATE(2028, 12, 31), J1595<=50000), "Pendente", F1595>= DATE(2029,1,1), "Não prioeitário")} -> Pendente e Caro | H1595: =YEAR(Tabela1[[#This Row],[Data de Validade]]) -> 2027 | I1595: =MONTH(Tabela1[[#This Row],[Data de Validade]]) -> 1 | J1595: 78178 | K1595: Holanda | N1595: H873P158 | O1595: =COUNTIFS(B:B,N1595) -> 1
A1596: Dovetumofi | B1596: P976P355 | C1596: MA | D1596: =VLOOKUP(Tabela1[[#This Row],[Origem]], 'Perguntas 1 a 24'!$J$28:$K$34, 2, 0) -> Nordeste | E1596: =Tabela1[[#This Row],[Descrição]]&"-"&Tabela1[[#This Row],[Código]]&"/"&Tabela1[[#This Row],[Origem]] -> Dovetumofi-P976P355/MA | F1596: 46405 | G1596: {=_xlfn.IFS(AND(Tabela1[[#This Row],[Data de Validade]]<= DATE(2025, 12, 31), Tabela1[[#This Row],[Custo de Produção]]>50000), "Urgente e Caro", AND(Tabela1[[#This Row],[Data de Validade]]<= DATE(2025, 12, 31), Tabela1[[#This Row],[Custo de Produção]]<= 50000), "Urgente", AND(F1596>= DATE(2026,1,1), F1596<= DATE(2028, 12, 31), J1596>50000), "Pendente e Caro", AND(F1596>= DATE(2026,1,1), F1596<= DATE(2028, 12, 31), J1596<=50000), "Pendente", F1596>= DATE(2029,1,1), "Não prioeitário")} -> Pendente e Caro | H1596: =YEAR(Tabela1[[#This Row],[Data de Validade]]) -> 2027 | I1596: =MONTH(Tabela1[[#This Row],[Data de Validade]]) -> 1 | J1596: 108659 | K1596: Austrália | N1596: P976P355 | O1596: =COUNTIFS(B:B,N1596) -> 1
A1597: Levafi | B1597: P152P474 | C1597: SP | D1597: =VLOOKUP(Tabela1[[#This Row],[Origem]], 'Perguntas 1 a 24'!$J$28:$K$34, 2, 0) -> Sudeste | E1597: =Tabela1[[#This Row],[Descrição]]&"-"&Tabela1[[#This Row],[Código]]&"/"&Tabela1[[#This Row],[Origem]] -> Levafi-P152P474/SP | F1597: 46405 | G1597: {=_xlfn.IFS(AND(Tabela1[[#This Row],[Data de Validade]]<= DATE(2025, 12, 31), Tabela1[[#This Row],[Custo de Produção]]>50000), "Urgente e Caro", AND(Tabela1[[#This Row],[Data de Validade]]<= DATE(2025, 12, 31), Tabela1[[#This Row],[Custo de Produção]]<= 50000), "Urgente", AND(F1597>= DATE(2026,1,1), F1597<= DATE(2028, 12, 31), J1597>50000), "Pendente e Caro", AND(F1597>= DATE(2026,1,1), F1597<= DATE(2028, 12, 31), J1597<=50000), "Pendente", F1597>= DATE(2029,1,1), "Não prioeitário")} -> Pendente | H1597: =YEAR(Tabela1[[#This Row],[Data de Validade]]) -> 2027 | I1597: =MONTH(Tabela1[[#This Row],[Data de Validade]]) -> 1 | J1597: 41487 | K1597: Panamá | N1597: P152P474 | O1597: =COUNTIFS(B:B,N1597) -> 1
... A3843: Cupara | B3843: P724P994 | C3843: SP | D3843: =VLOOKUP(Tabela1[[#This Row],[Origem]], 'Perguntas 1 a 24'!$J$28:$K$34, 2, 0) -> Sudeste | E3843: =Tabela1[[#This Row],[Descrição]]&"-"&Tabela1[[#This Row],[Código]]&"/"&Tabela1[[#This Row],[Origem]] -> Cupara-P724P994/SP | F3843: 47815 | G3843: {=_xlfn.IFS(AND(Tabela1[[#This Row],[Data de Validade]]<= DATE(2025, 12, 31), Tabela1[[#This Row],[Custo de Produção]]>50000), "Urgente e Caro", AND(Tabela1[[#This Row],[Data de Validade]]<= DATE(2025, 12, 31), Tabela1[[#This Row],[Custo de Produção]]<= 50000), "Urgente", AND(F3843>= DATE(2026,1,1), F3843<= DATE(2028, 12, 31), J3843>50000), "Pendente e Caro", AND(F3843>= DATE(2026,1,1), F3843<= DATE(2028, 12, 31), J3843<=50000), "Pendente", F3843>= DATE(2029,1,1), "Não prioeitário")} -> Não prioeitário | H3843: =YEAR(Tabela1[[#This Row],[Data de Validade]]) -> 2030 | I3843: =MONTH(Tabela1[[#This Row],[Data de Validade]]) -> 11 | J3843: 60286 | K3843: Espanha | N3843: P276P477 | O3843: =COUNTIFS(B:B,N3843) -> 1
A3844: Dimuvime | B3844: H596P577 | C3844: RJ | D3844: =VLOOKUP(Tabela1[[#This Row],[Origem]], 'Perguntas 1 a 24'!$J$28:$K$34, 2, 0) -> Sudeste | E3844: =Tabela1[[#This Row],[Descrição]]&"-"&Tabela1[[#This Row],[Código]]&"/"&Tabela1[[#This Row],[Origem]] -> Dimuvime-H596P577/RJ | F3844: 47815 | G3844: {=_xlfn.IFS(AND(Tabela1[[#This Row],[Data de Validade]]<= DATE(2025, 12, 31), Tabela1[[#This Row],[Custo de Produção]]>50000), "Urgente e Caro", AND(Tabela1[[#This Row],[Data de Validade]]<= DATE(2025, 12, 31), Tabela1[[#This Row],[Custo de Produção]]<= 50000), "Urgente", AND(F3844>= DATE(2026,1,1), F3844<= DATE(2028, 12, 31), J3844>50000), "Pendente e Caro", AND(F3844>= DATE(2026,1,1), F3844<= DATE(2028, 12, 31), J3844<=50000), "Pendente", F3844>= DATE(2029,1,1), "Não prioeitário")} -> Não prioeitário | H3844: =YEAR(Tabela1[[#This Row],[Data de Validade]]) -> 2030 | I3844: =MONTH(Tabela1[[#This Row],[Data de Validade]]) -> 11 | J3844: 22548 | K3844: Panamá | N3844: 0 | O3844: =COUNTIFS(B:B,N3844) -> 0
A3845: Ciculi | B3845: H719P191 | C3845: MA | D3845: =VLOOKUP(Tabela1[[#This Row],[Origem]], 'Perguntas 1 a 24'!$J$28:$K$34, 2, 0) -> Nordeste | E3845: =Tabela1[[#This Row],[Descrição]]&"-"&Tabela1[[#This Row],[Código]]&"/"&Tabela1[[#This Row],[Origem]] -> Ciculi-H719P191/MA | F3845: 47817 | G3845: {=_xlfn.IFS(AND(Tabela1[[#This Row],[Data de Validade]]<= DATE(2025, 12, 31), Tabela1[[#This Row],[Custo de Produção]]>50000), "Urgente e Caro", AND(Tabela1[[#This Row],[Data de Validade]]<= DATE(2025, 12, 31), Tabela1[[#This Row],[Custo de Produção]]<= 50000), "Urgente", AND(F3845>= DATE(2026,1,1), F3845<= DATE(2028, 12, 31), J3845>50000), "Pendente e Caro", AND(F3845>= DATE(2026,1,1), F3845<= DATE(2028, 12, 31), J3845<=50000), "Pendente", F3845>= DATE(2029,1,1), "Não prioeitário")} -> Não prioeitário | H3845: =YEAR(Tabela1[[#This Row],[Data de Validade]]) -> 2030 | I3845: =MONTH(Tabela1[[#This Row],[Data de Validade]]) -> 11 | J3845: 71304 | K3845: Panamá
A3846: Togupori | B3846: H947P779 | C3846: GO | D3846: =VLOOKUP(Tabela1[[#This Row],[Origem]], 'Perguntas 1 a 24'!$J$28:$K$34, 2, 0) -> Centro-Oeste | E3846: =Tabela1[[#This Row],[Descrição]]&"-"&Tabela1[[#This Row],[Código]]&"/"&Tabela1[[#This Row],[Origem]] -> Togupori-H947P779/GO | F3846: 47817 | G3846: {=_xlfn.IFS(AND(Tabela1[[#This Row],[Data de Validade]]<= DATE(2025, 12, 31), Tabela1[[#This Row],[Custo de Produção]]>50000), "Urgente e Caro", AND(Tabela1[[#This Row],[Data de Validade]]<= DATE(2025, 12, 31), Tabela1[[#This Row],[Custo de Produção]]<= 50000), "Urgente", AND(F3846>= DATE(2026,1,1), F3846<= DATE(2028, 12, 31), J3846>50000), "Pendente e Caro", AND(F3846>= DATE(2026,1,1), F3846<= DATE(2028, 12, 31), J3846<=50000), "Pendente", F3846>= DATE(2029,1,1), "Não prioeitário")} -> Não prioeitário | H3846: =YEAR(Tabela1[[#This Row],[Data de Validade]]) -> 2030 | I3846: =MONTH(Tabela1[[#This Row],[Data de Validade]]) -> 11 | J3846: 29933 | K3846: Espanha
A3847: Poputa | B3847: P347H837 | C3847: MA | D3847: =VLOOKUP(Tabela1[[#This Row],[Origem]], 'Perguntas 1 a 24'!$J$28:$K$34, 2, 0) -> Nordeste | E3847: =Tabela1[[#This Row],[Descrição]]&"-"&Tabela1[[#This Row],[Código]]&"/"&Tabela1[[#This Row],[Origem]] -> Poputa-P347H837/MA | F3847: 47818 | G3847: {=_xlfn.IFS(AND(Tabela1[[#This Row],[Data de Validade]]<= DATE(2025, 12, 31), Tabela1[[#This Row],[Custo de Produção]]>50000), "Urgente e Caro", AND(Tabela1[[#This Row],[Data de Validade]]<= DATE(2025, 12, 31), Tabela1[[#This Row],[Custo de Produção]]<= 50000), "Urgente", AND(F3847>= DATE(2026,1,1), F3847<= DATE(2028, 12, 31), J3847>50000), "Pendente e Caro", AND(F3847>= DATE(2026,1,1), F3847<= DATE(2028, 12, 31), J3847<=50000), "Pendente", F3847>= DATE(2029,1,1), "Não prioeitário")} -> Não prioeitário | H3847: =YEAR(Tabela1[[#This Row],[Data de Validade]]) -> 2030 | I3847: =MONTH(Tabela1[[#This Row],[Data de Validade]]) -> 12 | J3847: 60007 | K3847: Espanha
A3848: Poruritimi | B3848: P563P261 | C3848: MG | D3848: =VLOOKUP(Tabela1[[#This Row],[Origem]], 'Perguntas 1 a 24'!$J$28:$K$34, 2, 0) -> Sudeste | E3848: =Tabela1[[#This Row],[Descrição]]&"-"&Tabela1[[#This Row],[Código]]&"/"&Tabela1[[#This Row],[Origem]] -> Poruritimi-P563P261/MG | F3848: 47818 | G3848: {=_xlfn.IFS(AND(Tabela1[[#This Row],[Data de Validade]]<= DATE(2025, 12, 31), Tabela1[[#This Row],[Custo de Produção]]>50000), "Urgente e Caro", AND(Tabela1[[#This Row],[Data de Validade]]<= DATE(2025, 12, 31), Tabela1[[#This Row],[Custo de Produção]]<= 50000), "Urgente", AND(F3848>= DATE(2026,1,1), F3848<= DATE(2028, 12, 31), J3848>50000), "Pendente e Caro", AND(F3848>= DATE(2026,1,1), F3848<= DATE(2028, 12, 31), J3848<=50000), "Pendente", F3848>= DATE(2029,1,1), "Não prioeitário")} -> Não prioeitário | H3848: =YEAR(Tabela1[[#This Row],[Data de Validade]]) -> 2030 | I3848: =MONTH(Tabela1[[#This Row],[Data de Validade]]) -> 12 | J3848: 54354 | K3848: Espanha
A3849: Pilipudutu | B3849: H377H966 | C3849: GO | D3849: =VLOOKUP(Tabela1[[#This Row],[Origem]], 'Perguntas 1 a 24'!$J$28:$K$34, 2, 0) -> Centro-Oeste | E3849: =Tabela1[[#This Row],[Descrição]]&"-"&Tabela1[[#This Row],[Código]]&"/"&Tabela1[[#This Row],[Origem]] -> Pilipudutu-H377H966/GO | F3849: 47819 | G3849: {=_xlfn.IFS(AND(Tabela1[[#This Row],[Data de Validade]]<= DATE(2025, 12, 31), Tabela1[[#This Row],[Custo de Produção]]>50000), "Urgente e Caro", AND(Tabela1[[#This Row],[Data de Validade]]<= DATE(2025, 12, 31), Tabela1[[#This Row],[Custo de Produção]]<= 50000), "Urgente", AND(F3849>= DATE(2026,1,1), F3849<= DATE(2028, 12, 31), J3849>50000), "Pendente e Caro", AND(F3849>= DATE(2026,1,1), F3849<= DATE(2028, 12, 31), J3849<=50000), "Pendente", F3849>= DATE(2029,1,1), "Não prioeitário")} -> Não prioeitário | H3849: =YEAR(Tabela1[[#This Row],[Data de Validade]]) -> 2030 | I3849: =MONTH(Tabela1[[#This Row],[Data de Validade]]) -> 12 | J3849: 85095 | K3849: Panamá
A3850: Teludife | B3850: H721P935 | C3850: MG | D3850: =VLOOKUP(Tabela1[[#This Row],[Origem]], 'Perguntas 1 a 24'!$J$28:$K$34, 2, 0) -> Sudeste | E3850: =Tabela1[[#This Row],[Descrição]]&"-"&Tabela1[[#This Row],[Código]]&"/"&Tabela1[[#This Row],[Origem]] -> Teludife-H721P935/MG | F3850: 47819 | G3850: {=_xlfn.IFS(AND(Tabela1[[#This Row],[Data de Validade]]<= DATE(2025, 12, 31), Tabela1[[#This Row],[Custo de Produção]]>50000), "Urgente e Caro", AND(Tabela1[[#This Row],[Data de Validade]]<= DATE(2025, 12, 31), Tabela1[[#This Row],[Custo de Produção]]<= 50000), "Urgente", AND(F3850>= DATE(2026,1,1), F3850<= DATE(2028, 12, 31), J3850>50000), "Pendente e Caro", AND(F3850>= DATE(2026,1,1), F3850<= DATE(2028, 12, 31), J3850<=50000), "Pendente", F3850>= DATE(2029,1,1), "Não prioeitário")} -> Não prioeitário | H3850: =YEAR(Tabela1[[#This Row],[Data de Validade]]) -> 2030 | I3850: =MONTH(Tabela1[[#This Row],[Data de Validade]]) -> 12 | J3850: 80868 | K3850: Panamá
A3851: Comecope | B3851: P551H135 | C3851: AL | D3851: =VLOOKUP(Tabela1[[#This Row],[Origem]], 'Perguntas 1 a 24'!$J$28:$K$34, 2, 0) -> Nordeste | E3851: =Tabela1[[#This Row],[Descrição]]&"-"&Tabela1[[#This Row],[Código]]&"/"&Tabela1[[#This Row],[Origem]] -> Comecope-P551H135/AL | F3851: 47819 | G3851: {=_xlfn.IFS(AND(Tabela1[[#This Row],[Data de Validade]]<= DATE(2025, 12, 31), Tabela1[[#This Row],[Custo de Produção]]>50000), "Urgente e Caro", AND(Tabela1[[#This Row],[Data de Validade]]<= DATE(2025, 12, 31), Tabela1[[#This Row],[Custo de Produção]]<= 50000), "Urgente", AND(F3851>= DATE(2026,1,1), F3851<= DATE(2028, 12, 31), J3851>50000), "Pendente e Caro", AND(F3851>= DATE(2026,1,1), F3851<= DATE(2028, 12, 31), J3851<=50000), "Pendente", F3851>= DATE(2029,1,1), "Não prioeitário")} -> Não prioeitário | H3851: =YEAR(Tabela1[[#This Row],[Data de Validade]]) -> 2030 | I3851: =MONTH(Tabela1[[#This Row],[Data de Validade]]) -> 12 | J3851: 47577 | K3851: Austrália
A3852: Dipumu | B3852: H429P414 | C3852: MA | D3852: =VLOOKUP(Tabela1[[#This Row],[Origem]], 'Perguntas 1 a 24'!$J$28:$K$34, 2, 0) -> Nordeste | E3852: =Tabela1[[#This Row],[Descrição]]&"-"&Tabela1[[#This Row],[Código]]&"/"&Tabela1[[#This Row],[Origem]] -> Dipumu-H429P414/MA | F3852: 47820 | G3852: {=_xlfn.IFS(AND(Tabela1[[#This Row],[Data de Validade]]<= DATE(2025, 12, 31), Tabela1[[#This Row],[Custo de Produção]]>50000), "Urgente e Caro", AND(Tabela1[[#This Row],[Data de Validade]]<= DATE(2025, 12, 31), Tabela1[[#This Row],[Custo de Produção]]<= 50000), "Urgente", AND(F3852>= DATE(2026,1,1), F3852<= DATE(2028, 12, 31), J3852>50000), "Pendente e Caro", AND(F3852>= DATE(2026,1,1), F3852<= DATE(2028, 12, 31), J3852<=50000), "Pendente", F3852>= DATE(2029,1,1), "Não prioeitário")} -> Não prioeitário | H3852: =YEAR(Tabela1[[#This Row],[Data de Validade]]) -> 2030 | I3852: =MONTH(Tabela1[[#This Row],[Data de Validade]]) -> 12 | J3852: 106881 | K3852: Holanda
A3853: Tapavucome | B3853: P182P543 | C3853: MG | D3853: =VLOOKUP(Tabela1[[#This Row],[Origem]], 'Perguntas 1 a 24'!$J$28:$K$34, 2, 0) -> Sudeste | E3853: =Tabela1[[#This Row],[Descrição]]&"-"&Tabela1[[#This Row],[Código]]&"/"&Tabela1[[#This Row],[Origem]] -> Tapavucome-P182P543/MG | F3853: 47821 | G3853: {=_xlfn.IFS(AND(Tabela1[[#This Row],[Data de Validade]]<= DATE(2025, 12, 31), Tabela1[[#This Row],[Custo de Produção]]>50000), "Urgente e Caro", AND(Tabela1[[#This Row],[Data de Validade]]<= DATE(2025, 12, 31), Tabela1[[#This Row],[Custo de Produção]]<= 50000), "Urgente", AND(F3853>= DATE(2026,1,1), F3853<= DATE(2028, 12, 31), J3853>50000), "Pendente e Caro", AND(F3853>= DATE(2026,1,1), F3853<= DATE(2028, 12, 31), J3853<=50000), "Pendente", F3853>= DATE(2029,1,1), "Não prioeitário")} -> Não prioeitário | H3853: =YEAR(Tabela1[[#This Row],[Data de Validade]]) -> 2030 | I3853: =MONTH(Tabela1[[#This Row],[Data de Validade]]) -> 12 | J3853: 77032 | K3853: Espanha
A3854: Toperuvutu | B3854: P577P867 | C3854: AL | D3854: =VLOOKUP(Tabela1[[#This Row],[Origem]], 'Perguntas 1 a 24'!$J$28:$K$34, 2, 0) -> Nordeste | E3854: =Tabela1[[#This Row],[Descrição]]&"-"&Tabela1[[#This Row],[Código]]&"/"&Tabela1[[#This Row],[Origem]] -> Toperuvutu-P577P867/AL | F3854: 47821 | G3854: {=_xlfn.IFS(AND(Tabela1[[#This Row],[Data de Validade]]<= DATE(2025, 12, 31), Tabela1[[#This Row],[Custo de Produção]]>50000), "Urgente e Caro", AND(Tabela1[[#This Row],[Data de Validade]]<= DATE(2025, 12, 31), Tabela1[[#This Row],[Custo de Produção]]<= 50000), "Urgente", AND(F3854>= DATE(2026,1,1), F3854<= DATE(2028, 12, 31), J3854>50000), "Pendente e Caro", AND(F3854>= DATE(2026,1,1), F3854<= DATE(2028, 12, 31), J3854<=50000), "Pendente", F3854>= DATE(2029,1,1), "Não prioeitário")} -> Não prioeitário | H3854: =YEAR(Tabela1[[#This Row],[Data de Validade]]) -> 2030 | I3854: =MONTH(Tabela1[[#This Row],[Data de Validade]]) -> 12 | J3854: 39965 | K3854: Holanda
A3855: Gipuri | B3855: P461H612 | C3855: ES | D3855: =VLOOKUP(Tabela1[[#This Row],[Origem]], 'Perguntas 1 a 24'!$J$28:$K$34, 2, 0) -> Sudeste | E3855: =Tabela1[[#This Row],[Descrição]]&"-"&Tabela1[[#This Row],[Código]]&"/"&Tabela1[[#This Row],[Origem]] -> Gipuri-P461H612/ES | F3855: 47822 | G3855: {=_xlfn.IFS(AND(Tabela1[[#This Row],[Data de Validade]]<= DATE(2025, 12, 31), Tabela1[[#This Row],[Custo de Produção]]>50000), "Urgente e Caro", AND(Tabela1[[#This Row],[Data de Validade]]<= DATE(2025, 12, 31), Tabela1[[#This Row],[Custo de Produção]]<= 50000), "Urgente", AND(F3855>= DATE(2026,1,1), F3855<= DATE(2028, 12, 31), J3855>50000), "Pendente e Caro", AND(F3855>= DATE(2026,1,1), F3855<= DATE(2028, 12, 31), J3855<=50000), "Pendente", F3855>= DATE(2029,1,1), "Não prioeitário")} -> Não prioeitário | H3855: =YEAR(Tabela1[[#This Row],[Data de Validade]]) -> 2030 | I3855: =MONTH(Tabela1[[#This Row],[Data de Validade]]) -> 12 | J3855: 50344 | K3855: Austrália
A3856: Docimepepo | B3856: P276P477 | C3856: ES | D3856: =VLOOKUP(Tabela1[[#This Row],[Origem]], 'Perguntas 1 a 24'!$J$28:$K$34, 2, 0) -> Sudeste | E3856: =Tabela1[[#This Row],[Descrição]]&"-"&Tabela1[[#This Row],[Código]]&"/"&Tabela1[[#This Row],[Origem]] -> Docimepepo-P276P477/ES | F3856: 47822 | G3856: {=_xlfn.IFS(AND(Tabela1[[#This Row],[Data de Validade]]<= DATE(2025, 12, 31), Tabela1[[#This Row],[Custo de Produção]]>50000), "Urgente e Caro", AND(Tabela1[[#This Row],[Data de Validade]]<= DATE(2025, 12, 31), Tabela1[[#This Row],[Custo de Produção]]<= 50000), "Urgente", AND(F3856>= DATE(2026,1,1), F3856<= DATE(2028, 12, 31), J3856>50000), "Pendente e Caro", AND(F3856>= DATE(2026,1,1), F3856<= DATE(2028, 12, 31), J3856<=50000), "Pendente", F3856>= DATE(2029,1,1), "Não prioeitário")} -> Não prioeitário | H3856: =YEAR(Tabela1[[#This Row],[Data de Validade]]) -> 2030 | I3856: =MONTH(Tabela1[[#This Row],[Data de Validade]]) -> 12 | J3856: 29585 | K3856: Holanda

Sheet Perguntas 1 a 24
C2: Separe as informações da base, deixando cada campo em uma coluna. Oculte as linhas de grade da planilha | J2: Crie na base de dados uma coluna com a chave do produto. Essa chave será a junção do código do produto, seu nome e estado de origem no seguinte formato: nome-código/origem. Por exemplo, o produto de nome Nocogifo, código P931H285 e origem MA terá a chave Nocogifo-P931H285/MA
C5: Formate a base de dados, aplicando formatação de moeda e de data abreviada nas colunas que se adequam. Ajuste também a largura das colunas e as cores das células: o preenchimento da primeira linha deve ser azul, o preenchimento das demais linhas será cinza e a cor da fonte de todas as linhas será preta. Use os tons das células abaixo:
J6: Na Base 1 existem códigos que aparecem mais do que uma vez na lista. Qual é o número máximo de aparições de um mesmo código na lista?
J9: =MAX('Base de Dados'!O:O) -> 6
E10: Fonte
J11: Qual a descrição, origem e data de validade dos 8 códigos abaixo? Não faça qualquer alteração na base de dados para responder essa pergunta. Caso algum código não seja encontrado, exibir a mensagem "não encontrado".
C12: O que é necessário para adicionar uma segmentação de dados nessa base de dados sem o uso de tabela dinâmica?
J14: Código | K14: Data de Validade | L14: Origem | M14: Descrição
C15: Formate a base como tabela, sem perder a formatação aplicada no exercício dois. | J15: H485H921 | K15: =_xlfn.XLOOKUP($J15,Tabela1[Código], Tabela1[Data de Validade],"Não",0) -> 46319 | L15: =_xlfn.XLOOKUP(J15,'Base de Dados'!B:B, 'Base de Dados'!C:C,"Não",0) -> RJ | M15: =_xlfn.XLOOKUP($J15, 'Base de Dados'!B:B, 'Base de Dados'!A:A, "Não", 0) -> Malari
J16: P469P428 | K16: =_xlfn.XLOOKUP($J16,Tabela1[Código], Tabela1[Data de Validade],"Não",0) -> 47476 | L16: =_xlfn.XLOOKUP(J16,'Base de Dados'!B:B, 'Base de Dados'!C:C,"Não",0) -> RJ | M16: =_xlfn.XLOOKUP($J16, 'Base de Dados'!B:B, 'Base de Dados'!A:A, "Não", 0) -> Tipafa
C17: Adicione uma formatação condicional de semáforo, colocando sinal vermelho quando custo de produção for maior que R$100.000, sinal amarelo com custo entre R$50.000 e R$100.000 e sinal verde quando for menor que R$50.000 | J17: H3643212 | K17: =_xlfn.XLOOKUP($J17,Tabela1[Código], Tabela1[Data de Validade],"Não",0) -> Não | L17: =_xlfn.XLOOKUP(J17,'Base de Dados'!B:B, 'Base de Dados'!C:C,"Não",0) -> Não | M17: =_xlfn.XLOOKUP($J17, 'Base de Dados'!B:B, 'Base de Dados'!A:A, "Não", 0) -> Não
J18: P577H891 | K18: =_xlfn.XLOOKUP($J18,Tabela1[Código], Tabela1[Data de Validade],"Não",0) -> 46650 | L18: =_xlfn.XLOOKUP(J18,'Base de Dados'!B:B, 'Base de Dados'!C:C,"Não",0) -> RJ | M18: =_xlfn.XLOOKUP($J18, 'Base de Dados'!B:B, 'Base de Dados'!A:A, "Não", 0) -> Vetoci
J19: H298P268 | K19: =_xlfn.XLOOKUP($J19,Tabela1[Código], Tabela1[Data de Validade],"Não",0) -> 46770 | L19: =_xlfn.XLOOKUP(J19,'Base de Dados'!B:B, 'Base de Dados'!C:C,"Não",0) -> GO | M19: =_xlfn.XLOOKUP($J19, 'Base de Dados'!B:B, 'Base de Dados'!A:A, "Não", 0) -> Vidipu
J20: P6545323 | K20: =_xlfn.XLOOKUP($J20,Tabela1[Código], Tabela1[Data de Validade],"Não",0) -> Não | L20: =_xlfn.XLOOKUP(J20,'Base de Dados'!B:B, 'Base de Dados'!C:C,"Não",0) -> Não | M20: =_xlfn.XLOOKUP($J20, 'Base de Dados'!B:B, 'Base de Dados'!A:A, "Não", 0) -> Não
C21: Pinte o preenchimento das células da coluna País de Destino. A cor da célula deve mudar automaticamente quando o País for alterado. Cada país terá uma cor específica conforme abaixo: | J21: H445H467 | K21: =_xlfn.XLOOKUP($J21,Tabela1[Código], Tabela1[Data de Validade],"Não",0) -> 45758 | L21: =_xlfn.XLOOKUP(J21,'Base de Dados'!B:B, 'Base de Dados'!C:C,"Não",0) -> AL | M21: =_xlfn.XLOOKUP($J21, 'Base de Dados'!B:B, 'Base de Dados'!A:A, "Não", 0) -> Rurofelupa
J22: H484H675 | K22: =_xlfn.XLOOKUP($J22,Tabela1[Código], Tabela1[Data de Validade],"Não",0) -> 46926 | L22: =_xlfn.XLOOKUP(J22,'Base de Dados'!B:B, 'Base de Dados'!C:C,"Não",0) -> GO | M22: =_xlfn.XLOOKUP($J22, 'Base de Dados'!B:B, 'Base de Dados'!A:A, "Não", 0) -> Favidufere
C24: Holanda | D24: Austrália | E24: Panamá | F24: Espanha | J24: Crie uma coluna na base de dados com as Regiões de Origem de cada produto de acordo com os Estados de Origem.
C26: Agora pinte a linha inteira de acordo com o País de Destino, não apenas as células da coluna País de Destino. A cor das células da linha deve mudar automaticamente quando o país for alterado.
J27: Estado | K27: Região
J28: AL | K28: Nordeste
J29: ES | K29: Sudeste
C30: Crie um filtro na base de dados e ordene a base de acordo com a data de validade (do mais antigo para o mais novo) | J30: GO | K30: Centro-Oeste
J31: MA | K31: Nordeste
J32: MG | K32: Sudeste
C33: Preencha as células abaixo com o o somatório, média, contagem, valor máximo e mínimo da coluna de custo de produção. Esses valores precisam ser recalculados automaticamente quando os valores da base forem alterados | J33: RJ | K33: Sudeste
J34: SP | K34: Sudeste
J36: Monte um quadro resumo com o custo total de produção levando em consideração a Região de Origem e o País de Destino.
C37: Somatório | D37: Média | E37: Contagem | F37: Máximo | G37: Mínimo
C38: =SUM('Base de Dados'!J:J) -> 272140218 | D38: =AVERAGE('Base de Dados'!J:J) -> 70594.09 | E38: =COUNT('Base de Dados'!J:J) -> 3855 | F38: =MAX('Base de Dados'!J:J) -> 119945 | G38: =MIN('Base de Dados'!J:J) -> 20044 | K38: Austrália | L38: Espanha | M38: Holanda | N38: Panamá
J39: Nordeste | K39: =SUMIFS('Base de Dados'!$J:$J, 'Base de Dados'!$K:$K, 'Perguntas 1 a 24'!K$38,'Base de Dados'!$D:$D, 'Perguntas 1 a 24'!$J39) -> 21582443 | L39: =SUMIFS('Base de Dados'!$J:$J, 'Base de Dados'!$K:$K, 'Perguntas 1 a 24'!L$38,'Base de Dados'!$D:$D, 'Perguntas 1 a 24'!$J39) -> 18432363 | M39: =SUMIFS('Base de Dados'!$J:$J, 'Base de Dados'!$K:$K, 'Perguntas 1 a 24'!M$38,'Base de Dados'!$D:$D, 'Perguntas 1 a 24'!$J39) -> 19384102 | N39: =SUMIFS('Base de Dados'!$J:$J, 'Base de Dados'!$K:$K, 'Perguntas 1 a 24'!N$38,'Base de Dados'!$D:$D, 'Perguntas 1 a 24'!$J39) -> 19329788
C40: Agora preencha o resumo abaixo com as mesmas informações do exercício anterior, mas de forma que os valores sejam atualizados quando os filtros aplicados na base de dados forem alterados. | J40: Sudeste | K40: =SUMIFS('Base de Dados'!$J:$J, 'Base de Dados'!$K:$K, 'Perguntas 1 a 24'!K$38,'Base de Dados'!$D:$D, 'Perguntas 1 a 24'!$J40) -> 37494439 | L40: =SUMIFS('Base de Dados'!$J:$J, 'Base de Dados'!$K:$K, 'Perguntas 1 a 24'!L$38,'Base de Dados'!$D:$D, 'Perguntas 1 a 24'!$J40) -> 38989407 | M40: =SUMIFS('Base de Dados'!$J:$J, 'Base de Dados'!$K:$K, 'Perguntas 1 a 24'!M$38,'Base de Dados'!$D:$D, 'Perguntas 1 a 24'!$J40) -> 38539749 | N40: =SUMIFS('Base de Dados'!$J:$J, 'Base de Dados'!$K:$K, 'Perguntas 1 a 24'!N$38,'Base de Dados'!$D:$D, 'Perguntas 1 a 24'!$J40) -> 37891952
J41: Centro-Oeste | K41: =SUMIFS('Base de Dados'!$J:$J, 'Base de Dados'!$K:$K, 'Perguntas 1 a 24'!K$38,'Base de Dados'!$D:$D, 'Perguntas 1 a 24'!$J41) -> 12025755 | L41: =SUMIFS('Base de Dados'!$J:$J, 'Base de Dados'!$K:$K, 'Perguntas 1 a 24'!L$38,'Base de Dados'!$D:$D, 'Perguntas 1 a 24'!$J41) -> 9401319 | M41: =SUMIFS('Base de Dados'!$J:$J, 'Base de Dados'!$K:$K, 'Perguntas 1 a 24'!M$38,'Base de Dados'!$D:$D, 'Perguntas 1 a 24'!$J41) -> 9133421 | N41: =SUMIFS('Base de Dados'!$J:$J, 'Base de Dados'!$K:$K, 'Perguntas 1 a 24'!N$38,'Base de Dados'!$D:$D, 'Perguntas 1 a 24'!$J41) -> 9935480
J42: Norte | K42: =SUMIFS('Base de Dados'!$J:$J, 'Base de Dados'!$K:$K, 'Perguntas 1 a 24'!K$38,'Base de Dados'!$D:$D, 'Perguntas 1 a 24'!$J42) -> 0 | L42: =SUMIFS('Base de Dados'!$J:$J, 'Base de Dados'!$K:$K, 'Perguntas 1 a 24'!L$38,'Base de Dados'!$D:$D, 'Perguntas 1 a 24'!$J42) -> 0 | M42: =SUMIFS('Base de Dados'!$J:$J, 'Base de Dados'!$K:$K, 'Perguntas 1 a 24'!M$38,'Base de Dados'!$D:$D, 'Perguntas 1 a 24'!$J42) -> 0 | N42: =SUMIFS('Base de Dados'!$J:$J, 'Base de Dados'!$K:$K, 'Perguntas 1 a 24'!N$38,'Base de Dados'!$D:$D, 'Perguntas 1 a 24'!$J42) -> 0
J43: Total | K43: =SUM(K39:K42) -> 71102637 | L43: =SUM(L39:L42) -> 66823089 | M43: =SUM(M39:M42) -> 67057272 | N43: =SUM(N39:N42) -> 67157220
C44: Somatório | D44: Média | E44: Contagem | F44: Máximo | G44: Mínimo | J44: Para qual país irão mais produtos em quantidade de produtos? E em valor?
C45: =SUBTOTAL(9, 'Base de Dados'!J:J) -> 272140218 | D45: =SUBTOTAL(1, 'Base de Dados'!J:J) -> 70594.09 | E45: =SUBTOTAL(2, 'Base de Dados'!J:J) -> 3855 | F45: =SUBTOTAL(4, 'Base de Dados'!J:J) -> 119945 | G45: =SUBTOTAL(5, 'Base de Dados'!J:J) -> 20044
J46: Quantidade | K46: {=INDEX('Base de Dados'!K:K, MATCH(_xlfn.XLOOKUP(LARGE('Base de Dados'!O:O,1),'Base de Dados'!O:O, 'Base de Dados'!N:N,,0),'Base de Dados'!B:B,0), 0)} -> Holanda
C47: Utilizando a mesma estrutura do exercício anterior, preencha a tabela abaixo considerando apenas as linhas com origem RJ. É necessária alguma alteração na fórmula? | J47: Valor | K47: =INDEX(K38:N38, 1, MATCH(LARGE(K43:N43, 1), K43:N43, 0)) -> Austrália
J49: Monte uma tabela com os TOP 5 produtos com maior Custo de Produção. Complemente com as demais informações pedidas.
C50: Somatório | D50: Média | E50: Contagem | F50: Máximo | G50: Mínimo
C51: =SUMIFS('Base de Dados'!J:J, 'Base de Dados'!C:C, "RJ") -> 35615146 | D51: =AVERAGEIFS('Base de Dados'!J:J,'Base de Dados'!C:C,"RJ") -> 69696.959 | E51: =COUNTIFS('Base de Dados'!C:C,"RJ") -> 511 | F51: =_xlfn.MAXIFS('Base de Dados'!J:J, 'Base de Dados'!C:C,"RJ") -> 119698 | G51: =_xlfn.MINIFS('Base de Dados'!J:J, 'Base de Dados'!C:C, "RJ") -> 20044
J52: TOP 5 | K52: Descrição | L52: Código | M52: Custo de Produção | N52: País de Destino
C53: Utilizando a mesma estrutura do exercício anterior, preencha a tabela abaixo considerando apenas as linhas com custo maior que R$70.000. | J53: 1 | K53: {=INDEX('Base de Dados'!$A:$A, MATCH(LARGE('Base de Dados'!$J:$J,$J53), 'Base de Dados'!$J:$J, 0), 0)} -> Vutufe | L53: {=INDEX('Base de Dados'!B:B, MATCH(LARGE('Base de Dados'!$J:$J,$J53), 'Base de Dados'!$J:$J, 0), 0)} -> P873H963 | M53: {=INDEX('Base de Dados'!J:J, MATCH(LARGE('Base de Dados'!$J:$J,$J53), 'Base de Dados'!$J:$J, 0), 0)} -> 119945 | N53: {=INDEX('Base de Dados'!K:K, MATCH(LARGE('Base de Dados'!$J:$J,$J53), 'Base de Dados'!$J:$J, 0), 0)} -> Panamá
J54: 2 | K54: {=INDEX('Base de Dados'!$A:$A, MATCH(LARGE('Base de Dados'!$J:$J,$J54), 'Base de Dados'!$J:$J, 0), 0)} -> Licapiro | L54: {=INDEX('Base de Dados'!B:B, MATCH(LARGE('Base de Dados'!$J:$J,$J54), 'Base de Dados'!$J:$J, 0), 0)} -> H948H323 | M54: {=INDEX('Base de Dados'!J:J, MATCH(LARGE('Base de Dados'!$J:$J,$J54), 'Base de Dados'!$J:$J, 0), 0)} -> 119933 | N54: {=INDEX('Base de Dados'!K:K, MATCH(LARGE('Base de Dados'!$J:$J,$J54), 'Base de Dados'!$J:$J, 0), 0)} -> Austrália
J55: 3 | K55: {=INDEX('Base de Dados'!$A:$A, MATCH(LARGE('Base de Dados'!$J:$J,$J55), 'Base de Dados'!$J:$J, 0), 0)} -> Gopenemo | L55: {=INDEX('Base de Dados'!B:B, MATCH(LARGE('Base de Dados'!$J:$J,$J55), 'Base de Dados'!$J:$J, 0), 0)} -> H155P441 | M55: {=INDEX('Base de Dados'!J:J, MATCH(LARGE('Base de Dados'!$J:$J,$J55), 'Base de Dados'!$J:$J, 0), 0)} -> 119903 | N55: {=INDEX('Base de Dados'!K:K, MATCH(LARGE('Base de Dados'!$J:$J,$J55), 'Base de Dados'!$J:$J, 0), 0)} -> Austrália
C56: Somatório | D56: Média | E56: Contagem | F56: Máximo | G56: Mínimo | J56: 4 | K56: {=INDEX('Base de Dados'!$A:$A, MATCH(LARGE('Base de Dados'!$J:$J,$J56), 'Base de Dados'!$J:$J, 0), 0)} -> Petitode | L56: {=INDEX('Base de Dados'!B:B, MATCH(LARGE('Base de Dados'!$J:$J,$J56), 'Base de Dados'!$J:$J, 0), 0)} -> H119P473 | M56: {=INDEX('Base de Dados'!J:J, MATCH(LARGE('Base de Dados'!$J:$J,$J56), 'Base de Dados'!$J:$J, 0), 0)} -> 119901 | N56: {=INDEX('Base de Dados'!K:K, MATCH(LARGE('Base de Dados'!$J:$J,$J56), 'Base de Dados'!$J:$J, 0), 0)} -> Austrália
C57: =SUMIFS('Base de Dados'!J:J, 'Base de Dados'!J:J, ">70000") -> 187219272 | D57: =AVERAGEIFS('Base de Dados'!J:J, 'Base de Dados'!J:J, ">70000") -> 94794.568 | E57: =COUNTIFS('Base de Dados'!J:J, ">70000") -> 1975 | F57: =_xlfn.MAXIFS('Base de Dados'!J:J, 'Base de Dados'!J:J, ">70000") -> 119945 | G57: =_xlfn.MINIFS('Base de Dados'!J:J, 'Base de Dados'!J:J, ">70000") -> 70004 | J57: 5 | K57: {=INDEX('Base de Dados'!$A:$A, MATCH(LARGE('Base de Dados'!$J:$J,$J57), 'Base de Dados'!$J:$J, 0), 0)} -> Vigopurutu | L57: {=INDEX('Base de Dados'!B:B, MATCH(LARGE('Base de Dados'!$J:$J,$J57), 'Base de Dados'!$J:$J, 0), 0)} -> H776P365 | M57: {=INDEX('Base de Dados'!J:J, MATCH(LARGE('Base de Dados'!$J:$J,$J57), 'Base de Dados'!$J:$J, 0), 0)} -> 119889 | N57: {=INDEX('Base de Dados'!K:K, MATCH(LARGE('Base de Dados'!$J:$J,$J57), 'Base de Dados'!$J:$J, 0), 0)} -> Panamá
C59: Utilizando a mesma estrutura do exercício anterior, preencha a tabela abaixo considerando apenas as linhas com data de validade entre 2025 e 2027 | J59: Coloque na célula J65 uma lista suspensa com os possíveis estados de Origem e na céula K65 uma lista suspensa com os possíveis valores de Destino. Em seguida, construa na célula L65 uma fórmula que calcule o total do custo de produção dos produtos que tem origem E destino iguais as células J65 e K65 respectivamente. Assim, se na célula J65 estiver GO e na K65 Holanda, o valor exibido na célula L65 deve ser igual ao total do custo de produção de todos os produtos de origem em GO e destino Holanda.
C62: Somatório | D62: Média | E62: Contagem | F62: Máximo | G62: Mínimo
C63: =SUMIFS('Base de Dados'!J:J, 'Base de Dados'!F:F, ">="&DATE(2025,1,1), 'Base de Dados'!F:F, "<="&DATE(2027,12,31)) -> 126160763 | D63: =AVERAGEIFS('Base de Dados'!J:J,'Base de Dados'!F:F, ">="&DATE(2025,1,1), 'Base de Dados'!F:F, "<="&DATE(2027, 12, 1)) -> 71213.865 | E63: =COUNTIFS('Base de Dados'!H:H, 2025) + COUNTIFS('Base de Dados'!H:H, 2026)+ COUNTIFS('Base de Dados'!H:H, 2027) -> 1773 | F63: =_xlfn.MAXIFS('Base de Dados'!J:J, 'Base de Dados'!F:F, ">="&DATE(2025, 1, 1), 'Base de Dados'!F:F, "<="&DATE(2027,12,31)) -> 119903 | G63: =_xlfn.MINIFS('Base de Dados'!J:J, 'Base de Dados'!F:F, ">="&DATE(2025, 1, 1), 'Base de Dados'!F:F, "<="&DATE(2027,12,31)) -> 20081
C65: Utilizando a mesma estrutura do exercício anterior, preencha a tabela abaixo considerando apenas as linhas com cor verde. | J65: GO | K65: Holanda | L65: =SUMIFS('Base de Dados'!J:J,'Base de Dados'!C:C,'Perguntas 1 a 24'!J65,'Base de Dados'!K:K,'Perguntas 1 a 24'!K65) -> 9133421
J67: Crie uma coluna na base de dados com a urgência de envio dos produtos. Produtos com validade até 31/12/2025 e valor acima de R$50.000,00 terão o valor "Urgente e Caro". Produtos com validade até 31/12/2025 e valor abaixo ou igual a R$50.000,00 terão o valor "Urgente". Produtos com validade entre 2026 e 2028 e custo acima de R$50.000 terão o valor "Pendente e caro". Produtos com validade entre 2026 e 2028 e custo abaixo ou igual a R$50.000 terão o valor "Pendente". Produtos com validade a partir de 2029 terão o valor "Não prioritário" independente de seu custo.
C68: Somatório | D68: Média | E68: Contagem | F68: Máximo | G68: Mínimo
C69: =SUMIFS('Base de Dados'!J:J, 'Base de Dados'!K:K, "Holanda") -> 67057272 | D69: =AVERAGEIFS('Base de Dados'!J:J, 'Base de Dados'!K:K, "Holanda") -> 69997.152 | E69: =COUNTIFS('Base de Dados'!K:K, "Holanda") -> 958 | F69: =_xlfn.MAXIFS('Base de Dados'!J:J, 'Base de Dados'!K:K, "Holanda") -> 119595 | G69: =_xlfn.MINIFS('Base de Dados'!J:J, 'Base de Dados'!K:K, "Holanda") -> 20081
C71: Impeça que seja inserido qualquer produto com data de validade do ano 2023 ou menor. Ao tentar inserir essa data de validade, a planilha deverá exibir a seguinte mensagem: "ATENÇÃO! Só são permitidos produtos com data de validade a partir do ano de 2024."
J74: Urgente e Caro | K74: Validade até 31/12/2025 | L74: > 50.000
J75: Urgente | K75: Validade até 31/12/2025 | L75: <= 50.000
J76: Pendente e Caro | K76: 2026 até 2028 | L76: >50.000
J77: Pendente | K77: 2026 até 2028 | L77: <=50.000
J78: Não prioritário | K78: >=2029

Sheet Controle Financeiro
C1: 43101 | H1: 43132 | M1: 43160 | R1: 43191 | W1: 43221 | AB1: 43252 | AG1: 43282 | AL1: 43313 | AQ1: 43344 | AV1: 43374 | BA1: 43405 | BF1: 43435 | BK1: 43466 | BP1: 43497 | BU1: 43525 | BZ1: 43556 | CE1: 43586 | CJ1: 43617 | CO1: 43647 | CT1: 43678 | CY1: 43709 | DD1: 43739 | DI1: 43770 | DN1: 43800 | DS1: 43831 | DX1: 43862 | EC1: 43891 | EH1: 43922 | EM1: 43952 | ER1: 43983 | EW1: 44013 | FB1: 44044 | FG1: 44075 | FL1: 44105 | FQ1: 44136 | FV1: 44166 | GA1: 44197 | GF1: 44228 | GK1: 44256 | GP1: 44287 | GU1: 44317 | GZ1: 44348 | HE1: 44378 | HJ1: 44409 | HO1: 44440 | HT1: 44470 | HY1: 44501 | ID1: 44531 | II1: 44562 | IN1: 44593 | IS1: 44621 | IX1: 44652 | JC1: 44682 | JH1: 44713 | JM1: 44743 | JR1: 44774 | JW1: 44805 | KB1: 44835 | KG1: 44866 | KL1: 44896 | KQ1: 44927 | KV1: 44958 | LA1: 44986 | LF1: 45017 | LK1: 45047 | LP1: 45078 | LU1: 45108 | LZ1: 45139 | ME1: 45170 | MJ1: 45200 | MO1: 45231 | MT1: 45261
B2: Descrição | C2: S1 | D2: S2 | E2: S3 | F2: S4 | G2: Crédito | H2: S1 | I2: S2 | J2: S3 | K2: S4 | L2: Crédito | M2: S1 | N2: S2 | O2: S3 | P2: S4 | Q2: Crédito | R2: S1 | S2: S2 | T2: S3 | U2: S4 | V2: Crédito | W2: S1 | X2: S2 | Y2: S3 | Z2: S4 | AA2: Crédito | AB2: S1 | AC2: S2 | AD2: S3 | AE2: S4 | AF2: Crédito | AG2: S1 | AH2: S2 | AI2: S3 | AJ2: S4 | AK2: Crédito | AL2: S1 | AM2: S2 | AN2: S3 | AO2: S4 | AP2: Crédito | AQ2: S1 | AR2: S2 | AS2: S3 | AT2: S4 | AU2: Crédito | AV2: S1 | AW2: S2 | AX2: S3 | AY2: S4 | AZ2: Crédito | BA2: S1 | BB2: S2 | BC2: S3 | BD2: S4 | BE2: Crédito | BF2: S1 | BG2: S2 | BH2: S3 | BI2: S4 | BJ2: Crédito | BK2: S1 | BL2: S2 | BM2: S3 | BN2: S4 | BO2: Crédito | BP2: S1 | BQ2: S2 | BR2: S3 | BS2: S4 | BT2: Crédito | BU2: S1 | BV2: S2 | BW2: S3 | BX2: S4 | BY2: Crédito | BZ2: S1 | CA2: S2 | CB2: S3 | CC2: S4 | CD2: Crédito | CE2: S1 | CF2: S2 | CG2: S3 | CH2: S4 | CI2: Crédito | CJ2: S1 | CK2: S2 | CL2: S3 | CM2: S4 | CN2: Crédito | CO2: S1 | CP2: S2 | CQ2: S3 | CR2: S4 | CS2: Crédito | CT2: S1 | CU2: S2 | CV2: S3 | CW2: S4 | CX2: Crédito | CY2: S1 | CZ2: S2 | DA2: S3 | DB2: S4 | DC2: Crédito | DD2: S1 | DE2: S2 | DF2: S3 | DG2: S4 | DH2: Crédito | DI2: S1 | DJ2: S2 | DK2: S3 | DL2: S4 | DM2: Crédito | DN2: S1 | DO2: S2 | DP2: S3 | DQ2: S4 | DR2: Crédito | DS2: S1 | DT2: S2 | DU2: S3 | DV2: S4 | DW2: Crédito | DX2: S1 | DY2: S2 | DZ2: S3 | EA2: S4 | EB2: Crédito | EC2: S1 | ED2: S2 | EE2: S3 | EF2: S4 | EG2: Crédito | EH2: S1 | EI2: S2 | EJ2: S3 | EK2: S4 | EL2: Crédito | EM2: S1 | EN2: S2 | EO2: S3 | EP2: S4 | EQ2: Crédito | ER2: S1 | ES2: S2 | ET2: S3 | EU2: S4 | EV2: Crédito | EW2: S1 | EX2: S2 | EY2: S3 | EZ2: S4 | FA2: Crédito | FB2: S1 | FC2: S2 | FD2: S3 | FE2: S4 | FF2: Crédito | FG2: S1 | FH2: S2 | FI2: S3 | FJ2: S4 | FK2: Crédito | FL2: S1 | FM2: S2 | FN2: S3 | FO2: S4 | FP2: Crédito | FQ2: S1 | FR2: S2 | FS2: S3 | FT2: S4 | FU2: Crédito | FV2: S1 | FW2: S2 | FX2: S3 | FY2: S4 | FZ2: Crédito | GA2: S1 | GB2: S2 | GC2: S3 | GD2: S4 | GE2: Crédito | GF2: S1 | GG2: S2 | GH2: S3 | GI2: S4 | GJ2: Crédito | GK2: S1 | GL2: S2 | GM2: S3 | GN2: S4 | GO2: Crédito | GP2: S1 | GQ2: S2 | GR2: S3 | GS2: S4 | GT2: Crédito | GU2: S1 | GV2: S2 | GW2: S3 | GX2: S4 | GY2: Crédito | GZ2: S1 | HA2: S2 | HB2: S3 | HC2: S4 | HD2: Crédito | HE2: S1 | HF2: S2 | HG2: S3 | HH2: S4 | HI2: Crédito | HJ2: S1 | HK2: S2 | HL2: S3 | HM2: S4 | HN2: Crédito | HO2: S1 | HP2: S2 | HQ2: S3 | HR2: S4 | HS2: Crédito | HT2: S1 | HU2: S2 | HV2: S3 | HW2: S4 | HX2: Crédito | HY2: S1 | HZ2: S2 | IA2: S3 | IB2: S4 | IC2: Crédito | ID2: S1 | IE2: S2 | IF2: S3 | IG2: S4 | IH2: Crédito | II2: S1 | IJ2: S2 | IK2: S3 | IL2: S4 | IM2: Crédito | IN2: S1 | IO2: S2 | IP2: S3 | IQ2: S4 | IR2: Crédito | IS2: S1 | IT2: S2 | IU2: S3 | IV2: S4 | IW2: Crédito | IX2: S1 | IY2: S2 | IZ2: S3 | JA2: S4 | JB2: Crédito | JC2: S1 | JD2: S2 | JE2: S3 | JF2: S4 | JG2: Crédito | JH2: S1 | JI2: S2 | JJ2: S3 | JK2: S4 | JL2: Crédito | JM2: S1 | JN2: S2 | JO2: S3 | JP2: S4 | JQ2: Crédito | JR2: S1 | JS2: S2 | JT2: S3 | JU2: S4 | JV2: Crédito | JW2: S1 | JX2: S2 | JY2: S3 | JZ2: S4 | KA2: Crédito | KB2: S1 | KC2: S2 | KD2: S3 | KE2: S4 | KF2: Crédito | KG2: S1 | KH2: S2 | KI2: S3 | KJ2: S4 | KK2: Crédito | KL2: S1 | KM2: S2 | KN2: S3 | KO2: S4 | KP2: Crédito | KQ2: S1 | KR2: S2 | KS2: S3 | KT2: S4 | KU2: Crédito | KV2: S1 | KW2: S2 | KX2: S3 | KY2: S4 | KZ2: Crédito | LA2: S1 | LB2: S2 | LC2: S3 | LD2: S4 | LE2: Crédito | LF2: S1 | LG2: S2 | LH2: S3 | LI2: S4 | LJ2: Crédito | LK2: S1 | LL2: S2 | LM2: S3 | LN2: S4 | LO2: Crédito | LP2: S1 | LQ2: S2 | LR2: S3 | LS2: S4 | LT2: Crédito | LU2: S1 | LV2: S2 | LW2: S3 | LX2: S4 | LY2: Crédito | LZ2: S1 | MA2: S2 | MB2: S3 | MC2: S4 | MD2: Crédito | ME2: S1 | MF2: S2 | MG2: S3 | MH2: S4 | MI2: Crédito | MJ2: S1 | MK2: S2 | ML2: S3 | MM2: S4 | MN2: Crédito | MO2: S1 | MP2: S2 | MQ2: S3 | MR2: S4 | MS2: Crédito | MT2: S1 | MU2: S2 | MV2: S3 | MW2: S4 | MX2: Crédito
A3: Receitas | B3: Trabalho 1 | D3: =1836.79*0.4 -> 734.716 | F3: =1836.79*0.6-165.31 -> 936.764 | I3: 734.72 | K3: 998.23 | N3: 735.72 | P3: =859.61-0.08 -> 859.53 | S3: 734.72 | U3: 818.29 | X3: 734.72 | Z3: 1018.19 | AC3: 734.72 | AE3: 942.33 | AH3: 734.72 | AJ3: 855.94 | AM3: 734.72 | AO3: 852.27 | AR3: 734.72 | AT3: 866.96 | AW3: 734.72 | AY3: 855.94 | BB3: 734.72 | BD3: =2244.85+918.4+866.96 -> 4030.21 | BG3: 979.38 | BH3: 827.15 | BI3: 110.15 | BL3: 752.54 | BN3: =821.48+116.34 -> 937.82 | BQ3: 752.54 | BS3: 884.25 | BV3: 752.54 | BW3: 0.02 | BX3: 884.25 | CB3: 752.54 | CC3: 839.25 | CF3: 752.54 | CH3: 876.72 | CK3: 752.54 | CM3: 888.01 | CP3: 752.54 | CQ3: 800 | CR3: 847.96 | CU3: 752.54 | CW3: 876.72 | CZ3: 752.54 | DB3: 910.58 | DD3: 22.66 | DE3: 752.54 | DG3: 872.96 | DJ3: 752.54 | DL3: =2323.57+1523.52+941.82+971.54+112.32 -> 5872.77 | DP3: 796.65 | DT3: 777.23 | DV3: 909.36 | DY3: 777.23 | EA3: 917.13 | ED3: 777.23 | EF3: 880.04 | EH3: =11.41+19.88+12.19+9.7+11.17+11.33+11.82+9.3+11.66+10.42+11+10.61+12.89 -> 153.38 | EI3: 777.23 | EJ3: =9.3+11.79 -> 21.09 | EK3: 932.81 | EN3: 777.23 | EP3: 1006.65 | ES3: 777.23 | EU3: 1006.65 | EX3: 777.23 | EZ3: 1006.65 | FC3: 777.23 | FE3: 1270.37 | FI3: 900.39 | FJ3: =(1270.37-123.16) -> 1147.21 | FM3: 900.39 | FN3: 100 | FO3: =(1270.37-123.16) -> 1147.21 | FR3: 900.39 | FS3: 100 | FT3: =2730.19+1201.08+4501+1158.58 -> 9590.85 | FX3: =942.89+100 -> 1042.89 | FY3: 116.48 | GB3: 926.86 | GD3: 1178.52 | GG3: 926.86 | GI3: 1178.52 | GK3: 100 | GL3: =926.86+100 -> 1026.86 | GN3: 1253.52 | GQ3: 926.86 | GR3: 100 | GT3: 2747.87 | GV3: 926.86 | GX3: 1178.52 | HB3: 926.86 | HC3: 1178.52 | HF3: 926.86 | HG3: 94.2 | HH3: 1178.52 | HK3: 926.86 | HL3: 99.91 | HM3: 3791.33 | HP3: 2400 | HQ3: 100 | HR3: 2318.19 | HU3: 2400 | HV3: 100 | HW3: 2727.45 | HZ3: 2650.08 | IA3: 74.73 | IB3: =7057.29+1617.92+564.5+3312.6+5007.04 -> 17559.35 | IF3: 2061.41 | II3: 100 | IJ3: 2650.08 | IL3: 1143.83 | IP3: 2650.08 | IQ3: 1806.35 | IU3: 2650.08 | IV3: 1806.35 | IY3: 2650.08 | JA3: 1806.35 | JD3: 8577.96 | JK3: 4000 | KJ3: 400
B4: Trabalho 2 | D4: 800 | K4: 1200 | R4: 1200 | X4: 1600 | AC4: 800 | AI4: 1400 | AM4: 1700 | AS4: 1700 | AY4: 700 | BD4: 1700 | BL4: 500 | BQ4: 1500 | BX4: 800 | CA4: 800 | CF4: 1000 | CK4: 1000 | CV4: 1000 | CZ4: 1000 | DG4: 1000 | DI4: 1000 | DN4: 1000 | DT4: 1000 | DZ4: 1500 | EF4: 1500 | ES4: 1150 | EW4: 1150 | FB4: 2000 | FG4: 2000 | FL4: 2000 | FQ4: 2000 | FV4: 2000 | GA4: 2000 | GF4: 2000 | GK4: 2000 | GP4: 2000 | GU4: 2000 | GZ4: 2000 | HE4: 2000 | HJ4: 2000 | HO4: 2000 | HT4: 2500 | HY4: 2000 | ID4: 2000 | II4: 3000 | IN4: 2000 | IS4: 2000 | IX4: 3000 | JC4: 7000 | JH4: 7000 | JM4: 20000 | JR4: 7000 | JW4: =7000 -> 7000 | KB4: 7000 | KG4: 7000 | KL4: 7000 | KQ4: 40000 | KV4: 7500 | LA4: 7500 | LF4: 7500 | LK4: 7500 | LP4: 7500 | LU4: 7500 | LZ4: 7500 | ME4: 7500 | MJ4: 7500 | MO4: 7500 | MT4: 7500
A6: Despesas | B6: Transporte público | C6: 200 | E6: =300 -> 300 | M6: 150 | AB6: 30 | AD6: =67+50 -> 117 | BW6: =4+4.6+8.8 -> 17.4 | CA6: =51.5 -> 51.5 | CB6: 17.8 | CC6: =12+8.25 -> 20.25 | CL6: =70-4.5+5-8.15 -> 62.35 | FK6: 29.9 | FP6: 29.9 | FU6: 29.9 | FZ6: 29.9 | GJ6: 3.9 | GO6: =29.9*2 -> 59.8
B7: Uber | D7: =7.75+12.52+7.75+8.28+7.93 -> 44.23 | E7: =7+7.75+8.96 -> 23.71 | H7: =7.75+9.15+8.43+8.21+7.75+7.75 -> 49.04 | I7: =7.75+8.4+10.48+10.3 -> 36.93 | J7: =11.94+8.37 -> 20.31 | K7: =8.97+9.43 -> 18.4 | M7: =10.14+13.36+8.24+13.08 -> 44.82 | N7: =7.75+8.13+13.58+8.55 -> 38.01 | O7: =8.42 -> 8.42 | P7: =8.75+7.75+7.75 -> 24.25 | R7: =8.54+9.73+7.75+12.26+8.07+7.75 -> 54.1 | S7: =7.75*3+8.3+8.23+7.75 -> 47.53 | T7: =7.75*2 -> 15.5 | U7: =8.55+7.75 -> 16.3 | W7: =7.75*5 -> 38.75 | X7: =7.75*4+17+16.31+8.95 -> 73.26 | Y7: =5*7.75 -> 38.75 | Z7: =7.75*3 -> 23.25 | AB7: =8.7+8.86+10.07+7.25+7.75+7.75+7.75+7.75+7 -> 72.88 | AC7: =7.75+11.98+7.75 -> 27.48 | AD7: =7.75+9.03 -> 16.78 | AE7: 7.75 | AH7: =14.3+7.75+18.69+16.96+7.75+7.75+7.75 -> 80.95 | AI7: 7.75 | AJ7: =10.23+7.79+10.49+14.64+8.62+7.75+7.75 -> 67.27 | AL7: =7.75+23.35+10.01+11.95+10.03+15.23+10.55 -> 88.87 | AM7: =9.97+88.62 -> 98.59 | AN7: =24.81+9.97+8.95+7.75 -> 51.48 | AO7: 19.73 | AQ7: =7.75+12.55+7.75+7.75+11.84 -> 47.64 | AR7: =24.97+29.38+8.25+8.25 -> 70.85 | AS7: =24.17+27.88+7.75+8 -> 67.8 | AT7: =10.36+7.75 -> 18.11 | AV7: =7.75+7.81+14.5 -> 30.06 | AW7: =7.75+9.9+7.75 -> 25.4 | AX7: =11.35+8.42+7.73+7.5+50 -> 85 | AY7: =5.6+5.5+7.5+7.75+14.95+6.8+6.1+5.94+12.7 -> 72.84 | BA7: =7.2+6.82+12.2+7.5+7.5 -> 41.22 | BB7: =5.25+6+6+18.16+9 -> 44.41 | BC7: =7.26+6.37+5.62+22.8 -> 42.05 | BD7: =7.5+9.8+8.59+7.5+6.37+9.8 -> 49.56 | BG7: =7.5+9.8+19.46+7.5+7.5 -> 51.76 | BH7: =13.5+12.8+7.5+7.6 -> 41.4 | BI7: =9.3+7.5+8.06+15.42 -> 40.28 | BJ7: =9.8+11.3+10.9 -> 32 | BK7: =7.5+13.46+15+18.26 -> 54.22 | BO7: =7.5+7.5+6.38 -> 21.38 | BQ7: 3.88 | BR7: 13.1 | BS7: =7.75+7.5 -> 15.25 | BT7: =7.5+7.5+23.29+8 -> 46.29 | BV7: =7.69+6.21 -> 13.9 | BW7: =6.21+6.9+6 -> 19.11 | BY7: =7.5+7.5+9.8+8.3+8+7.8+7.5+7.5+6.37+12.61+6.22+6.21+6.8+9.67+6.21+12.7+7.3 -> 137.99 | BZ7: =9.8+7.5+6+7.3+8.4 -> 39 | CA7: =5.5+13.1 -> 18.6 | CD7: =10.8+6.21+7.3+7.28+9.6+13.2+13.1+8.74+7.49+6.37+8.4+8.81+7.5+7.5+20.3 -> 142.6 | CI7: =7.5+7.5+5.27+8.92+7.1+7.29+11.73+6.2+6.2+13.5+6.2+5.35+6.2+8.33+5.35+6.4+5.53+5.35+5.35+10.6+18.19+7.74+13.2+6.2+13.5+12.8 -> 217.5 | CJ7: 6.4 | CN7: =6.2+5.35+8.9+8+9.9+13.1+(39.37-25.47)+8+32.69+4.2+13.2+6.2+13.1+6.2+6.2+12.7+6.2+(13.42-7.22)+6.2+12.9+7.5+13.1 -> 219.94 | CS7: =6.2+6.2+6.2+6.7+9.11+6.2+13+20.7+13.5+6.2+22.9+14.2+6.2+6.2+8.4+6.2+6.2+6.2+6.2+6.2+8.1+11.2+6.2+6.2+(54.21-48.01)+6.2+5.44*4+6.57 -> 255.34 | CX7: =5.44*5+5.27*3+7.04+12.95+9.48+6+12.98+5.3+5.3+4.8+5.27+5.3+6.64+12.94+6.16+7.38+7.85+5.27+5+6.96+5+5.5+12.7 -> 198.83 | DC7: =4.96+5+5+5.06+12.8+5.78+5+38.9+23.28+21.85+38.55+(5.06+12.06+17.11+8.7+12.48+23.79+19.97)+12.4+9.8+7.27+5+22.66+9.27+10+5.9+15.46+5+11.73+10.45 -> 390.29 | DH7: =8.04+5.08+6.64+4+6.64+5.08+7+11.14+5.08+5.09+18.34+5.98+5.98+15.57+5.98+7.47+9.52+5.08+7.32+6+7.4+12.94+5.08+5.08+10.84+5+0.03 -> 197.4 | DJ7: =6.4+24.53 -> 30.93 | DM7: =5.08+8.64+12.92+17.79+9.48+5.08+9.25+9.17+5.08+12.79+8.36+6.75+10.66+13.22+9.27+5.08+21+6.64+11.42+9+5.98+6.8+22.09+5.2+16.35+10.84+5.98+11.59+8.1+14.5+5+10.28+5.98+9.38+14.46+10.95+19.97+20.2 -> 400.33 | DR7: =6.9+13.63+10.9+5.91+5.8+6.12+6.13+2+5+7.5+9.63+10.29+14.68+22.61+5.67+6+8.1+9.5+5.98+9.67+5.79+7.2+6.9 -> 191.91 | DW7: =11+8.15+9.49+7.5+12.75+5.79+5.79+5.2+8.39+8.31+5+6.7+5.79+5+5.5+5.79+5.79+5.79+5.98+7+5.79+5.79+5.4+5.82+5+5.8+6.7+((((31.12-17.52))))+8.4+8.4+6.6+4.88+5.79 -> 228.68 | EB7: =5.79+10.96+5.84+5.79+5.79+8.5+5.79+9.7+5.61+11.52+14.9+6.96+5+8+11.6+9.5+5.5+7.7+9.2+15.56+5.5+23.45 -> 198.16 | EE7: =5.67+6.8+6.1+19.88+11.41+12.19+11.17+11.33+11.82+6.01+8.29 -> 110.67 | EF7: =9.3+11.66+11.79 -> 32.75 | EG7: =7.4+7.6+16.5+16.48+6.7+5+11.92+5.67+8.6+11.32+9.3+14+10.2+41.07+10.46+16.67+8+8.49+6.37+9.7+10.42+11+10.61+12.89+5.87+6.3 -> 288.54 | EL7: =9.27+6.22+7.89 -> 23.38 | EQ7: 93.65 | EY7: 83 | FA7: =5.58+8.86+5.35+5.35+72.13+79.37+52.68+5.35+5.81 -> 240.48 | FF7: =16.35+73.59+77.39+5.35+5.81+4.89+5.35+11+5.81+26.64 -> 232.18 | FP7: =6.01+9.54+8.93 -> 24.48 | GJ7: =7.85+18.28+14.39 -> 40.52 | GO7: 34.87 | GX7: 200 | GY7: =6.81+8.99+8.29+80.77+62.19+45.52+6.22+8.02+5.88+7.18+7+5.88+7.05 -> 259.8 | HD7: =9.05+9.1+6.68+15.5+11.92+14.91+5.88+5.88+14.93+7.62+10.99+5.88+8.44+7.21+5.88+8.92+12.92 -> 161.71 | HE7: =18.94 -> 18.94 | HI7: =8.91+6.99+10.97+5+19.99+12.92+10.92+6.68+7.9+8.32+14.95+12.98+21.92+7.9+6.68+6.21+6.13+5.49+5.49 -> 186.35 | HN7: =8.56+6.76+12.96+17.91+15+9.15+8.44+6.68+7.53+5.51+6.61+15.95+9.93+54.99+23.98+51.98+54.99+55.96 -> 372.89 | HS7: =8.94+8.84+12.94+10.91+50.91+51.94+7.61+8.41+8.73+9.91 -> 179.14 | HX7: =7.21+11.97+8.93+8.97+8.77+10.94+10.9+8.93+9.95+8.98+9.91+8.84+40.45+51.95+11.95+12.97+13.98+8.95+10.97+11.05+10.96+10.9+64.99+54.93+10.9+8.86+9.99+8.72+9.95+11.95 -> 478.72 | HY7: 7.51 | HZ7: =12.98+16.99+11.94+15.92+11.94 -> 69.77 | IA7: =8.9+10.94+14.96+10.93+12.96+10.97 -> 69.66 | IB7: =13.95+9.94+7.99+9.92+9.62+11.97+9.92+13.94+15.9+9.91 -> 113.06 | IC7: =13.93+52.03+10.94+49.96+10.94+11.99+17.01+10.97+13.91+12.96+14.91+10.97+7.96+10.97+16.91+9.96+10.92+10.98 -> 298.22 | ID7: =10.98+11.99+13.92+11.99+16.52+9.62+9.76+9.78 -> 94.56 | IE7: =13.07+14.98+8.95+9.98+12.53+8.97+10.82+8.45 -> 87.75 | IF7: =13.18+20.34+8.99+12.91+16.9+17.94+16.54+10.94+9.59+20.22 -> 147.55 | IG7: =9.01+9.4 -> 18.41 | IH7: =9.98+7.96 -> 17.94 | II7: =9.82+9.4+2+8.66 -> 29.88 | IM7: =8.45+10.45+10.9+11.71+9.01+9.9+8.91+9.7+8.58+7.84+9.12+7.93+7.57+9.85+10.9+9.95+10.59+10.18+9.11 -> 180.65 | IR7: =9.96+7.26+7.68+9.4+10.3+10.91+15.93+10.98+13.9+11.19+9.96+11.15+10.9+9.52+10.84+10.54+7.7+9.93+12.08+10.25+9.76+9.88+10.85+8.88 -> 249.75 | IW7: =6.43+10.97+10.93+17.94+11.95+11.91+10.97+8.98+9.96+20.2+9.92+10.95+10.93 -> 152.04 | JB7: =20+20.98+11.95+17.97+11.95+9.93+11.92+10.94+9.91+11.92+9.91+9.98+9.05+9.95+10.91+10.93+11.98+9.9+8.7+10.99+29.99+11.95+9.93+16.93+19.98+10.17+9.99 -> 348.71 | JE7: =13.92+13.96+9.99+8.79+8.73+8.91+9.93+11.93+5.73+8.93 -> 100.82 | JF7: =14.96+9.94+((64.96+69.95+65.01+64.96)) -> 289.78 | JG7: =59.95+65.12+11.95+9.93+10.96+10.97+9.93+8.53+9.28+24.95+((61.67+65.31+64.94+65.18+61.65+65.17+69.99+69.92+69.96+69.9))+19.98+11.91+10.96+9.9+12.97+10.99+16.24+14.91+24.66 -> 1017.78 | JH7: =8.56+69.98+81.18+69.9+63.7 -> 293.32 | JI7: =79.92+69.97 -> 149.89 | JM7: =19.97+13.95+12.91+10.95+9.9 -> 67.68 | JN7: =8.48+8.62 -> 17.1 | JV7: 50 | KA7: =160+200-(318.65) -> 41.35 | KE7: =9.38+19.99 -> 29.37 | KF7: =9.58+10.98 -> 20.56 | KK7: =10.91+9.97+10.94+29.96+10.95+14.91+69.92 -> 157.56 | KP7: =8.97+8.93+10.99+12.95 -> 41.84 | KU7: =-2105.16 -> -2105.16 | LH7: =8.96 -> 8.96 | LI7: =74.92+84.99-90.02 -> 69.89 | LL7: =11.93+9.93 -> 21.86 | MC7: =16.94+59.94+69.91 -> 146.79 | MD7: =150+150+(66.7+66.66*5-8.25)+(33.35+33.33*5-4.13)-612.19 -> 275.43 | MN7: =(400-8.25)+(300-6.19)+14.43-714.43 -> -14.44 | MS7: =29.99+2.1+176.86+85.56+33.03-292.41+79.91+84.98+105.11 -> 305.13 | MX7: =(6.9*3+7.4) -> 28.1
B8: Carro | JL8: =138.9+200+116.73 -> 455.63 | JM8: 141.92 | JO8: 59.79 | JP8: =100+150 -> 250 | JQ8: =347.56+(116.66*11-50.45)+(78.3)+200+54.86+100 -> 2013.53 | JT8: =6 -> 6 | JU8: 100 | JV8: =324.31+(69.66)+263.68 -> 657.65 | JY8: =3.5+6 -> 9.5 | JZ8: 11.49 | KA8: =324.31+50+209.98+100+16.46 -> 700.75 | KB8: 100 | KF8: =324.31+(16.44*5-1.36)+21.94+232.43 -> 659.52 | KK8: =237.74+79.9 -> 317.64 | KN8: 225.52 | KP8: =324.31+100.1 -> 424.41 | KR8: =2025.24+183.24 -> 2208.48 | KT8: =100+100 -> 200 | KU8: =405.77+77.44+191.6+95.81 -> 770.62 | KY8: 150 | KZ8: =405.77 -> 405.77 | LC8: =50+14 -> 64 | LD8: 50 | LE8: =405.77 -> 405.77 | LF8: 183.24 | LJ8: =405.77+87.36+97.22+100+97.27 -> 787.62 | LL8: 53 | LM8: =14+6 -> 20 | LN8: =35+45 -> 80 | LO8: =405.77+60+6+(97.27+110+95+50) -> 824.04 | LT8: =405.77+98.07+100 -> 603.84 | LX8: 4 | LY8: =405.77+147.41+74+50+6+15+96.49+6 -> 800.67 | MA8: 348.3 | MC8: 15 | MD8: =405.77+15+15+150+18+4+93.22 -> 700.99 | ME8: =3+17 -> 20 | MF8: 17 | MG8: 58 | MH8: 51.2 | MI8: =405.77+186.42+6.2 -> 598.39 | MJ8: 58 | MM8: =74+20 -> 94 | MN8: =405.77+139.82+89.7+95.59 -> 730.88 | MS8: =405.77+136.91+6.2 -> 548.88 | MX8: =405.77 -> 405.77
B9: Investimentos | D9: 25.5 | S9: 40 | AH9: 5 | AT9: 400 | AW9: 69.9 | AY9: 99.9 | BA9: 189.8 | BE9: 138.75 | BF9: 6.98 | BJ9: =138.74+36.03 -> 174.77 | BO9: =67.81+35.99 -> 103.8 | BP9: 20 | BT9: =67.81+35.99 -> 103.8 | BW9: 5 | BY9: 35.99 | CD9: 35.99 | CE9: 132 | CI9: 43.96 | CM9: 99.99 | CP9: 119.99 | CR9: =(400-145.7+1.7) -> 256 | CS9: =24.1+119.9+(116.7/2+45.9)+93.7 -> 341.95 | CX9: =116.7/2+45.2+15 -> 118.55 | DA9: 37 | DC9: =45.2+8.99 -> 54.19 | DH9: =45.2 -> 45.2 | DZ9: 25 | EB9: 60.97 | FA9: 199.8 | FF9: =(199.8*4-1.53)+42.97+39.9+(33.34+33.33*5-0.64)+(41.34+41.33*2-0.16) -> 1203.73 | FP9: 27.5 | FX9: 73.95 | FZ9: =848.5+29.9 -> 878.4 | GE9: 848.5 | GH9: =710.5-100 -> 610.5 | GJ9: =848.5+99.8 -> 948.3 | GY9: =(142.37+142.33*9-14.17) -> 1409.17 | HD9: 127.48 | HI9: 45.87 | HO9: =230+1612 -> 1842 | ID9: 137.76 | IE9: 328 | IF9: 117.14 | IP9: 170 | IT9: =129.33+436+109 -> 674.33 | IU9: 210.09 | IX9: =129.33+414 -> 543.33 | JB9: =170+92.91+24.27+1.55 -> 288.73 | JD9: =81.49+49.6 -> 131.09 | JG9: =45.9+168.68 -> 214.58 | JI9: 30 | JL9: =47.9+(43.33+43.32*2-1.01)+(65*10-22.24) -> 804.62 | JU9: =125.1+279.8 -> 404.9 | KK9: =21.95+27.4+69.9 -> 119.25 | KP9: =77.65*3-1.94+51.9+(70+69.99-0.58)+(65+64.99-0.54)+35.99 -> 587.76 | LC9: 179.7 | LI9: 84.98 | LL9: 104.27 | LM9: 49.9 | LW9: 116.1 | LY9: 47.8 | MC9: 279.7 | MD9: =47.8+47.99 -> 95.79 | MI9: 47.8 | MN9: 47.8 | MQ9: 323.7 | MS9: =47.8+69.99+140 -> 257.79 | MX9: =(47.8*5-3.96) -> 235.04
B10: Presentes | H10: 89.8 | J10: 426.93 | M10: 15 | N10: =25.9+189.9 -> 215.8 | P10: 30 | R10: 10.36 | W10: 10 | AB10: 12.29 | AE10: 20 | AH10: =49.99+99.9 -> 149.89 | AM10: 30 | BH10: =119.98+119.99+49.99 -> 289.96 | BK10: 16 | BW10: 44 | CM10: 100 | CN10: 99.9 | DC10: =15+59.9+21.99 -> 96.89 | DR10: =(375.6-1.11)+(82.27+5.25)+247.16+99.98+39.9 -> 849.05 | EU10: 100 | FA10: =(9.99*12-0.94)+(9.43*12-0.84) -> 231.26 | FZ10: 405.37 | GL10: 50 | GO10: 78.47 | JN10: 48.94 | JR10: 738.21 | KG10: 60 | LL10: 288 | LU10: 1094.44 | LW10: 100 | LZ10: 26.38 | MC10: 151 | MO10: 310.85
B11: Subsistência e Saúde | D11: =12.9+12 -> 24.9 | E11: 38 | F11: =14.84 -> 14.84 | H11: =9.9+18.9+17 -> 45.8 | I11: 40 | J11: 18.9 | K11: =24.86 -> 24.86 | M11: 17 | N11: 20 | O11: =45.46+36 -> 81.46 | P11: =7.89+17 -> 24.89 | R11: =60+60 -> 120 | S11: =9.45+14.65 -> 24.1 | T11: 17 | U11: =31.79+19.98 -> 51.77 | W11: 120 | X11: =17 -> 17 | Y11: =30+23.43 -> 53.43 | AB11: =9.45+2.7+17+3.77+3.99 -> 36.91 | AC11: 16.97 | AD11: 15.18 | AE11: =27.49+8.55+17+200 -> 253.04 | AG11: 20 | AH11: 7.52 | AI11: 30 | AJ11: =17+13.58+20 -> 50.58 | AN11: 20 | AO11: =20.5 -> 20.5 | AR11: =20+12 -> 32 | AT11: =20 -> 20 | AW11: =12+20 -> 32 | BA11: 12 | BC11: =31.79 -> 31.79 | BD11: =18.36+20+12 -> 50.36 | BG11: =45.96+10.9 -> 56.86 | BH11: 13.98 | BI11: =20+7.94 -> 27.94 | BK11: 20 | BM11: 20 | BN11: 8.99 | BQ11: 45.51 | BR11: 20 | BS11: 26.97 | BU11: 14.99 | BV11: 2 | BX11: =20 -> 20 | BZ11: 44.99 | CC11: 12 | CE11: 44.99 | CG11: 23.97 | CH11: 20 | CI11: 106.03 | CJ11: 44.99 | CM11: =12+44.99 -> 56.99 | CQ11: 23.27 | CS11: 22 | CT11: 44.99 | CY11: =44.99+20 -> 64.99 | DC11: =1.96+18.37+(4.29+2.99+34)+9.9 -> 71.51 | DD11: =44.99+20 -> 64.99 | DH11: =210+99.9 -> 309.9 | DI11: 44.99 | DJ11: =12+20+22.99 -> 54.99 | DM11: =210+31.95+99.9*2 -> 441.75 | DN11: 44.99 | DR11: =99.9+18.15+23.99 -> 142.04 | DS11: 44.99 | DT11: 107.5 | DU11: 12 | DV11: 20 | DW11: =99.9+9.99+8.97+12 -> 130.86 | DX11: 44.99 | DY11: 29.94 | EB11: =5+22+99.9+28.75+8.29+40.2+188.11+20+16.58 -> 428.83 | EC11: 85.97 | ED11: 27 | EE11: =131+11.96+14.05+10.16+9.17+17.94+36.29+16.54+36.47+74.21 -> 357.79 | EF11: =21.75+17.31+39.25+37.64+30.9+24.84 -> 171.69 | EG11: =99.9+13.08+48.98+8.78+16.96+3.17+13.08+27.89+20 -> 251.84 | EH11: =73.88+25.06+123.01+58.7+23.67 -> 304.32 | EI11: =32.58+42.54+44.96+71.71+22.43 -> 214.22 | EJ11: =30.98+48.35+16.99 -> 96.32 | EK11: =84.78+69.3 -> 154.08 | EM11: =47.99+14.03+91.84 -> 153.86 | EN11: 123.48 | EO11: 64.2 | EP11: 99.96 | EQ11: =10.49+17.38+38.49+18.72 -> 85.08 | ER11: 48.93 | EU11: 41.02 | EV11: 229.49 | EW11: 48.93 | FA11: =51.43+1.12+0.17+122.6+51.27+56.1-4.83+0.12+31.87+35.57+73.49+((73.1+58.4))-6.03+40.99+12.7-0.6 -> 597.47 | FB11: 48.93 | FC11: 11.34 | FF11: =66.08+56+50.98+15.11+22.16 -> 210.33 | FG11: 48.93 | FK11: =94.92+21.24 -> 116.16 | FL11: =48.93+10.52 -> 59.45 | FM11: 42.67 | FQ11: 48.93 | FU11: =69.13+172.62+109.16 -> 350.91 | FV11: 48.93 | FX11: =10+23.24 -> 33.24 | GA11: 48.93 | GB11: =8.25+17.98+25.64 -> 51.87 | GE11: =9.42*10-0.54+42.11+37.47 -> 173.24 | GF11: 48.93 | GJ11: =42.99+48.34 -> 91.33 | GK11: =48.93+10 -> 58.93 | GO11: =26.99+63.97 -> 90.96 | GP11: 49.98 | GT11: =29.92+18.96+21.99+42.09+9.97+44.69+141.55+28.9+49.1+4.38 -> 391.55 | GU11: =49.98+144.51 -> 194.49 | GY11: =30.4+249.92+190.23+320.78 -> 791.33 | GZ11: =49.98+175.39+54.51+28.98 -> 308.86 | HB11: =9.98+115.67+19.6+83.9 -> 229.15 | HD11: =190.22+36.5+173 -> 399.72 | HE11: =49.98 -> 49.98 | HI11: =(101.27+2.3)+49.21 -> 152.78 | HJ11: =49.98 -> 49.98 | HN11: =49.2+318.01 -> 367.21 | HO11: =49.98 -> 49.98 | HP11: 36.8 | HR11: 90.03 | HS11: =(49.2*2-0.16)+(45.57+13.2)+90 -> 247.01 | HT11: =49.97+12.06 -> 62.03 | HU11: 4 | HX11: 174.24 | HY11: =49.97+48.5+40.99 -> 139.46 | HZ11: 85.3 | IA11: =196.21+11.38+240+83.98+144.29 -> 675.86 | IB11: 201.79 | IC11: 133.97 | ID11: =49.99+136.99+11.7 -> 198.68 | IE11: 323.64 | IF11: =151.89+91.94+140.26+77.96 -> 462.05 | IH11: 69.89 | II11: =49.99 -> 49.99 | IK11: 183.08 | IL11: =8+121 -> 129 | IM11: =68.97+64.97+129.47 -> 263.41 | IN11: =49.99+70+20 -> 139.99 | IO11: -450 | IR11: =156.8+200+126.98+62+205.92 -> 751.7 | IS11: =49.99 -> 49.99 | IW11: 275.23 | IX11: 57.99 | JC11: =57.99+150 -> 207.99 | JH11: 57.99 | JI11: 127.99 | JJ11: 143 | JL11: 144.43 | JM11: =58.01+106.06 -> 164.07 | JN11: =142.48+124.49 -> 266.97 | JO11: =71.66+147.48 -> 219.14 | JQ11: 198.26 | JR11: =58.01+132.5 -> 190.51 | JS11: 17 | JU11: =112.76+29.9 -> 142.66 | JV11: 147.59 | JW11: =58.01+8.43 -> 66.44 | JX11: 129.9 | KA11: =129.9+(108.32+312.68) -> 550.9 | KB11: =44.59 -> 44.59 | KE11: 124.49 | KF11: =129.9+71.22 -> 201.12 | KG11: 49.91 | KK11: =129.9+73.98+360.61+(168.19+11.83+212.65-(168.2+11.83+212.65)) -> 564.48 | KL11: =49.91+45.8 -> 95.71 | KN11: =109.79+94.6 -> 204.39 | KP11: =129.9+(288.8+242.95)+217.9+47.47 -> 927.02 | KQ11: =49.91+49.91 -> 99.82 | KU11: =129.9+284.9 -> 414.8 | KV11: =232.57+149.75 -> 382.32 | KW11: =154.79+272.79 -> 427.58 | KX11: 28.93 | KY11: =83.12+13.28 -> 96.4 | KZ11: 129.9 | LA11: =49.91+174.24+96.78 -> 320.93 | LC11: =86.29+13.91 -> 100.2 | LD11: =41.91 -> 41.91 | LE11: 129.9 | LF11: =56.21+(8.79+20.82+28.35) -> 114.17 | LG11: =43.59+119.07+11.78 -> 174.44 | LH11: 109.41 | LJ11: =129.9+106.96+1.8 -> 238.66 | LK11: 56.21 | LL11: =44.73+55.91 -> 100.64 | LM11: =60.84+76.49+101.35 -> 238.68 | LO11: =129.9+26.38 -> 156.28 | LP11: =56.21+8.44+12+207.34 -> 283.99 | LR11: 63.31 | LS11: =11.78+9.9 -> 21.68 | LT11: =129.9+46.13+64+46.46 -> 286.49 | LU11: =56.21+97.2+47.17 -> 200.58 | LW11: 99.72 | LY11: =129.9+59+167.94 -> 356.84 | LZ11: =56.21+47.81 -> 104.02 | MA11: 400.9 | MC11: 34.55 | MD11: 129.9 | ME11: =56.21+44.05+71.01 -> 171.27 | MF11: 317.87 | MG11: =128.68+25.62 -> 154.3 | MH11: 8.15 | MI11: 129.9 | MJ11: =56.21+38.86 -> 95.07 | MK11: =190.35+43.16 -> 233.51 | MM11: 78.29 | MN11: 129.9 | MO11: =56.21+283.37 -> 339.58 | MQ11: 85.16 | MS11: 129.9 | MT11: 56.21 | MW11: 500 | MX11: 129.9
B12: Alimentação Fora | C12: 7.5 | D12: 15 | E12: 27.33 | F12: 54 | H12: 8.5 | I12: 19 | J12: 0 | K12: 3.96 | M12: 25.98 | N12: 6 | O12: 47.8 | P12: 39.21 | R12: 9.5 | S12: 4 | T12: 42.9 | U12: 0 | W12: 18.5 | X12: 10.7 | Y12: 168.45 | Z12: 7.88 | AB12: 1.3 | AC12: 2 | AD12: 0 | AE12: 3.6 | AG12: 5 | AH12: 5 | AI12: 0 | AJ12: 75.6 | AL12: 4.5 | AM12: 6 | AN12: 21.5 | AO12: 4 | AQ12: 3 | AR12: 25.2 | AS12: 24.5 | AT12: 2 | AV12: 0 | AW12: 18.5 | AX12: 82.3 | AY12: 62.77 | BA12: 27 | BB12: 0 | BC12: 11 | BD12: 4.5 | BE12: 0 | BF12: 0 | BG12: 4.5 | BH12: 49.31 | BI12: 0 | BJ12: 11.8 | BK12: 17.9 | BL12: 5 | BM12: 44.78 | BN12: 81.18 | BO12: 135.95 | BP12: 22.5 | BQ12: 0 | BR12: 77.57 | BS12: 57.9 | BT12: 0 | BU12: 29.79 | BV12: 4 | BW12: 20.25 | BX12: 0 | BY12: 36.09 | BZ12: 0 | CA12: 0 | CB12: 12.9 | CC12: 0 | CD12: 0 | CE12: 16 | CF12: 12.3 | CG12: 10.9 | CH12: 102.23 | CI12: 0 | CJ12: 33 | CK12: 23.58 | CL12: 75.26 | CM12: 40.3 | CN12: 0 | CO12: 0 | CP12: 10.59 | CQ12: 0 | CR12: 67.61 | CS12: 0 | CT12: 26.1 | CU12: 28.49 | CV12: 49.8 | CW12: 8 | CX12: 281.38 | CY12: 6 | CZ12: 5.5 | DA12: 0 | DB12: 0 | DC12: 612.05 | DD12: 66 | DE12: 14.5 | DF12: 4 | DG12: 22.4 | DH12: 433.69 | DI12: 23.48 | DJ12: 12 | DK12: 0 | DL12: 4 | DM12: 330.95 | DN12: 33.6 | DO12: 14.98 | DP12: 8 | DQ12: 0 | DR12: 190.42 | DS12: 30.1 | DT12: 11.49 | DU12: 3 | DV12: 5.92 | DW12: 221.5 | DX12: 4.25 | DY12: 22.5 | DZ12: 60.1 | EA12: 7.24 | EB12: 527 | EC12: 13 | ED12: 16.89 | EE12: 46.62 | EF12: 71.48 | EG12: 309.37 | IH12: 39.49 | II12: 12.5 | IK12: 16.8 | IO12: =19+5.49 -> 24.49 | IP12: 8 | JE12: 7.9 | JF12: =((50)) -> 50 | JG12: =((49.02+46.49+42.73)) -> 138.24 | JM12: 6.7 | JQ12: =13.96+32.49 -> 46.45 | JU12: 41.9 | JV12: 33.98 | JW12: =32+82.12+(16+45+43+25)+35.9 -> 279.02 | KA12: =57.75+100+43 -> 200.75 | KB12: 31.8 | KF12: 23.98 | KK12: 47.7 | KP12: =22.5+73.48 -> 95.98 | KR12: 16.97 | KS12: =17+27.47 -> 44.47 | KT12: =50.89+17.97+34.9 -> 103.76 | KU12: 36.77 | KX12: 16.89 | KY12: 46.89 | LA12: =21.99+22.98+30.5+21.99 -> 97.46 | LB12: =18.99+16.89 -> 35.88 | LC12: 16.89 | LD12: =22.4+18.99+26.98 -> 68.37 | LI12: =47.98+24+26.5 -> 98.48 | LJ12: =52.98+45.99+45.99+42.9 -> 187.86 | LK12: 10.35 | LL12: 39 | LM12: =16.89+62.1+19.5+31.9 -> 130.39 | LN12: 19.85 | LO12: =(14.9+14)+37.99+50+37.9 -> 154.79 | LQ12: =20+18.7 -> 38.7 | LR12: 37.55 | LS12: 30.98 | LT12: =47.99+21.98+36.8+36.8+27.89 -> 171.46 | LV12: 13 | LY12: =48.9+38.9+33.79+37.8+8.4+33.89 -> 201.68 | MA12: =47.3+10.79 -> 58.09 | MC12: =44+21+32.95+38.99+21.5+33.3+7.5+30.9 -> 230.14 | MD12: =42.99+13.89+37.8+45.8+17.99+30.9+44.8 -> 234.17 | ME12: =21.65+29.01+30+28.5 -> 109.16 | MF12: =7.99+34.78+26.98+26+42 -> 137.75 | MG12: =21.99+26+37.8 -> 85.79 | MH12: =32.95+38.9+25.99 -> 97.84 | MI12: =18.89+38.99 -> 57.88 | MJ12: =37.8+13.9+30+22.9 -> 104.6 | ML12: =18+10 -> 28 | MM12: =62+25.9 -> 87.9 | MN12: =38.99+18.99+37.8+35.69+13.9+28.89 -> 174.26 | MO12: =19.69+18 -> 37.69 | MS12: =28.5+20.95+30+46.1+26.99+8.02+37.8+21.99+27.99+9.9+35.5+29.99+35.94+45.42+12.5+46.89+29.4+26+21.99 -> 541.87 | MT12: =15+40 -> 55 | MX12: =22.89+37.9+21.99+64.68 -> 147.46
B13: Lazer | C13: 71 | D13: 30.07 | E13: =44.4 -> 44.4 | F13: 117.92 | I13: =44 -> 44 | J13: 46.26 | M13: 18 | Y13: 15.67 | AB13: 12 | AE13: 22 | AG13: =25+25 -> 50 | AH13: 34 | AI13: =6+53.82 -> 59.82 | AJ13: 47.96 | AN13: 45.3 | AW13: =250+20.5+8.5 -> 279 | AX13: 45.78 | AY13: 9 | BB13: 32.9 | BC13: 50 | BG13: =65+50 -> 115 | BH13: 75.24 | BO13: 62.04 | BQ13: =33.29+13.99+24.83-50 -> 22.11 | BR13: 10 | BS13: =109.39+22.48+20 -> 151.87 | BU13: 147.4 | BY13: 319.43 | CE13: 118.22 | CF13: 40.7 | CI13: 9.9 | CO13: 138.16 | CR13: =40.4+20.2+6.7+20+46.82 -> 134.12 | CS13: =80.2+12.5+37+47.19+49.56+(396+12.52+41.69+29.9+7.75+8.05+9.19+6.9+51+8.43+5.7+5.44+8.17)+10 -> 827.19 | CX13: =97.7+50.33 -> 148.03 | CY13: =(25) -> 25 | CZ13: =(100) -> 100 | DC13: =(50.1+88+15.25+102.85+135.5+12.5+15+71.9) -> 491.1 | DF13: 3.9 | DH13: =40.43+12.9+63.64 -> 116.97 | DM13: =50.38+180 -> 230.38 | DP13: 50 | DR13: =103+78.63+43.45+20+66.82 -> 311.9 | DW13: =45.57+61.55+10.45+(41.1*6-1.82)+48+5.9+170.94 -> 587.19 | EG13: =22.03+49.91 -> 71.94 | EI13: 12.99 | EK13: 9.43 | EL13: 297.3 | EQ13: 27.9 | EV13: 16.89 | FF13: 10.8 | FP13: 93.84 | FU13: =13.98+97.9+18+12.9 -> 142.78 | FV13: =15+(42+20.11) -> 77.11 | FX13: 240 | FY13: =16.75+77+39.9+25.48+15 -> 174.13 | GA13: 217.9 | GC13: =7+18.98+2+15 -> 42.98 | GE13: =14+74.97+48+50+50+28.08+20.9 -> 285.95 | GH13: =185.53+13.5 -> 199.03 | GJ13: 128.96 | GM13: 15.9 | GO13: =34.9+61.45 -> 96.35 | GQ13: 19 | GR13: =150+22.4 -> 172.4 | GT13: 237.6 | GY13: 71.29 | HD13: =39.9 -> 39.9 | HI13: 60 | HN13: 76.01 | HQ13: 217.69 | HR13: 18.18 | HT13: =135.98+4 -> 139.98 | HV13: 188.88 | HW13: 73.9 | HX13: =106.3+124.39+39.99+68 -> 338.68 | HY13: =46+32.3 -> 78.3 | IB13: 119.29 | IE13: =103.49+48.99+82 -> 234.48 | IF13: =84.5 -> 84.5 | IK13: 19 | IL13: 10.9 | IM13: =68+40.99+55.49+44.99+50.19+46.89 -> 306.55 | IQ13: 19 | IR13: =59.49+84.48 -> 143.97 | IW13: =154.34+233.41+12+62+49.44+77+91.75+39.19 -> 719.13 | JB13: =109.89+74.99+250+26+48.99 -> 509.87 | JE13: =63.89+(168.13-80)+189.48 -> 341.5 | JF13: =145.64+39.9+8+51.49 -> 245.03 | JG13: =33.99+25.88+155.34+32.99+124.49 -> 372.69 | JH13: =114.12+20+83.01 -> 217.13 | JI13: 25.8 | JK13: =94.99+74.02+44.98 -> 213.99 | JL13: =54.97+39.9+58.9+12+(16.5+13.9+20+12) -> 228.17 | JM13: =200+28.98+84.9 -> 313.88 | JO13: 55.99 | JQ13: =39.9+100+23.99+39.19+(84.9+47.99)+142 -> 477.97 | JS13: 73 | JT13: =134.7-46-48.5 -> 40.2 | JU13: =98.5-20+69.93 -> 148.43 | JV13: =39.9+147.89+13+74.79+152.49+79+38.7+13 -> 558.77 | JW13: 73.3 | KA13: =309.12+299.39+13 -> 621.51 | KE13: =38.76+20+13 -> 71.76 | KF13: =147.48+53.95+147.48-50-6+122.43+(13+6.98+361.26)+46.37 -> 842.95 | KG13: 170 | KK13: =356.39+57.09+26+35.4+125+(12+13+13)+18+28.38+75.99-19 -> 741.25 | KL13: 31.5 | KM13: 99.66 | KO13: =15.5+6+343.86+48.4+17+37 -> 467.76 | KP13: =90+20+25.8+(192.62+85.63-47.47-100)+104.6+13+27.8+71.9 -> 483.88 | KQ13: 13 | KR13: =14+21.25+36.95 -> 72.2 | KS13: 19.8 | KU13: =14+25.8+51+28.8+100+20+10+6+332.31+155+14 -> 756.91 | KV13: =25.68+114+66.99 -> 206.67 | KW13: 69.9 | KX13: =18+26 -> 44 | KY13: =11.9+11.35 -> 23.25 | LA13: =27.88+15.8+114 -> 157.68 | LB13: =146.66 -> 146.66 | LH13: =15+132 -> 147 | LI13: =14+23.54+11.9+34 -> 83.44 | LJ13: 16.89 | LK13: 52.98 | LL13: =19.99+14.95+29.85 -> 64.79 | LN13: =47.98+16.4+101.53+16.07 -> 181.98 | LO13: =38.7+(92.45+22.5+26+16.5+16) -> 212.15 | LP13: 81.4 | LS13: =126.98+53.79+14 -> 194.77 | LT13: =63.89+35.9+19.8 -> 119.59 | LU13: 40 | LV13: =4+81.26 -> 85.26 | LX13: =186+18.5 -> 204.5 | LY13: =6+118+45.7+88.32 -> 258.02 | MB13: 248.64 | MC13: 29.12 | MD13: =219.07+56.18+68.99 -> 344.24 | MF13: 30.97 | MG13: 110 | MH13: =74.6+13.4 -> 88 | MK13: 37.18 | MS13: =314.14+69.9+108.89 -> 492.93 | MX13: =114.67+195.94 -> 310.61
B14: Casa | F14: 200 | K14: =202+2125.26 -> 2327.26 | P14: 202 | U14: =202+110 -> 312 | Z14: 202 | AE14: 202 | AJ14: 202 | AL14: 457.02 | AN14: =1386.18+139.74 -> 1525.92 | AO14: 202 | AT14: =202+125.74 -> 327.74 | AY14: =202+125.79 -> 327.79 | BD14: 202 | BI14: 202 | BJ14: =160+220+115.52 -> 495.52 | BL14: 190 | BM14: =244.28+2267.74 -> 2512.02 | BN14: 202 | BO14: 76.24 | BS14: 202 | BT14: =76.24+45.5+98.87-75 -> 145.61 | BX14: 202 | BY14: =(420.13+115.2+30-600)+76.24+71.32 -> 112.89 | BZ14: 100 | CC14: 202 | CD14: =80.21+71.31 -> 151.52 | CI14: =49.28+80.19+71.31+47.27+45.5 -> 293.55 | CN14: =80.19+71.2 -> 151.39 | CS14: =71.2+66 -> 137.2 | CX14: =71.2+66 -> 137.2 | DC14: =66+275+273.98-600 -> 14.98 | DH14: =66+(309.8/2-160)+58.65 -> 119.55 | DM14: =309.8/2+(58.64*5-1.85)+100+147.23 -> 693.48 | DW14: =(146.32-145) -> 1.32 | EB14: =146.31+65 -> 211.31 | EG14: =64.99+500 -> 564.99 | EL14: 500 | EQ14: =500+24 -> 524 | EV14: 500 | FA14: =500+24 -> 524 | FC14: 400 | FF14: =500+74.97+82.36+(56.67+56.66*2-0.22)+24 -> 851.1 | FK14: =500+24 -> 524 | FP14: =500+24 -> 524 | FS14: =750+400 -> 1150 | FU14: =500+24 -> 524 | FZ14: =500+24 -> 524 | GE14: 24 | GG14: 600 | GJ14: 24 | GK14: 300 | GL14: 489.26 | GO14: 28 | GT14: =28+147 -> 175 | GY14: =28+131.5 -> 159.5 | GZ14: =4663.26+500 -> 5163.26 | HA14: =2000+10291.26*2+2718.61+1500 -> 26801.13 | HB14: =500+190+431.06+155.19+3324.8+(750*4+11+4000)+50+1000+300+2000+330.6+216+300 -> 15808.65 | HC14: =79.4+98.95+660.5+1000+140+1300+324.05+35.5+17.7+((1830.03+861.45+928.81+305.29)+(37.54*5+39.42+41.29+44.74+45.05)+(273.43*6+289.46+305.49+334.88+337.55))+1000+(10.5+5.75)+((1974.5+1903.07+770.69+4843.68))+500+808.29+101.87+25.17 -> 22791.36 | HG14: =(18.5+9.7+35.7+68.8)+288.3+1500+500+150 -> 2571 | HJ14: =600+7+1000+250+100 -> 1957 | HK14: =62+940+1000+500+135 -> 2637 | HL14: =255+138+1000 -> 1393 | HN14: =36+180+100.18+386.94+176.55+119.94+248.27 -> 1247.88 | HP14: =325+1500+3000 -> 4825 | HR14: =982.69+141.5+(25+34+58.5)+232+800 -> 2273.69 | ID14: =600+65+74.5+50+187.06+2000+1914.1+140+295+1500+2000+75+100+210+500+37.8+380+1432+184.1+299+2500+315+2000+480+51.9+870 -> 18260.46 | IG14: =149.3+31+2000+((382.01+255.65+389.78+296.25+344.16+322.71+293.5+391.86+326.79+281.16+387.35+281.16+385.31+389.81+273.68+198.43+346.88+290.85+310.06+324.61))+179.87+340+3000+165 -> 12337.18 | IM14: =36+39.9+155.61+36.48 -> 267.99 | IO14: =2000+89.5 -> 2089.5 | IR14: =155.61+36+39.9+100 -> 331.51 | IS14: =652.31+450+2000 -> 3102.31 | IU14: =310+2000+322.5 -> 2632.5 | IV14: =64+367.5+2000+675 -> 3106.5 | IW14: =36+39.9+155.61 -> 231.51 | IX14: =450+2000+58.03+795.4+199+1230+347.5+2000 -> 7079.93 | IY14: 2000 | IZ14: =2000+20 -> 2020 | JA14: 2000 | JB14: =36+39.9+(155.61+155.61-1.12)+194.45+42.9+50.49+(44.62+44.58*11-20.62)+156.28+89.6+167.5 -> 1601.6 | JC14: =880.74+58.03+409.07+325+450+2000+44 -> 4166.84 | JG14: =36+39.9+1033.35+204.35 -> 1313.6 | JK14: =65.6 -> 65.6 | JL14: =36+39.9+1033.33+275+63.8 -> 1448.03 | JM14: =450+2000+426.99+162.5+2000 -> 5039.49 | JN14: =837.88+2000+189.1 -> 3026.98 | JO14: =105+2000+126.5+58.03 -> 2289.53 | JP14: =185+160.86+199+2000 -> 2544.86 | JQ14: =1033.33+36+39.9+482.09 -> 1591.32 | JR14: =58.03+450+332.51+255+2000 -> 3095.54 | JS14: 2000 | JT14: =841+269.6+591.2+2000+29.05+1704.66 -> 5435.51 | JX14: 1000 | JY14: 1000 | JZ14: 500 | KB14: =322.42+500 -> 822.42 | KC14: 500 | KD14: 1000 | KE14: 1000 | KG14: =183.47+450+353.21+1000 -> 1986.68 | KH14: 1000 | KI14: 1000 | KJ14: 1000 | KK14: =36+39.9+(61.99+54+61+88.75+88.75)+318.16+50+141.33+12 -> 951.88 | KL14: =450+446.53+134.73+1000+46 -> 2077.26 | KR14: =454.2+139.9+600 -> 1194.1 | KS14: =405.19 -> 405.19 | KU14: =36+39.9+14.9 -> 90.8 | KV14: =64.88+450 -> 514.88 | KZ14: =36+39.9+14.9+10.45 -> 101.25 | LA14: =64.88+450+513.84+3660 -> 4688.72 | LC14: 301.26 | LE14: =36+39.9+19.9 -> 95.8 | LF14: =64.88+882.56+529.71 -> 1477.15 | LI14: 216.31 | LJ14: =36+39.9+19.9+(316.25-315) -> 97.05 | LK14: =472.32 -> 472.32 | LO14: =36+39.9+19.9+(316.25-315)+241.25 -> 338.3 | LP14: =64.88+204.95+360.15 -> 629.98 | LR14: 87.39 | LT14: =36+19.9+(50+69.44+66.34) -> 241.68 | LU14: =64.88+894.41+286.41+12668.63 -> 13914.33 | LV14: =99.9+859.82 -> 959.72 | LW14: =351.11-352 -> -0.89 | LY14: =36+19.9+(50+69.44+66.33) -> 241.67 | MD14: =36+19.9+(50+69.44+66.33) -> 241.67 | ME14: =85.23+136.72+160+15+289.08+(943.9+678.14+201.05) -> 2509.12 | MH14: =202.32+70+180+36 -> 488.32 | MI14: =36+130+37.9 -> 203.9 | MJ14: =85.23+342.85+943.9+678.14+201.05+(306.27+139.98) -> 2697.42 | MN14: =36+130 -> 166 | MO14: =85.23+379.52+306.26+943.9+678.14+201.05 -> 2594.1 | MS14: =36+130 -> 166 | MT14: =96.13+377.27+943.9 -> 1417.3
B15: Apto | KQ15: =1200+586+2400 -> 4186 | KR15: =102.77+273.96+27 -> 403.73 | KS15: =5823+1529.1+129+20+2741.62 -> 10242.72 | KT15: =109.9+45.68+181.48+23.9+28.9+406.98 -> 796.84 | KU15: =98.59+(44.74+44.73*3-2.23)+101.8+119.9+23.12+82.62+99.9+58.65+233.87+53.82+210.57+147.95+71.84+61.9+80.38+71.99*2+234.97 -> 2000.56 | KV15: =1200+586.1 -> 1786.1 | KW15: =25.02+51.5 -> 76.52 | KY15: =150+20+39.42 -> 209.42 | KZ15: =171.63+25.02 -> 196.65 | LA15: =1200+679.39+99.9+154.28+129.51 -> 2263.08 | LD15: 99.9 | LE15: 1143.27 | LF15: =1200+679.39+154.28+143.61+68.59 -> 2245.87 | LI15: 104.91 | LJ15: 908.3 | LK15: =1200+679.37+154.28+99.9+177 -> 2310.55 | LM15: 70 | LO15: =908.3+37.51 -> 945.81 | LP15: =1200+679.38+154.28+99.9+68.59+127.07 -> 2329.22 | LS15: =68.33+99.9 -> 168.23 | LT15: 945.79 | LU15: =1200+679.38+154.28+128.25+68.33+68.13+(228.41+232.13) -> 2758.91 | LX15: 99.9 | LY15: =945.79+(94.19+92.89+62.43+67.25+24.4+27.35) -> 1314.3 | LZ15: =1200+679.38+154.28+127.93+68.13 -> 2229.72 | MC15: 99.9 | MD15: =945.79+40.4+420+180+(80.29*2-2)+(69.44*2-1.73)+(233.81-0.39)+(37.49*2-0.94)+(10.45*3-0.52)+(50-0.42)+(53.75-0.45) -> 2323.09 | MF15: =117+92+260.4+15.77+69.89 -> 555.06 | MH15: 99.9 | MI15: =21.9+1224.14+(66.99+66.98-0.56)+14.9+43.7 -> 1438.05 | MJ15: =1200+679.38+154.28+128.59 -> 2162.25 | ML15: 146.82 | MM15: 99.9 | MN15: =21.9+14.9+990.33 -> 1027.13 | MO15: =1200+679.38+154.28+66.13+163.29 -> 2263.08 | MR15: 99.9 | MS15: =21.9+14.9+30.93+779.82+(23.85+97.6) -> 969 | MT15: =1200+679.38+154.28+66.97+145.24 -> 2245.87 | MW15: 99.9 | MX15: =21.9+14.9+729.64 -> 766.44
B16: Outros | C16: 24 | D16: =4.55 -> 4.55 | H16: =5+4.55 -> 9.55 | J16: 1 | M16: =4.55+0.35 -> 4.9 | N16: =47+7 -> 54 | P16: 15 | R16: =5+4.55 -> 9.55 | U16: =0.9*3+15 -> 17.7 | W16: =45+(2.42+0.23+0.07) -> 47.72 | X16: =4.55+16 -> 20.55 | AB16: =1.09+0.09+12 -> 13.18 | AC16: 20 | AE16: 1.25 | AI16: =20+5+20+1.5 -> 46.5 | AJ16: =1+10 -> 11 | AL16: 0.58 | AQ16: 0.05 | AX16: =0.9 -> 0.9 | BA16: =0.57+0.03 -> 0.6 | BF16: 1.04 | BK16: 7 | BO16: =12+39 -> 51 | BS16: 0.99 | BT16: 27.9 | BY16: =27.9+24.74 -> 52.64 | CD16: 27.9 | CE16: 10 | CF16: 0.5 | CI16: 27.9 | CJ16: 0.02 | CN16: 27.9 | CS16: 27.9 | CT16: 0.3 | CX16: 27.9 | CY16: =10.17+0.65 -> 10.82 | DC16: =10.9+27.9 -> 38.8 | DG16: 8 | DH16: =27.9+13.97 -> 41.87 | DI16: 0.55 | DM16: 27.9 | DN16: 2.2 | DR16: 27.9 | DU16: =16.32 -> 16.32 | DW16: =45.7+27.9+0.1 -> 73.7 | EB16: =27.9 -> 27.9 | EC16: =1.57+0.1 -> 1.67 | EG16: 27.9 | EH16: =1.29+0.11+10 -> 11.4 | EL16: 32.9 | EQ16: =1.28+32.9 -> 34.18 | ER16: 9.53 | EU16: 13.81 | EV16: 56.9 | FA16: =32.9 -> 32.9 | FC16: 27 | FF16: =13.9 -> 13.9 | FK16: =(482-481.48-1.04) -> -0.52 | GK16: =1.55 -> 1.55 | GP16: =0.28 -> 0.28 | GT16: 103.24 | GW16: 313.39 | GX16: 2000 | GY16: 39.9 | GZ16: 0.01 | HC16: =25 -> 25 | HF16: 50 | HL16: 62.3 | HS16: =150.27 -> 150.27 | HV16: =140.61+387.6 -> 528.21 | HW16: 507.2 | IB16: =53.97+60.8 -> 114.77 | ID16: 28.7 | IE16: =60+4.8 -> 64.8 | II16: =(0.16+0.15) -> 0.31 | IN16: =1.64+1.05+0.05 -> 2.74 | IQ16: =65.6*2 -> 131.2 | IS16: =1.39+1.34+0.02 -> 2.75 | IW16: -383.96 | JB16: =586.89+63.92+13.33+67.45-144.7-0.01-202 -> 384.88 | JD16: =10 -> 10 | JH16: =10 -> 10 | JI16: 15 | JM16: =1.39+0.69+0.02+50+17 -> 69.1 | JS16: =550+293.47 -> 843.47 | JV16: =-550-79+49.2 -> -579.8 | JW16: =(17.32-0.87-2.63-4.2-0.68-0.68-21.36-1.74) -> -14.84 | JX16: 15 | KA16: =-49.2*2 -> -98.4 | KE16: =200+20 -> 220 | KF16: =49.2-200-20.55 -> -171.35 | KJ16: =17+4 -> 21 | KK16: 0.1 | KL16: =3.38+1.51+0.13 -> 5.02 | KM16: 40 | KO16: 40 | KP16: =-0.41-40 -> -40.41 | KQ16: =105.75 -> 105.75 | KS16: =(328.25-330) -> -1.75 | KU16: =(600.02+143.02-742)+(109.41+3.09-110)+156.16 -> 159.7 | KV16: =0.26+0.26+1033.12+207.02+52.06 -> 1292.72 | KW16: 17 | KX16: =(116.08-94-22) -> 0.08 | KY16: =(338.86-330) -> 8.86 | KZ16: =-(171.55+25.02+10.45+52.06) -> -259.08 | LA16: =56.98+57.95+17 -> 131.93 | LC16: 10 | LE16: =-51.98-5+9.93-10 -> -57.05 | LF16: =(4.83+0.11+1.36) -> 6.3 | LG16: 760.91 | LH16: =17+15.89 -> 32.89 | LI16: 100 | LJ16: =-760.91-15.89-100 -> -876.8 | LK16: 0.03 | LL16: =(108.06+37.9+110) -> 255.96 | LM16: =100 -> 100 | LN16: =17+20 -> 37 | LO16: =-108.06-37.9-110-100-45 -> -400.96 | LR16: =17+20+3.81 -> 40.81 | LT16: =316.25-3.81 -> 312.44 | LW16: 20 | LY16: =316.25 -> 316.25 | MB16: =1800+20 -> 1820 | MC16: =6.94+355.6+20+200+100-612.19 -> 70.35 | MD16: =-1800-6.94-355.6-200-100+612.19 -> -1850.35 | ME16: 6.22 | MF16: =58.8+37.7 -> 96.5 | MI16: =-6.22-58.8-37.7 -> -102.72 | MJ16: 20 | MK16: 88.17 | MO16: 20 | MS16: =5.12+56.31+0.28+3.03+24.53 -> 89.27 | MT16: 20 | MX16: =-129.9-14.9 -> -144.8
A19: Subtotais | B19: Receitas | C19: =SUBTOTAL(9, C3:C4) -> 0 | D19: =SUBTOTAL(9, D3:D4) -> 1534.716 | E19: =SUBTOTAL(9, E3:E4) -> 0 | F19: =SUBTOTAL(9, F3:F4) -> 936.764 | G19: =SUBTOTAL(9, G3:G4) -> 0 | H19: =SUBTOTAL(9, H3:H4) -> 0 | I19: =SUBTOTAL(9, I3:I4) -> 734.72 | J19: =SUBTOTAL(9, J3:J4) -> 0 | ... MX19: =SUBTOTAL(9, MX3:MX4) -> 0
B20: Despesas | C20: =SUBTOTAL(9,C6:C16)*-1 -> -302.5 | D20: =SUBTOTAL(9,D6:D16)*-1 -> -144.25 | E20: =SUBTOTAL(9,E6:E16)*-1 -> -433.44 | F20: =SUBTOTAL(9,F6:F16)*-1 -> -386.76 | G20: =SUBTOTAL(9,G6:G16)*-1 -> 0 | H20: =SUBTOTAL(9,H6:H16)*-1 -> -202.69 | I20: =SUBTOTAL(9,I6:I16)*-1 -> -139.93 | J20: =SUBTOTAL(9,J6:J16)*-1 -> -513.4 | ... MX20: =SUBTOTAL(9,MX6:MX16)*-1 -> -1878.52
A22: Saldos | B22: Na semana | C22: =SUM(C19:C20) -> -302.5 | D22: =SUM(D19:D20) -> 1390.466 | E22: =SUM(E19:E20) -> -433.44 | F22: =SUM(F19:F20) -> 550.004 | G22: =SUM(G19:G20) -> 0 | H22: =SUM(H19:H20) -> -202.69 | I22: =SUM(I19:I20) -> 594.79 | J22: =SUM(J19:J20) -> -513.4 | ... MX22: =SUM(MX19:MX20) -> -1878.52
B23: Acumulado | C23: =SUM(C22) -> -302.5 | D23: =C23+D22 -> 1087.966 | E23: =D23+E22 -> 654.526 | F23: =E23+F22 -> 1204.53 | G23: =F23+G22 -> 1204.53 | H23: =G23+H22 -> 1001.84 | I23: =H23+I22 -> 1596.63 | J23: =I23+J22 -> 1083.23 | K23: =J23+K22 -> 906.98 | ... MX23: =MW23+MX22 -> 522.46

Sheet Perguntas 25 e 26 - Financeiro
C2: Preencha as linhas 22 e 23 da planilha Controle Financeiro com o somatório de receitas e despesas por semana. Depois preencha a linha 25 com o saldo da semana (receita - despesas) e a linha 26 com o saldo acumulado (saldo acumulado da semana = saldo acumulado da semana anterior + receitas da semana - despesas da semana)
C5: Preencha o resumo abaixo com o somatório de despesas mensais de 2018 até 2023. É necessário desenvolver uma única fórmula que poderá ser arrastada para baixo e preencher todos os meses.
B7: 0 | C7: 2018 | D7: JAN | E7: =SUM(OFFSET('Controle Financeiro'!$C$6:$G$16,0,5*B7)) -> 1266.95
B8: 1 | D8: FEV | E8: =SUM(OFFSET('Controle Financeiro'!$C$6:$G$16,0,5*B8)) -> 3230.5
B9: 2 | D9: MAR | E9: =SUM(OFFSET('Controle Financeiro'!$C$6:$G$16,0,5*B9)) -> 1082.54
B10: 3 | D10: ABR | E10: =SUM(OFFSET('Controle Financeiro'!$C$6:$G$16,0,5*B10)) -> 792.31
B11: 4 | D11: MAI | E11: =SUM(OFFSET('Controle Financeiro'!$C$6:$G$16,0,5*B11)) -> 865.91
B12: 5 | D12: JUN | E12: =SUM(OFFSET('Controle Financeiro'!$C$6:$G$16,0,5*B12)) -> 903.61
B13: 6 | D13: JUL | E13: =SUM(OFFSET('Controle Financeiro'!$C$6:$G$16,0,5*B13)) -> 955.84
B14: 7 | D14: AGO | E14: =SUM(OFFSET('Controle Financeiro'!$C$6:$G$16,0,5*B14)) -> 2595.99
B15: 8 | D15: SET | E15: =SUM(OFFSET('Controle Financeiro'!$C$6:$G$16,0,5*B15)) -> 1038.89
B16: 9 | D16: OUT | E16: =SUM(OFFSET('Controle Financeiro'!$C$6:$G$16,0,5*B16)) -> 1241.14
B17: 10 | D17: NOV | E17: =SUM(OFFSET('Controle Financeiro'!$C$6:$G$16,0,5*B17)) -> 927.94
B18: 11 | D18: DEZ | E18: =SUM(OFFSET('Controle Financeiro'!$C$6:$G$16,0,5*B18)) -> 1690.34
B19: 12 | C19: 2019 | D19: JAN | E19: =SUM(OFFSET('Controle Financeiro'!$C$6:$G$16,0,5*B19)) -> 3629.5
B20: 13 | D20: FEV | E20: =SUM(OFFSET('Controle Financeiro'!$C$6:$G$16,0,5*B20)) -> 1013.25
B21: 14 | D21: MAR | E21: =SUM(OFFSET('Controle Financeiro'!$C$6:$G$16,0,5*B21)) -> 1234.87
B22: 15 | D22: ABR | E22: =SUM(OFFSET('Controle Financeiro'!$C$6:$G$16,0,5*B22)) -> 877.05
B23: 16 | D23: MAI | E23: =SUM(OFFSET('Controle Financeiro'!$C$6:$G$16,0,5*B23)) -> 1230.65
B24: 17 | D24: JUN | E24: =SUM(OFFSET('Controle Financeiro'!$C$6:$G$16,0,5*B24)) -> 1042.01
B25: 18 | D25: JUL | E25: =SUM(OFFSET('Controle Financeiro'!$C$6:$G$16,0,5*B25)) -> 2361.32
B26: 19 | D26: AGO | E26: =SUM(OFFSET('Controle Financeiro'!$C$6:$G$16,0,5*B26)) -> 1069.57
B27: 20 | D27: SET | E27: =SUM(OFFSET('Controle Financeiro'!$C$6:$G$16,0,5*B27)) -> 2019.12
B28: 21 | D28: OUT | E28: =SUM(OFFSET('Controle Financeiro'!$C$6:$G$16,0,5*B28)) -> 1448.37
B29: 22 | D29: NOV | E29: =SUM(OFFSET('Controle Financeiro'!$C$6:$G$16,0,5*B29)) -> 2295.73
B30: 23 | D30: DEZ | E30: =SUM(OFFSET('Controle Financeiro'!$C$6:$G$16,0,5*B30)) -> 1866.99
B31: 24 | C31: 2020 | D31: JAN | E31: =SUM(OFFSET('Controle Financeiro'!$C$6:$G$16,0,5*B31)) -> 1494.57
B32: 25 | D32: FEV | E32: =SUM(OFFSET('Controle Financeiro'!$C$6:$G$16,0,5*B32)) -> 1648.19
B33: 26 | D33: MAR | E33: =SUM(OFFSET('Controle Financeiro'!$C$6:$G$16,0,5*B33)) -> 2450.11
B34: 27 | D34: ABR | E34: =SUM(OFFSET('Controle Financeiro'!$C$6:$G$16,0,5*B34)) -> 1656.34
B35: 28 | D35: MAI | E35: =SUM(OFFSET('Controle Financeiro'!$C$6:$G$16,0,5*B35)) -> 1206.31
B36: 29 | D36: JUN | E36: =SUM(OFFSET('Controle Financeiro'!$C$6:$G$16,0,5*B36)) -> 1016.57
B37: 30 | D37: JUL | E37: =SUM(OFFSET('Controle Financeiro'!$C$6:$G$16,0,5*B37)) -> 1957.84
B38: 31 | D38: AGO | E38: =SUM(OFFSET('Controle Financeiro'!$C$6:$G$16,0,5*B38)) -> 3009.31
B39: 32 | D39: SET | E39: =SUM(OFFSET('Controle Financeiro'!$C$6:$G$16,0,5*B39)) -> 718.47
B40: 33 | D40: OUT | E40: =SUM(OFFSET('Controle Financeiro'!$C$6:$G$16,0,5*B40)) -> 801.84
B41: 34 | D41: NOV | E41: =SUM(OFFSET('Controle Financeiro'!$C$6:$G$16,0,5*B41)) -> 2246.52
B42: 35 | D42: DEZ | E42: =SUM(OFFSET('Controle Financeiro'!$C$6:$G$16,0,5*B42)) -> 2485.03
B43: 36 | C43: 2021 | D43: JAN | E43: =SUM(OFFSET('Controle Financeiro'!$C$6:$G$16,0,5*B43)) -> 1693.37
B44: 37 | D44: FEV | E44: =SUM(OFFSET('Controle Financeiro'!$C$6:$G$16,0,5*B44)) -> 2695.47
B45: 38 | D45: MAR | E45: =SUM(OFFSET('Controle Financeiro'!$C$6:$G$16,0,5*B45)) -> 1304.09
B46: 39 | D46: ABR | E46: =SUM(OFFSET('Controle Financeiro'!$C$6:$G$16,0,5*B46)) -> 1149.05
B47: 40 | D47: MAI | E47: =SUM(OFFSET('Controle Financeiro'!$C$6:$G$16,0,5*B47)) -> 5438.87
B48: 41 | D48: JUN | E48: =SUM(OFFSET('Controle Financeiro'!$C$6:$G$16,0,5*B48)) -> 71856.23
B49: 42 | D49: JUL | E49: =SUM(OFFSET('Controle Financeiro'!$C$6:$G$16,0,5*B49)) -> 3134.92
B50: 43 | D50: AGO | E50: =SUM(OFFSET('Controle Financeiro'!$C$6:$G$16,0,5*B50)) -> 8163.27
B51: 44 | D51: SET | E51: =SUM(OFFSET('Controle Financeiro'!$C$6:$G$16,0,5*B51)) -> 9929.79
B52: 45 | D52: OUT | E52: =SUM(OFFSET('Controle Financeiro'!$C$6:$G$16,0,5*B52)) -> 2495.84
B53: 46 | D53: NOV | E53: =SUM(OFFSET('Controle Financeiro'!$C$6:$G$16,0,5*B53)) -> 2106.96
B54: 47 | D54: DEZ | E54: =SUM(OFFSET('Controle Financeiro'!$C$6:$G$16,0,5*B54)) -> 33052.98
B55: 48 | C55: 2022 | D55: JAN | E55: =SUM(OFFSET('Controle Financeiro'!$C$6:$G$16,0,5*B55)) -> 1470.06
B56: 49 | D56: FEV | E56: =SUM(OFFSET('Controle Financeiro'!$C$6:$G$16,0,5*B56)) -> 3611.85
B57: 50 | D57: MAR | E57: =SUM(OFFSET('Controle Financeiro'!$C$6:$G$16,0,5*B57)) -> 10772.42
B58: 51 | D58: ABR | E58: =SUM(OFFSET('Controle Financeiro'!$C$6:$G$16,0,5*B58)) -> 16835.04
B59: 52 | D59: MAI | E59: =SUM(OFFSET('Controle Financeiro'!$C$6:$G$16,0,5*B59)) -> 8607.84
B60: 53 | D60: JUN | E60: =SUM(OFFSET('Controle Financeiro'!$C$6:$G$16,0,5*B60)) -> 4430.59
B61: 54 | D61: JUL | E61: =SUM(OFFSET('Controle Financeiro'!$C$6:$G$16,0,5*B61)) -> 18909.67
B62: 55 | D62: AGO | E62: =SUM(OFFSET('Controle Financeiro'!$C$6:$G$16,0,5*B62)) -> 14145.52
B63: 56 | D63: SET | E63: =SUM(OFFSET('Controle Financeiro'!$C$6:$G$16,0,5*B63)) -> 5086.67
B64: 57 | D64: OUT | E64: =SUM(OFFSET('Controle Financeiro'!$C$6:$G$16,0,5*B64)) -> 5521.21
B65: 58 | D65: NOV | E65: =SUM(OFFSET('Controle Financeiro'!$C$6:$G$16,0,5*B65)) -> 8187.45
B66: 59 | D66: DEZ | E66: =SUM(OFFSET('Controle Financeiro'!$C$6:$G$16,0,5*B66)) -> 5807.3
B67: 60 | C67: 2023 | D67: JAN | E67: =SUM(OFFSET('Controle Financeiro'!$C$6:$G$16,0,5*B67)) -> 22236.08
B68: 61 | D68: FEV | E68: =SUM(OFFSET('Controle Financeiro'!$C$6:$G$16,0,5*B68)) -> 5972.9
B69: 62 | D69: MAR | E69: =SUM(OFFSET('Controle Financeiro'!$C$6:$G$16,0,5*B69)) -> 10492.26
B70: 63 | D70: ABR | E70: =SUM(OFFSET('Controle Financeiro'!$C$6:$G$16,0,5*B70)) -> 7377.93
B71: 64 | D71: MAI | E71: =SUM(OFFSET('Controle Financeiro'!$C$6:$G$16,0,5*B71)) -> 6988.17
B72: 65 | D72: JUN | E72: =SUM(OFFSET('Controle Financeiro'!$C$6:$G$16,0,5*B72)) -> 6689.3
B73: 66 | D73: JUL | E73: =SUM(OFFSET('Controle Financeiro'!$C$6:$G$16,0,5*B73)) -> 23246.8
B74: 67 | D74: AGO | E74: =SUM(OFFSET('Controle Financeiro'!$C$6:$G$16,0,5*B74)) -> 8787.53
B75: 68 | D75: SET | E75: =SUM(OFFSET('Controle Financeiro'!$C$6:$G$16,0,5*B75)) -> 7585.62
B76: 69 | D76: OUT | E76: =SUM(OFFSET('Controle Financeiro'!$C$6:$G$16,0,5*B76)) -> 8292.64
B77: 70 | D77: NOV | E77: =SUM(OFFSET('Controle Financeiro'!$C$6:$G$16,0,5*B77)) -> 9574.83
B78: 71 | D78: DEZ | E78: =SUM(OFFSET('Controle Financeiro'!$C$6:$G$16,0,5*B78)) -> 6272.8

Sheet Base Vendas
A1: Data | B1: Código | C1: Funcionário | D1: Produto | E1: Marca | F1: Valor | K1: Funcionário | L1: Total Vendido | N1: Produto | O1: Valor
A2: 43466 | B2: R6S4T3I9 | C2: Otávio | D2: Calça | E2: Amarela | F2: 180 | K2: {=_xlfn.UNIQUE(C2:C3500)} -> Otávio | L2: =SUMIFS(F:F, C:C, K2) -> 21260 | N2: {=_xlfn.UNIQUE(D2:D3500)} -> Calça | O2: =SUMIFS(F:F, D:D, N2, E:E, "Verde") -> 15120
A3: 43466 | B3: I1I1O7Q3 | C3: Caio | D3: Calça | E3: Amarela | F3: 180 | K3: Caio | L3: =SUMIFS(F:F, C:C, K3) -> 20250 | N3: Camisa | O3: =SUMIFS(F:F, D:D, N3, E:E, "Verde") -> 14240
A4: 43467 | B4: H9A4X9Z1 | C4: Gabriel | D4: Calça | E4: Amarela | F4: 180 | K4: Gabriel | L4: =SUMIFS(F:F, C:C, K4) -> 22920 | N4: Bermuda | O4: =SUMIFS(F:F, D:D, N4, E:E, "Verde") -> 14550
A5: 43468 | B5: N6L5S6E9 | C5: Luan | D5: Calça | E5: Amarela | F5: 180 | K5: Luan | L5: =SUMIFS(F:F, C:C, K5) -> 19250 | N5: Camiseta | O5: =SUMIFS(F:F, D:D, N5, E:E, "Verde") -> 9700
A6: 43469 | B6: F4O2T7Z1 | C6: Kelly | D6: Calça | E6: Amarela | F6: 180 | K6: Kelly | L6: =SUMIFS(F:F, C:C, K6) -> 21930 | N6: Chapéu | O6: =SUMIFS(F:F, D:D, N6, E:E, "Verde") -> 7380
A7: 43470 | B7: L8G2L1P2 | C7: Gabriel | D7: Calça | E7: Branca | F7: 180 | K7: Pablo | L7: =SUMIFS(F:F, C:C, K7) -> 24480 | N7: Saia | O7: =SUMIFS(F:F, D:D, N7, E:E, "Verde") -> 7200
A8: 43471 | B8: Q4C6T5X6 | C8: Pablo | D8: Calça | E8: Verde | F8: 180 | K8: Bernardo | L8: =SUMIFS(F:F, C:C, K8) -> 23860 | N8: Boné | O8: =SUMIFS(F:F, D:D, N8, E:E, "Verde") -> 4800
A9: 43472 | B9: C3K1A8F6 | C9: Otávio | D9: Calça | E9: Azul | F9: 180 | K9: Natália | L9: =SUMIFS(F:F, C:C, K9) -> 23380 | N9: Chinelo | O9: =SUMIFS(F:F, D:D, N9, E:E, "Verde") -> 2640
A10: 43473 | B10: U4C7L3R5 | C10: Bernardo | D10: Calça | E10: Branca | F10: 180 | K10: Rafaela | L10: =SUMIFS(F:F, C:C, K10) -> 23230
A11: 43473 | B11: N1C5C9U9 | C11: Natália | D11: Calça | E11: Vermelha | F11: 180 | K11: Helena | L11: =SUMIFS(F:F, C:C, K11) -> 24290
A12: 43473 | B12: Z3J2C7U9 | C12: Rafaela | D12: Calça | E12: Verde | F12: 180 | K12: Iago | L12: =SUMIFS(F:F, C:C, K12) -> 23550
A13: 43474 | B13: U8F3C1R9 | C13: Helena | D13: Calça | E13: Azul | F13: 180 | K13: Amanda | L13: =SUMIFS(F:F, C:C, K13) -> 22080
A14: 43474 | B14: G8N3Q3D5 | C14: Iago | D14: Calça | E14: Vermelha | F14: 180 | K14: Eduarda | L14: =SUMIFS(F:F, C:C, K14) -> 16750
A15: 43476 | B15: R9Q3J6O4 | C15: Pablo | D15: Calça | E15: Branca | F15: 180 | K15: Fábio | L15: =SUMIFS(F:F, C:C, K15) -> 22790
A16: 43476 | B16: V9N5N7M3 | C16: Bernardo | D16: Calça | E16: Branca | F16: 180 | K16: Daniel | L16: =SUMIFS(F:F, C:C, K16) -> 21820
A17: 43478 | B17: Q7L9D3L2 | C17: Bernardo | D17: Calça | E17: Verde | F17: 180 | K17: João | L17: =SUMIFS(F:F, C:C, K17) -> 20880
A18: 43479 | B18: C9T6N2R7 | C18: Amanda | D18: Calça | E18: Verde | F18: 180 | K18: Marcela | L18: =SUMIFS(F:F, C:C, K18) -> 17890
A19: 43480 | B19: C1H9T5P7 | C19: Otávio | D19: Calça | E19: Branca | F19: 180
A20: 43481 | B20: V6C6C2Q5 | C20: Iago | D20: Calça | E20: Amarela | F20: 180
A21: 43481 | B21: C8P6B9E9 | C21: Eduarda | D21: Calça | E21: Branca | F21: 180
A22: 43482 | B22: R8A6T8E8 | C22: Rafaela | D22: Calça | E22: Azul | F22: 180
A23: 43482 | B23: O6X2S7D7 | C23: Iago | D23: Calça | E23: Azul | F23: 180
A24: 43483 | B24: Q7K8N3S8 | C24: Rafaela | D24: Calça | E24: Vermelha | F24: 180
A25: 43483 | B25: N6D6K6A5 | C25: Pablo | D25: Calça | E25: Vermelha | F25: 180
A26: 43484 | B26: J9V2Q2O1 | C26: Natália | D26: Calça | E26: Amarela | F26: 180
A27: 43484 | B27: C1L5T9Q8 | C27: Kelly | D27: Calça | E27: Branca | F27: 180
A28: 43486 | B28: K3O5X7I6 | C28: Rafaela | D28: Calça | E28: Verde | F28: 180
A29: 43487 | B29: D7K6P1C9 | C29: Fábio | D29: Calça | E29: Azul | F29: 180
A30: 43487 | B30: Q8V4L9A3 | C30: Helena | D30: Calça | E30: Branca | F30: 180
... A3500: 43828 | B3500: Q8E8G6R9 | C3500: Bernardo | D3500: Chinelo | E3500: Azul | F3500: 30

Sheet Perguntas 27 a 30 - Vendas
C2: Faça um TOP 5 dos funcionários que mais venderam no ano. | I2: Responda as questões abaixo sem o uso de fórmulas:
C4: Ranking | D4: Funcionário | E4: Total Vendido | I4: Quantas vendas foram realizadas no ano de 2019?
C5: 1 | D5: {=INDEX('Base Vendas'!K:K, MATCH(LARGE('Base Vendas'!$L:$L,$C5), 'Base Vendas'!$L:$L,0),0)} -> Pablo | E5: =_xlfn.XLOOKUP(LARGE('Base Vendas'!$L:$L,C5), 'Base Vendas'!$L:$L, 'Base Vendas'!$L:$L,,0) -> 24480 | I5: 3499
C6: 2 | D6: {=INDEX('Base Vendas'!K:K, MATCH(LARGE('Base Vendas'!$L:$L,$C6), 'Base Vendas'!$L:$L,0),0)} -> Helena | E6: =_xlfn.XLOOKUP(LARGE('Base Vendas'!$L:$L,C6), 'Base Vendas'!$L:$L, 'Base Vendas'!$L:$L,,0) -> 24290
C7: 3 | D7: {=INDEX('Base Vendas'!K:K, MATCH(LARGE('Base Vendas'!$L:$L,$C7), 'Base Vendas'!$L:$L,0),0)} -> Bernardo | E7: =_xlfn.XLOOKUP(LARGE('Base Vendas'!$L:$L,C7), 'Base Vendas'!$L:$L, 'Base Vendas'!$L:$L,,0) -> 23860 | I7: Quantas "Camisetas" foram vendidas em 2019?
C8: 4 | D8: {=INDEX('Base Vendas'!K:K, MATCH(LARGE('Base Vendas'!$L:$L,$C8), 'Base Vendas'!$L:$L,0),0)} -> Iago | E8: =_xlfn.XLOOKUP(LARGE('Base Vendas'!$L:$L,C8), 'Base Vendas'!$L:$L, 'Base Vendas'!$L:$L,,0) -> 23550 | I8: 440
C9: 5 | D9: {=INDEX('Base Vendas'!K:K, MATCH(LARGE('Base Vendas'!$L:$L,$C9), 'Base Vendas'!$L:$L,0),0)} -> Natália | E9: =_xlfn.XLOOKUP(LARGE('Base Vendas'!$L:$L,C9), 'Base Vendas'!$L:$L, 'Base Vendas'!$L:$L,,0) -> 23380
I10: Quantos "Bonés" da marca "Azul" foram vendidos em todo o período?
I11: 73
C12: Faça um TOP 3 dos produtos mais vendidos no ano pela marca "Verde"
C14: Ranking | D14: Produto | E14: Total Vendido | I14: Responda as questões abaixo usando fórmulas:
C15: 1 | D15: =_xlfn.XLOOKUP(E15,'Base Vendas'!O:O,'Base Vendas'!N:N,,0) -> Calça | E15: =LARGE('Base Vendas'!O:O,'Perguntas 27 a 30 - Vendas'!C15) -> 15120
C16: 2 | D16: =_xlfn.XLOOKUP(E16,'Base Vendas'!O:O,'Base Vendas'!N:N,,0) -> Bermuda | E16: =LARGE('Base Vendas'!O:O,'Perguntas 27 a 30 - Vendas'!C16) -> 14550 | I16: Qual é a soma do valor de venda da marca "Amarela"?
C17: 3 | D17: =_xlfn.XLOOKUP(E17,'Base Vendas'!O:O,'Base Vendas'!N:N,,0) -> Camisa | E17: =LARGE('Base Vendas'!O:O,'Perguntas 27 a 30 - Vendas'!C17) -> 14240 | I17: =SUMIFS('Base Vendas'!F:F,'Base Vendas'!E:E, "Amarela") -> 71260
I19: Qual é o valor total vendido de "Saias" da marca "Vermelha"?
I20: =SUMIFS('Base Vendas'!F:F, 'Base Vendas'!D:D, "Saia", 'Base Vendas'!E:E, "Vermelha") -> 6800
I22: Quem foi o funcionário que realizou a venda de código "N5E6Q9S3"?
I23: {=INDEX('Base Vendas'!C:C, MATCH("N5E6Q9S3", 'Base Vendas'!B:B, 0), 0)} -> Pablo
